Workbook

Sheet sheet1需求
A1: 序号 | B1: 系统 | C1: 需求 | D1: 需求详述 | E1: 需求图片说明 | F1: 需求进展 | G1: 紧急程度 | H1: 提出人 | I1: IT负责人 | J1: 提出日期 | K1: 完成日期 | L1: 问题状态 | M1: 备注
A2: 1 | B2: 测算系统&WMS系统 | C2: “其他库区库存”汇总 | D2: 在“存量模块”下新建“WMS库房分配表”详见sheet4，根据WMS库房分配表，判断F列是否为其他库区，判断为“是”，则从WMS里抓取库存数据，抓取逻辑及库存放置地点、页面展示字段同“各库区库存表”一样。“各库区库存表”和“其他库区”导出EXCEL命名尾缀需要根据导出日期做对应的命名，例如今日导出，则文件后缀自动命名今日导出日期2024****。 | E2: 详见shee2 | H2: 李美丽 | I2: 杜德天
A3: 2 | B3: 测算系统&WMS系统 | C3: 400派件补库单 | D3: 在“数据审视”下新建“400派件补库单”功能模块，需求字段及处理逻辑说明详见Sheet3 | E3: 详见Sheet3 | H3: 李美丽 | I3: 杜德天
A4: 2 | B4: 测算系统&WMS系统 | C4: 项目发料单

Sheet sheet2-需求描述截图
A1: 序号1
A3: 物料代码 | B3: 捆绑料号 | C3: 物料描述 | D3: 供应商PN码 | E3: 名称 | F3: 福州兴业银行 | G3: 北京建设银行 | H3: 上海人行清算
A4: 302-000000 | B4: 99-000712 | C4: S主板 S920X00-7260 2*920,64C | D4: 03027WNA | E4: 主板 | F4: 0 | G4: 0 | H4: 0
A5: 302-000001 | B5: 99-000711 | C5: S主板S920X00-2*5250(48C@2.6) | D5: 03027WNC | E5: 主板 | F5: 0 | G5: 1 | H5: 0
A6: 302-000002 | B6: 99-000665 | C6: S主板 S920X00-5230 2*920,32C | D6: 03027WNP | E6: 主板 | F6: 0 | G6: 0 | H6: 0
A8: 序号2
A51: 根据高级查询条件，导出明细方法

Sheet 计算维修收发货报表1
A1: CRM工单号 | B1: 报修时间 | C1: 换件单号 | D1: 工单状态 | E1: 报修物料号 | F1: 备件名称 | G1: 备件物料号 | H1: 备件SN | I1: 备件派件时间 | J1: 备件签收时间 | K1: 派件方式 | L1: 是否超时 | M1: 派件费用 | N1: 备件出库地 | O1: 故障现象（客户报） | P1: 返回件类型 | Q1: 返回件物料号 | R1: 返回件SN | S1: 旧件返回快递 | T1: 旧件收件时间 | U1: 故障件交接测试时间 | V1: 故障现象（实测） | W1: 测试结论 | X1: 复测处理完成时间 | Y1: 供应商 | Z1: 返厂快递 | AA1: 返厂时间 | AB1: TAT | AC1: 修复件返回快递 | AD1: 修复件收件时间 | AE1: 修复件物料号 | AF1: 修复件SN | AG1: 修复件入库时间 | AH1: 类别 | AI1: 机型 | AJ1: SLA | AK1: 服务开始时间 | AL1: 整机SN | AM1: 项目名称 | AN1: CRM立项编号 | AO1: 客户信息 | AP1: 负责人 | AQ1: 旧件返回对接人 | AR1: 备注 | AS1: 维修单号 | AT1: 特殊状态 | AU1: 处理方式 | AV1: 产品使用月份 | AW1: 捆绑料号（美丽自己手动加字段）
A2: 20240101018042 | B2: 45292 | C2: 600000004792.0 | D2: 完结 | E2: 302-000752 | F2: PCSSD | G2: 302-000752 | H2: YMA1256JA2210400896 | I2: 45292 | J2: 45293 | K2: SF1519155161720 | L2: 否 | M2: 0.0 | N2: 武汉 | O2: 开机黑屏，交叉测试显示器是正常的，故障在主机侧 | Q2: 302-000752 | R2: YMA1256JA2119600E7H | S2: SF1425708746378 | T2: 45296 | V2: 王义实测：抓不到硬盘。开机是显示：“无启动设备，按enter键继续”（其他硬盘都正常进系统。），然后15秒后掉电。 | W2: 故障件确认故障 | X2: 45321 | Y2: 中电港 | Z2: SF1519154094730 | AA2: 45394 | AB2: 26 | AC2: 1258204740835 | AD2: 45420 | AE2: 302-000752 | AF2: YMA1256JA2119600E7H | AG2: 45422 | AH2: 鲲泰PC产品 | AI2: D526-2台式机D2000-8G-256G-2G-13L-MK(无显示器) | AJ2: 青松台式机3年质保1年上门(5x9x2D) | AK2: 45153 | AL2: A220980003751201274 | AM2: 渠道PC分销（销售员：邱雨晴） | AN2: 渠道项目，无CRM编号 | AO2: 江西省南昌市东湖区二七北路527 | AP2: liufengab | AR2: 1/31反馈因为清除标准暂未出来，雷哥在找二线测试看有无故障，如果有故障麻烦单独摘处理并且写明对应的故障。如果没有故障就需要理清理数据、查看时间等。 | AS2: 700000003860.0 | AV2: 139 | AW2: =VLOOKUP(G2,[1]备料总表!$B:$GB,182,0) -> #N/A
A3: 20240101018043 | B3: 45292 | C3: 600000004793.0 | D3: 完结 | E3: 302-000756 | F3: 网卡 | G3: 302-000756 | H3: 2102570045N0P4102174 | I3: 45292 | J3: 45293 | K3: SF1519155161739 | L3: 否 | M3: 0.0 | N3: 武汉 | O3: 网卡无法识别 | Q3: 302-000756 | R3: 2102570045D9P9100865 | S3: SF1458291674483 | T3: 45300 | V3: 有物理损坏，不显示端口连接 | W3: 故障件确认故障 | X3: 45317 | Y3: 华为 | Z3: SF1527634331401 | AA3: 45317 | AB3: 34 | AC3: 华为自运 | AD3: 45351 | AE3: 302-000756 | AF3: 2102570045N0P7104872 | AG3: 45352 | AH3: 鲲泰服务器产品 | AI3: KunTai R622 服务器 | AJ3: 例外服务 | AK3: 45293 | AL3: KS004410NA06000065 | AM3: 中国移动2021年至2022年PC服务器集中采购补充采购第二期-FZ项目 | AN3: XTBYYS230810096 | AO3: 江西省南昌市保税区保税六路江西移动临空机房A1楼201机房 | AP3: liufengab | AS3: 700000003925.0 | AV3: 0 | AW3: =VLOOKUP(G3,[1]备料总表!$B:$GB,182,0) -> 99-000756
A4: 20240101018043 | B4: 45292 | C4: 600000004794.0 | D4: 完结 | E4: 302-001797 | F4: 光模块 | G4: 302-001797 | H4: MA2301142696 | I4: 45292 | J4: 45293 | K4: SF1519155161739 | L4: 否 | M4: 0.0 | N4: 武汉 | O4: 网卡无法识别 | Q4: 302-001797 | R4: MA2308161468 | S4: SF1458291674483 | T4: 45300 | V4: OK | W4: 故障件未复现故障 | X4: 45364 | AB4: 0 | AH4: 鲲泰服务器产品 | AI4: KunTai R622 服务器 | AJ4: 例外服务 | AK4: 45293 | AL4: KS004410NA06000065 | AM4: 中国移动2021年至2022年PC服务器集中采购补充采购第二期-FZ项目 | AN4: XTBYYS230810096 | AO4: 江西省南昌市保税区保税六路江西移动临空机房A1楼201机房 | AP4: liufengab | AS4: 700000003926.0 | AV4: 0 | AW4: =VLOOKUP(G4,[1]备料总表!$B:$GB,182,0) -> 99-000381
A5: 20240101018043 | B5: 45292 | C5: 600000004795.0 | D5: 完结 | E5: 302-001797 | F5: 光模块 | G5: 302-001797 | H5: MA2301142608 | I5: 45292 | J5: 45293 | K5: SF1519155161739 | L5: 否 | M5: 0.0 | N5: 武汉 | O5: 网卡无法识别 | Q5: 302-001797 | R5: MA2308060916 | S5: SF1458291674483 | T5: 45300 | V5: OK | W5: 故障件未复现故障 | X5: 45364 | AB5: 0 | AH5: 鲲泰服务器产品 | AI5: KunTai R622 服务器 | AJ5: 例外服务 | AK5: 45293 | AL5: KS004410NA06000065 | AM5: 中国移动2021年至2022年PC服务器集中采购补充采购第二期-FZ项目 | AN5: XTBYYS230810096 | AO5: 江西省南昌市保税区保税六路江西移动临空机房A1楼201机房 | AP5: liufengab | AS5: 700000003927.0 | AV5: 0 | AW5: =VLOOKUP(G5,[1]备料总表!$B:$GB,182,0) -> 99-000381
A6: 20240101018044 | B6: 45292 | C6: 600000004796.0 | D6: 完结 | E6: 302-000712 | F6: 主板 | G6: 302-001592 | H6: 2103050GHG10P1100003 | I6: 45292 | J6: 45292 | K6: 备件库派送 | L6: 否 | M6: 180.0 | N6: 呼和浩特 | O6: 服务器无法上电，BMC无法登录，电源亮黄灯 | Q6: 302-000712 | R6: 2103050CSV10MC000477 | S6: SF1408849418447 | T6: 45296 | V6: 实测上电后主板无法启动，主板指示灯不亮。 | W6: 故障件确认故障 | X6: 45301 | Y6: 华为 | Z6: SF1521864315183 | AA6: 45302 | AB6: 21 | AC6: 华为自运 | AD6: 45323 | AE6: 302-002030 | AF6: 2103050JKT10Q1100050 | AG6: 45340 | AH6: 鲲泰服务器产品 | AI6: KunTai R722 服务器 | AJ6: 2U3年标准+及基础硬件安装 | AK6: 44567 | AL6: KS001410LC28000161 | AM6: 2021年中国联通IT云呼和DC国产化资源池一期工 程_集团总部单项工程 | AN6: XTBYYS211019094 | AO6: 呼和浩特北二环联通云基地 | AP6: liufengab | AS6: 700000003861.0 | AV6: 725 | AW6: =VLOOKUP(G6,[1]备料总表!$B:$GB,182,0) -> 99-000712
A7: 20240101018044 | B7: 45292 | C7: 无 | D7: 完结 | E7: 302-000448 | F7: 电源 | G7: 302-000448 | H7: 2102312PEU10M3014039 | I7: 45292 | J7: 45292 | K7: 备件库派送 | L7: 否 | M7: 100.0 | N7: 呼和浩特 | O7: 服务器无法上电，BMC无法登录，电源亮黄灯 | Q7: 302-000448 | R7: 备件未使用 | S7: / | V7: ok | W7: 未使用备件测试正常 | Y7: / | Z7: / | AB7: 0 | AC7: / | AE7: / | AF7: / | AH7: 鲲泰服务器产品 | AI7: KunTai R722 服务器 | AJ7: 2U3年标准+及基础硬件安装 | AK7: 44567 | AL7: KS001410LC28000161 | AM7: 2021年中国联通IT云呼和DC国产化资源池一期工 程_集团总部单项工程 | AN7: XTBYYS211019094 | AO7: 呼和浩特北二环联通云基地 | AP7: liufengab | AV7: 725 | AW7: =VLOOKUP(G7,[1]备料总表!$B:$GB,182,0) -> 99-000448
A8: 20240101018044 | B8: 45292 | C8: 无 | D8: 完结 | E8: 302-000143 | F8: 机箱(硬盘背板) | G8: 302-000143 | H8: 2102312VXN10LA000159 | I8: 45292 | J8: 45292 | K8: 备件库派送 | L8: 否 | M8: 0.0 | N8: 呼和浩特 | O8: 服务器无法上电，BMC无法登录，电源亮黄灯 | Q8: 302-000143 | R8: 备件未使用 | S8: / | V8: ok | W8: 未使用备件测试正常 | Y8: / | Z8: / | AB8: 0 | AC8: / | AE8: / | AF8: / | AH8: 鲲泰服务器产品 | AI8: KunTai R722 服务器 | AJ8: 2U3年标准+及基础硬件安装 | AK8: 44567 | AL8: KS001410LC28000161 | AM8: 2021年中国联通IT云呼和DC国产化资源池一期工 程_集团总部单项工程 | AN8: XTBYYS211019094 | AO8: 呼和浩特北二环联通云基地 | AP8: liufengab | AV8: 725 | AW8: =VLOOKUP(G8,[1]备料总表!$B:$GB,182,0) -> 99-000143
A9: 20240101018044 | B9: 45292 | C9: 无 | D9: 完结 | E9: 302-000147 | F9: Riser卡 | G9: 302-000147 | H9: 2102312VXU10L9000462 | I9: 45292 | J9: 45292 | K9: 备件库派送 | L9: 否 | M9: 0.0 | N9: 呼和浩特 | O9: 服务器无法上电，BMC无法登录，电源亮黄灯 | Q9: 302-000147 | R9: 备件未使用 | S9: / | V9: ok | W9: 未使用备件测试正常 | Y9: / | Z9: / | AB9: 0 | AC9: / | AE9: / | AF9: / | AH9: 鲲泰服务器产品 | AI9: KunTai R722 服务器 | AJ9: 2U3年标准+及基础硬件安装 | AK9: 44567 | AL9: KS001410LC28000161 | AM9: 2021年中国联通IT云呼和DC国产化资源池一期工 程_集团总部单项工程 | AN9: XTBYYS211019094 | AO9: 呼和浩特北二环联通云基地 | AP9: liufengab | AV9: 725 | AW9: =VLOOKUP(G9,[1]备料总表!$B:$GB,182,0) -> 99-000147
A10: 20240101018044 | B10: 45292 | C10: 无 | D10: 完结 | E10: 302-000985 | F10: 内存 | G10: 302-000985 | H10: 80AD0120448476FDB9 | I10: 45292 | J10: 45292 | K10: 备件库派送 | L10: 否 | M10: 0.0 | N10: 呼和浩特 | O10: 服务器无法上电，BMC无法登录，电源亮黄灯 | Q10: 302-000985 | R10: 备件未使用 | S10: / | V10: ok | W10: 未使用备件测试正常 | Y10: / | Z10: / | AB10: 0 | AC10: / | AE10: / | AF10: / | AH10: 鲲泰服务器产品 | AI10: KunTai R722 服务器 | AJ10: 2U3年标准+及基础硬件安装 | AK10: 44567 | AL10: KS001410LC28000161 | AM10: 2021年中国联通IT云呼和DC国产化资源池一期工 程_集团总部单项工程 | AN10: XTBYYS211019094 | AO10: 呼和浩特北二环联通云基地 | AP10: liufengab | AV10: 725 | AW10: =VLOOKUP(G10,[1]备料总表!$B:$GB,182,0) -> 0
A11: 20240101018047 | B11: 45292 | C11: 600000004797.0 | D11: 完结 | E11: 302-000985 | F11: 内存 | G11: 302-000985 | H11: 80AD0120448476B9C2 | I11: 45292 | J11: 45292 | K11: 现场保障备件 | L11: 否 | M11: 0.0 | N11: 呼和浩特联通云基地 | O11: 服务器无法上电，BMC无法登录，电源亮黄灯 | Q11: 302-000985 | R11: 80AD01204444277C8A | S11: SF1401859935806 | T11: 45300 | V11: ok | W11: 故障件未复现故障 | X11: 45321 | AB11: 0 | AH11: 鲲泰服务器产品 | AI11: KunTai R722 服务器 | AJ11: 2U3年标准+及基础硬件安装 | AK11: 44567 | AL11: KS001410LC28000161 | AM11: 2021年中国联通IT云呼和DC国产化资源池一期工 程_集团总部单项工程 | AN11: XTBYYS211019094 | AO11: 呼和浩特北二环联通云基地 | AP11: liufengab | AS11: 700000003928.0 | AV11: 725 | AW11: =VLOOKUP(G11,[1]备料总表!$B:$GB,182,0) -> 0
A12: 20240102018048 | B12: 45293 | C12: 600000004798.0 | D12: 完结 | E12: 302-001672 | F12: HDD | G12: 302-001816 | H12: 2102540165N0PB103945 | I12: 45293 | J12: 45293 | K12: 备件库派送 | L12: 否 | M12: 100.0 | N12: 汕头 | O12: BMC查到到DISK2存在外部配置，告警码0x02000029 | Q12: 302-001672 | R12: 32N0A62MFDEH | S12: SF1404869847747 | T12: 45300 | V12: 王义实测：The disk Disk8 state is abnormal. 0x02000027 和The disk Disk8 is missing. 0x0200002D | W12: 故障件确认故障 | X12: 45321 | Y12: 喜和 | Z12: SF1527634331923 | AA12: 45348 | AB12: 35 | AC12: SF1676266240203 | AD12: 45383 | AE12: 302-001672 | AF12: 14P0A03DFDEH | AG12: 45384 | AH12: 鲲泰服务器产品 | AI12: KunTai 622 服务器 | AJ12: 2U3年标准+及基础硬件安装 | AK12: 44789 | AL12: KS004410M428000143 | AM12: 移动服务器集采落地-汕头-汕头落地项目 | AN12: XTBYYS220225157 | AO12: 广东省汕头市濠江区马窖街道南山湾工业园移动数据中心 | AP12: liufengab | AS12: 700000003929.0 | AV12: 504 | AW12: =VLOOKUP(G12,[1]备料总表!$B:$GB,182,0) -> 99-001043
A13: 20240102018049 | B13: 45293 | C13: 600000004799.0 | D13: 完结 | E13: 302-001716 | F13: 内存 | G13: 302-001716 | H13: 2102510058N0N4110531 | I13: 45293 | J13: 45293 | K13: 备件库派送 | L13: 否 | M13: 0.0 | N13: 汕头 | O13: BMC查到到DIMM040存在UCE报错，告警码0x01000017 | Q13: 302-001716 | R13: 210251005810N4103344 | S13: SF1445584577067 | T13: 45321 | V13: 实测ok | W13: 故障件未复现故障 | X13: 45323 | AB13: 0 | AH13: 鲲泰服务器产品 | AI13: KunTai 622 服务器 | AJ13: 2U3年标准+及基础硬件安装 | AK13: 44789 | AL13: KS004410M430000025 | AM13: 移动服务器集采落地-汕头-汕头落地项目 | AN13: XTBYYS220225157 | AO13: 广东省汕头市濠江区马窖街道南山湾工业园移动数据中心 | AP13: liufengab | AS13: 700000004208.0 | AV13: 504 | AW13: =VLOOKUP(G13,[1]备料总表!$B:$GB,182,0) -> 99-001716
A14: 20240102018058 | B14: 45293 | C14: 600000004800.0 | D14: 完结 | E14: 302-000759 | F14: PC主板 | G14: 302-000759 | H14: 026WTBBBM2003994 | I14: 45294 | J14: 45294 | K14: 备件库派送 | L14: 否 | M14: 0.0 | N14: 厦门 | O14: 开机后频繁死机，同时主机开关键有点按不动 | Q14: 302-000759 | R14: 026WTBBBM2002807 | S14: SF1526633942117 | T14: 45300 | V14: ok | W14: 故障件未复现故障 | X14: 45321 | AB14: 0 | AH14: 鲲泰PC产品 | AI14: KunTai D220 台式机 | AJ14: 台式机4年标准+及介质保留 | AK14: 44418 | AL14: KD000210L715000082 | AM14: 厦门市某局二期台式机采购 | AN14: FJFJ210128248 | AO14: 厦门市同安区祥平西路1号自然资源规划局同安分局 | AP14: liufengab | AS14: 700000003930.0 | AV14: 875 | AW14: =VLOOKUP(G14,[1]备料总表!$B:$GB,182,0) -> #N/A
A15: 20240102018058 | B15: 45293 | C15: 600000004801.0 | D15: 完结 | E15: 302-000909 | F15: PC机箱 | G15: 302-000909 | H15: 备件未使用 | I15: 45294 | J15: 45294 | K15: 备件库派送 | L15: 否 | M15: 0.0 | N15: 厦门 | O15: 开机后频繁死机，同时主机开关键有点按不动 | Q15: 302-000909 | R15: 备件未使用 | S15: / | V15: / | W15: 未使用备件测试正常 | Y15: / | Z15: / | AB15: 0 | AC15: / | AE15: / | AF15: / | AH15: 鲲泰PC产品 | AI15: KunTai D220 台式机 | AJ15: 台式机4年标准+及介质保留 | AK15: 44418 | AL15: KD000210L715000082 | AM15: 厦门市某局二期台式机采购 | AN15: FJFJ210128248 | AO15: 厦门市同安区祥平西路1号自然资源规划局同安分局 | AP15: liufengab | AV15: 875 | AW15: =VLOOKUP(G15,[1]备料总表!$B:$GB,182,0) -> #N/A
A16: 20240102018060 | B16: 45293 | C16: 600000004802.0 | D16: 完结 | E16: 301-000012 | F16: PC键鼠套装 | G16: 301-000012 | H16: MK000410M706003987 | I16: 45293 | J16: 45293 | K16: 备件库派送 | L16: 否 | M16: 0.0 | N16: 厦门 | O16: 2个键盘空格键失灵，会一直输入 | Q16: 301-000012 | R16: MK000410M706005409 | S16: SF1459081591455 | T16: 45296 | V16: 王义实测：会一直输入 | W16: 故障件确认故障 | X16: 45321 | Y16: 兴威特 | Z16: SF1527634331544 | AA16: 45342 | AB16: 78 | AC16: SF1525609231507 | AD16: 45420 | AE16: 301-000012 | AF16: MK000410Q302000008 | AG16: 45420 | AH16: 鲲泰PC产品 | AI16: KunTai D526-2 台式机 | AJ16: 台式机5年上门维保(7x24xND)及介质保留 | AK16: 45246 | AL16: KD000910N801000051 | AM16: 海沧区教育系统XC终端替换 | AN16: HNQ230506029 | AO16: 厦门双十中学海沧附属学校小学部门口快递柜 | AP16: liufengab | AS16: 700000003862.0 | AV16: 47 | AW16: =VLOOKUP(G16,[1]备料总表!$B:$GB,182,0) -> #N/A
A17: 20240102018060 | B17: 45293 | C17: 600000004803.0 | D17: 完结 | E17: 301-000012 | F17: PC键鼠套装 | G17: 301-000012 | H17: MK000410M706003985 | I17: 45293 | J17: 45293 | K17: 备件库派送 | L17: 否 | M17: 0.0 | N17: 厦门 | O17: 2个键盘空格键失灵，会一直输入 | Q17: 301-000012 | R17: MK000410M706005415 | S17: SF1459081591455 | T17: 45296 | V17: ok | W17: 故障件未复现故障 | X17: 45321 | AB17: 0 | AH17: 鲲泰PC产品 | AI17: KunTai D526-2 台式机 | AJ17: 台式机5年上门维保(7x24xND)及介质保留 | AK17: 45246 | AL17: KD000910N801000051 | AM17: 海沧区教育系统XC终端替换 | AN17: HNQ230506029 | AO17: 厦门双十中学海沧附属学校小学部门口快递柜 | AP17: liufengab | AS17: 700000003863.0 | AV17: 47 | AW17: =VLOOKUP(G17,[1]备料总表!$B:$GB,182,0) -> #N/A
A18: 20240102018061 | B18: 45293 | C18: 600000004804.0 | D18: 完结 | E18: 302-000759 | F18: PC主板 | G18: 302-000759 | H18: 026WTBBBM2003892 | I18: 45294 | J18: 45294 | K18: 备件库派送 | L18: 否 | M18: 0.0 | N18: 厦门 | O18: 频繁死机，键鼠没有反应 | Q18: 302-000759 | R18: 026WTBBBM2002428 | S18: SF1526633942117 | T18: 45300 | V18: ok | W18: 故障件未复现故障 | X18: 45321 | AB18: 0 | AH18: 鲲泰PC产品 | AI18: KunTai D220 台式机 | AJ18: 台式机4年标准+及介质保留 | AK18: 44377 | AL18: KD000210L615000092 | AM18: 厦门市某局二期台式机采购 | AN18: FJFJ210128248 | AO18: 厦门市自然资源规划局集美分局执法科 | AP18: liufengab | AS18: 700000003931.0 | AV18: 916 | AW18: =VLOOKUP(G18,[1]备料总表!$B:$GB,182,0) -> #N/A
A19: 20240102018062 | B19: 45293 | C19: 600000004805.0 | D19: 完结 | E19: 302-000756 | F19: 网卡 | G19: 302-000756 | H19: 2102570045N0P4101362 | I19: 45293 | J19: 45293 | K19: 备件库派送 | L19: 否 | M19: 100.0 | N19: 杭州 | O19: 前期已报故障（工单号：20231221017846），已派光模块处理，工程师表示光模块无法拔出 | Q19: 302-000756 | R19: 备件未使用 | S19: SF1456781101464 | T19: 45296 | W19: 未使用备件测试正常 | X19: 45301 | Y19: / | Z19: / | AB19: 0 | AC19: / | AE19: / | AF19: / | AH19: 鲲泰服务器产品 | AI19: KunTai R2280 服务器 | AJ19: 2U5年标准+及介质保留和基础硬件安装 | AK19: 45252 | AL19: KS000310N803000050 | AM19: 数智绍芯"工程配套硬件设备（第一批）服务器采购项目 | AN19: XTBJR230714167 | AO19: 浙江省绍兴市越城区中国联通绍兴分公司(延安东路) 金明杰 18057505155 | AP19: liufengab | AS19: 700000003866.0 | AV19: 41 | AW19: =VLOOKUP(G19,[1]备料总表!$B:$GB,182,0) -> 99-000756
A20: 20240102018062 | B20: 45293 | C20: 600000004806.0 | D20: 完结 | E20: 302-000756 | F20: 网卡 | G20: 302-000756 | H20: 2102570045N0P6114980 | I20: 45293 | J20: 45293 | K20: 备件库派送 | L20: 否 | M20: 0.0 | N20: 杭州 | O20: 前期已报故障（工单号：20231221017846），已派光模块处理，工程师表示光模块无法拔出 | Q20: 302-000756 | R20: 备件未使用 | S20: SF1456781101464 | T20: 45296 | W20: 未使用备件测试正常 | X20: 45301 | Y20: / | Z20: / | AB20: 0 | AC20: / | AE20: / | AF20: / | AH20: 鲲泰服务器产品 | AI20: KunTai R2280 服务器 | AJ20: 2U5年标准+及介质保留和基础硬件安装 | AK20: 45252 | AL20: KS000310N803000050 | AM20: 数智绍芯"工程配套硬件设备（第一批）服务器采购项目 | AN20: XTBJR230714167 | AO20: 浙江省绍兴市越城区中国联通绍兴分公司(延安东路) 金明杰 18057505155 | AP20: liufengab | AS20: 700000003867.0 | AV20: 41 | AW20: =VLOOKUP(G20,[1]备料总表!$B:$GB,182,0) -> 99-000756
A21: 20240102018062 | B21: 45293 | C21: 600000004807.0 | D21: 完结 | E21: 302-002431 | F21: 光模块 | G21: 302-002431 | H21: 2306051011.0 | I21: 45293 | J21: 45293 | K21: 备件库派送 | L21: 否 | M21: 0.0 | N21: 杭州 | O21: 前期已报故障（工单号：20231221017846），已派光模块处理，工程师表示光模块无法拔出 | Q21: 302-002431 | R21: 备件未使用 | S21: SF1456781101464 | T21: 45296 | W21: 未使用备件测试正常 | X21: 45301 | Y21: / | Z21: / | AB21: 0 | AC21: / | AE21: / | AF21: / | AH21: 鲲泰服务器产品 | AI21: KunTai R2280 服务器 | AJ21: 2U5年标准+及介质保留和基础硬件安装 | AK21: 45252 | AL21: KS000310N803000050 | AM21: 数智绍芯"工程配套硬件设备（第一批）服务器采购项目 | AN21: XTBJR230714167 | AO21: 浙江省绍兴市越城区中国联通绍兴分公司(延安东路) 金明杰 18057505155 | AP21: liufengab | AS21: 700000003868.0 | AV21: 41 | AW21: =VLOOKUP(G21,[1]备料总表!$B:$GB,182,0) -> 99-000381
A22: 20240102018062 | B22: 45293 | C22: 600000004808.0 | D22: 完结 | E22: 302-002431 | F22: 光模块 | G22: 302-002431 | H22: 2305123300.0 | I22: 45293 | J22: 45293 | K22: 备件库派送 | L22: 否 | M22: 0.0 | N22: 杭州 | O22: 前期已报故障（工单号：20231221017846），已派光模块处理，工程师表示光模块无法拔出 | Q22: 302-002431 | R22: 备件未使用 | S22: SF1456781101464 | T22: 45296 | W22: 未使用备件测试正常 | X22: 45301 | Y22: / | Z22: / | AB22: 0 | AC22: / | AE22: / | AF22: / | AH22: 鲲泰服务器产品 | AI22: KunTai R2280 服务器 | AJ22: 2U5年标准+及介质保留和基础硬件安装 | AK22: 45252 | AL22: KS000310N803000050 | AM22: 数智绍芯"工程配套硬件设备（第一批）服务器采购项目 | AN22: XTBJR230714167 | AO22: 浙江省绍兴市越城区中国联通绍兴分公司(延安东路) 金明杰 18057505155 | AP22: liufengab | AS22: 700000003869.0 | AV22: 41 | AW22: =VLOOKUP(G22,[1]备料总表!$B:$GB,182,0) -> 99-000381
A23: 20240102018063 | B23: 45293 | C23: 600000004809.0 | D23: 完结 | E23: 301-000000 | F23: PC显示器 | G23: 301-000021 | H23: XS001210NA18001254 | I23: 45294 | J23: 45294 | K23: 备件库派送 | L23: 否 | M23: 0.0 | N23: 厦门 | O23: 显示器黑屏 | Q23: 301-000000 | R23: XS000210L328000649 | S23: SF1526633941926 | T23: 45300 | V23: 王义实测：黑屏、不显示 | W23: 故障件确认故障 | X23: 45321 | Y23: 完美 | Z23: SF1527634331474 | AA23: 45341 | AB23: 42 | AD23: 45383 | AE23: 301-000000 | AF23: XS000210L328000649 | AG23: 45384 | AH23: 鲲泰PC产品 | AI23: KunTai D220 台式机 | AJ23: 台式机4年标准+及介质保留 | AK23: 44418 | AL23: KD000210L722000273 | AM23: 厦门市某局二期台式机采购 | AN23: FJFJ210128248 | AO23: 福建省厦门市思明区湖滨中路518号 | AP23: liufengab | AS23: 700000003932.0 | AV23: 875 | AW23: =VLOOKUP(G23,[1]备料总表!$B:$GB,182,0) -> 77-000021
A24: 20240102018064 | B24: 45293 | C24: 600000004810.0 | D24: 完结 | E24: 302-001271 | F24: PC主板 | G24: 302-001271 | H24: 2102313RPSZENB011521 | I24: 45295 | J24: 45295 | K24: 备件库派送 | L24: 否 | M24: 0.0 | N24: 厦门 | O24: 开机开机卡在LOGO界面无法进入系统，会黑屏重启。 | Q24: 302-001271 | R24: 2102313RPS6RMB054397 | S24: SF1526633942117 | T24: 45300 | V24: 王义实测：无法从u盘引导。 | W24: 故障件确认故障 | X24: 45321 | Y24: 华为 | Z24: SF1527634331410 | AA24: 45322 | AB24: 29 | AC24: 11709886.0 | AD24: 45351 | AE24: 302-001271 | AF24: 2102313RPSYPMA013151 | AG24: 45352 | AH24: 鲲泰PC产品 | AI24: KunTai D526-2 台式机 | AJ24: 台式机4年上门标准+(7x24xND)及介质保留 | AK24: 45273 | AL24: KD000910N827000326 | AM24: 万翔PC采购项目（第三批） | AN24: FJ230815132 | AO24: 厦门市思明区新华路45-47号公安局一号楼701 | AP24: liufengab | AS24: 700000003933.0 | AV24: 20 | AW24: =VLOOKUP(G24,[1]备料总表!$B:$GB,182,0) -> #N/A
A25: 20240102018064 | B25: 45293 | C25: 600000004811.0 | D25: 完结 | E25: 302-002074 | F25: PCSSD | G25: 302-002074 | H25: 备件未使用 | I25: 45295 | J25: 45295 | K25: 备件库派送 | L25: 否 | M25: 0.0 | N25: 厦门 | O25: 开机开机卡在LOGO界面无法进入系统，会黑屏重启。 | Q25: 302-002074 | R25: 备件未使用 | S25: / | V25: / | W25: 未使用备件测试正常 | Y25: / | Z25: / | AB25: 0 | AC25: / | AE25: / | AF25: / | AH25: 鲲泰PC产品 | AI25: KunTai D526-2 台式机 | AJ25: 台式机4年上门标准+(7x24xND)及介质保留 | AK25: 45273 | AL25: KD000910N827000326 | AM25: 万翔PC采购项目（第三批） | AN25: FJ230815132 | AO25: 厦门市思明区新华路45-47号公安局一号楼701 | AP25: liufengab | AV25: 20 | AW25: =VLOOKUP(G25,[1]备料总表!$B:$GB,182,0) -> #N/A
A26: 20240102018066 | B26: 45293 | C26: 600000004812.0 | D26: 完结 | E26: 302-000759 | F26: PC主板 | G26: 302-000759 | H26: 未派件 | K26: / | L26: / | M26: / | N26: 厦门 | O26: 风扇异响影响办公，电脑能正常运行 | Q26: 302-000759 | R26: 未派件 | S26: / | V26: / | Y26: / | Z26: / | AB26: 0 | AC26: / | AE26: / | AF26: / | AH26: 鲲泰PC产品 | AI26: KunTai D220 | AJ26: 台式机4年标准+及介质保留 | AK26: 44418 | AL26: KD000210L714000005 | AM26: 厦门市某局二期台式机采购 | AO26: 厦门市湖滨中路520档案大楼 | AP26: liufengab | AR26: 1/4厦门库房反馈客户要求取消。 | AV26: 875 | AW26: =VLOOKUP(G26,[1]备料总表!$B:$GB,182,0) -> #N/A
A27: 20240102018066 | B27: 45293 | C27: 600000004813.0 | D27: 完结 | E27: 302-000794 | F27: PC显卡 | G27: 302-000794 | H27: 未派件 | K27: / | L27: / | M27: / | N27: 厦门 | O27: 风扇异响影响办公，电脑能正常运行 | Q27: 302-000794 | R27: 未派件 | S27: / | V27: / | Y27: / | Z27: / | AB27: 0 | AC27: / | AE27: / | AF27: / | AH27: 鲲泰PC产品 | AI27: KunTai D220 | AJ27: 台式机4年标准+及介质保留 | AK27: 44418 | AL27: KD000210L714000005 | AM27: 厦门市某局二期台式机采购 | AO27: 厦门市湖滨中路520档案大楼 | AP27: liufengab | AR27: 1/4厦门库房反馈客户要求取消。 | AV27: 875 | AW27: =VLOOKUP(G27,[1]备料总表!$B:$GB,182,0) -> #N/A
A28: 20240102018067 | B28: 45293 | C28: 600000004814.0 | D28: 完结 | E28: 302-001672 | F28: HDD | G28: 302-001672 | H28: 73V0A068SDEH | I28: 45293 | J28: 45294 | K28: 备件库派送 | L28: 否 | M28: 100.0 | N28: 杭州 | O28: 服务器硬盘故障，disk4状态fail，bmc告警（0x02000007），无法提供日志 | Q28: 302-001672 | R28: X210A1SHFDEH | S28: SF1435140482552 | T28: 45308 | V28: 王义实测：The disk Disk2 is missing. 0x0200002D 和The disk Disk2 state is abnormal. 0x02000027 | W28: 故障件确认故障 | X28: 45321 | Y28: 喜和 | Z28: SF1527634331923 | AA28: 45348 | AB28: 35 | AC28: SF1676266240203 | AD28: 45383 | AE28: 302-001672 | AF28: 14P0A02UFDEH | AG28: 45384 | AH28: 鲲泰服务器产品 | AI28: KunTai R622 服务器 | AJ28: 2U3年标准+及基础硬件安装 | AK28: 45197 | AL28: KS004410N212000211 | AM28: 中国移动2021年至2022年PC服务器集中采购补充采购第二期（IT云四期） | AN28: XTBYYS221206034 | AO28: 浙江省 宁波市 慈溪市 杭州湾新区 滨海六路1208号 浙东信息产业园 | AP28: liufengab | AS28: 700000003970.0 | AV28: 96 | AW28: =VLOOKUP(G28,[1]备料总表!$B:$GB,182,0) -> 99-001043
A29: 20240102018068 | B29: 45293 | C29: 600000004815.0 | D29: 完结 | E29: 302-000288 | F29: 机箱(硬盘背板) | G29: 302-000288 | H29: 2106411207FSP6002256 | I29: 45293 | J29: 45293 | K29: 备件库派送 | L29: 否 | M29: 100.0 | N29: 广州 | O29: 服务器硬盘均无法识别，交叉测试sas线均无效果 | Q29: 302-000288 | R29: 备件未使用 | S29: SF1448851347628 | T29: 45296 | W29: 未使用备件测试正常 | X29: 45301 | Y29: / | Z29: / | AB29: 0 | AC29: / | AE29: / | AF29: / | AH29: 鲲泰服务器产品 | AI29: KunTai R522 服务器 | AJ29: 2U3年金牌+及介质保留 | AK29: 45350 | AL29: KS001310NB18000058 | AM29: 二阶段-ARM包服务器采购 | AN29: XTBGF231012097 | AO29: 广州市黄埔区建业六路10号 | AP29: liufengab | AS29: 700000003870.0 | AV29: 0 | AW29: =VLOOKUP(G29,[1]备料总表!$B:$GB,182,0) -> 88-000288
A30: 20240102018068 | B30: 45293 | C30: 600000004816.0 | D30: 完结 | E30: 302-002613 | F30: RAID卡 | G30: 302-002613 | H30: SKD2901594 | I30: 45293 | J30: 45293 | K30: 备件库派送 | L30: 否 | M30: 0.0 | N30: 广州 | O30: 服务器硬盘均无法识别，交叉测试sas线均无效果 | Q30: 302-002613 | R30: SKD2819260 | S30: SF1448851347628 | T30: 45296 | W30: 故障件未复现故障 | X30: 45301 | Y30: / | Z30: / | AB30: 0 | AC30: / | AE30: / | AF30: / | AH30: 鲲泰服务器产品 | AI30: KunTai R522 服务器 | AJ30: 2U3年金牌+及介质保留 | AK30: 45350 | AL30: KS001310NB18000058 | AM30: 二阶段-ARM包服务器采购 | AN30: XTBGF231012097 | AO30: 广州市黄埔区建业六路10号 | AP30: liufengab | AS30: 700000003871.0 | AV30: 0 | AW30: =VLOOKUP(G30,[1]备料总表!$B:$GB,182,0) -> 99-001705
A31: 20240102018070 | B31: 45293 | C31: 600000004817.0 | D31: 完结 | E31: 302-001644 | F31: 内存 | G31: 302-001644 | H31: 80AD01222814082E3D | I31: 45293 | J31: 45293 | K31: 现场保障备件 | L31: 否 | M31: 0.0 | N31: 廊坊软通 | O31: 内存DIMM100错误率超过阈值，bmc告警代码（0x01000057） | Q31: 302-001644 | R31: 2102510049D9P9161059 | S31: SF1435019329736 | T31: 45296 | V31: ok | W31: 故障件未复现故障 | X31: 45321 | AB31: 0 | AH31: 鲲泰服务器产品 | AI31: KunTai R722 服务器 | AJ31: 2U5年白金+及介质保留和基础硬件安装 | AK31: 45293 | AL31: KS001410NB04000242 | AM31: 邮储鲲鹏服务器423台采购 | AN31: XTBJR231019179 | AO31: 廊坊市安次区龙河移动云计算中心 | AP31: liufengab | AS31: 700000003872.0 | AV31: 0 | AW31: =VLOOKUP(G31,[1]备料总表!$B:$GB,182,0) -> 99-001627
A32: 20240102018069 | B32: 45293 | C32: 600000004818.0 | D32: 完结 | E32: 302-001815 | F32: HDD | G32: 302-001815 | H32: WS23XTT5 | I32: 45293 | J32: 45293 | K32: 备件库派送 | L32: 否 | M32: 100.0 | N32: 北京 | O32: iBMC无当前告警，客户系统平台中显示Disk4槽位硬盘故障，iBMC硬盘日志中显示有扇区错误 | Q32: 302-001815 | R32: 2102540166N0P6105769 | S32: SF1445930057541 | T32: 45308 | V32: 王义实测：The disk Disk11 is missing. 0x0200002D 和The disk Disk11 state is abnormal. 0x02000027 | W32: 故障件确认故障 | X32: 45321 | Y32: 华为 | Z32: 华为自取 | AA32: 45322 | AB32: 19 | AC32: 11709583.0 | AD32: 45341 | AE32: 302-001815 | AF32: 2102540166N0P8100070 | AG32: 45364 | AH32: 鲲泰服务器产品 | AI32: KunTai R722 服务器 | AJ32: 2U3年标准+及基础硬件安装 | AK32: 45293 | AL32: KS001410NA14000023 | AM32: 北京联通zx项目-38台 | AN32: XTBYYS230925280 | AO32: 北京市西城区西长安街11号(西单地铁站C东北口步行250米) 电报大楼 余嘉奥 17532060135 | AP32: liufengab | AS32: 700000003971.0 | AV32: 0 | AW32: =VLOOKUP(G32,[1]备料总表!$B:$GB,182,0) -> 99-001049
A33: 20240102018071 | B33: 45293 | C33: 600000004819.0 | D33: 完结 | E33: 302-001043 | F33: HDD | G33: 302-001241 | H33: 210254016510P5104672 | I33: 45293 | J33: 45293 | K33: 备件库派送 | L33: 否 | M33: 180.0 | N33: 厦门 | O33: iBMC中存在disk2硬盘告警，代码为：0x02000007、0x02000027及0x2C000075，硬盘状态为OFFLINE | Q33: 302-001043 | W33: 介质保留 | AB33: 0 | AH33: 鲲泰服务器产品 | AI33: KunTai R524-4 服务器 | AJ33: 2U3年标准+及介质保留 | AK33: 44894 | AL33: KS003610M825000041 | AM33: 厦门市公安局JZ大数据项目（包一159台） | AN33: HNQZF210826268 | AO33: 福建省厦门市公安局新华路45号 赵先生 17689205907 | AP33: liufengab | AT33: 介质保留 | AV33: 399 | AW33: =VLOOKUP(G33,[1]备料总表!$B:$GB,182,0) -> 99-001043
A34: 20240102018072 | B34: 45293 | C34: 600000004820.0 | D34: 完结 | E34: 302-000405 | F34: PC光驱 | G34: 302-000405 | H34: KAD0CF049958 | I34: 45294 | J34: 45294 | K34: 备件库派送 | L34: 否 | M34: 0.0 | N34: 厦门 | O34: 加电不显且反复重启 | Q34: 302-000405 | R34: M6D0CF104141 | S34: SF1526633942117 | T34: 45300 | V34: 王义实测：光驱无法正常使用。 | W34: 故障件确认故障 | X34: 45293 | Y34: 北神 | Z34: SF1527634331580 | AA34: 45348 | AB34: 35 | AC34: JDV014812538578 | AD34: 45383 | AE34: 302-000405 | AF34: M6D0CF104289 | AG34: 45404 | AH34: 鲲泰PC产品 | AI34: KunTai D526-2 台式机 | AJ34: 台式机4年上门(7x24xND)及介质保留 | AK34: 45338 | AL34: KD000910NB13000040 | AM34: 厦门市公安局XCPC采购 | AN34: FJZF230919197 | AO34: 厦门市思明区新华路45-47号1号楼507 | AP34: liufengab | AR34: 1/31发现PC光驱的前面板的卡扣断裂 | AS34: 700000003934.0 | AV34: 0 | AW34: =VLOOKUP(G34,[1]备料总表!$B:$GB,182,0) -> #N/A
A35: 20240102018074 | B35: 45293 | C35: 600000004821.0 | D35: 完结 | E35: 302-000759 | F35: PC主板 | G35: 302-000759 | H35: 备件未使用 | I35: 45294 | J35: 45294 | K35: 备件库派送 | L35: 否 | M35: 0.0 | N35: 厦门 | O35: 频繁死机 | Q35: 302-000759 | R35: 备件未使用 | S35: / | V35: / | W35: 未使用备件测试正常 | Y35: / | Z35: / | AB35: 0 | AC35: / | AE35: / | AF35: / | AH35: 鲲泰PC产品 | AI35: KunTai D220 台式机 | AJ35: 台式机4年标准+及介质保留 | AK35: 44418 | AL35: KD000210L715000104 | AM35: 厦门市某局二期台式机采购 | AN35: FJFJ210128248 | AO35: 厦门市同安区祥平西路1号自然资源规划局同安分局 | AP35: liufengab | AR35: 机器间接性卡死 二线数据调试正常。 | AV35: 875 | AW35: =VLOOKUP(G35,[1]备料总表!$B:$GB,182,0) -> #N/A
A36: 20240102018073 | B36: 45293 | C36: 600000004822.0 | D36: 完结 | E36: 302-001349 | F36: SSD | G36: 302-001349 | H36: 2102550438N0MC103578 | I36: 45293 | J36: 45293 | K36: 备件库派送 | L36: 否 | M36: 200.0 | N36: 上海 | O36: 告警代码：0x02000007 the disk Disk4 state is abnormal | Q36: 302-001349 | R36: 034BBR10P8107052 | S36: SF1516732971531 | T36: 45296 | W36: 故障件确认故障 | AB36: 0 | AC36: SF1652310531773 | AD36: 45302 | AE36: 302-001349 | AF36: 034BBRN0P8007010 | AG36: 45302 | AH36: 鲲泰服务器产品 | AI36: KunTai R522 服务器 | AJ36: 2U5年标准+及介质保留和基础硬件安装 | AK36: 45373 | AL36: KS001310NC10000064 | AM36: 中国银联2023年PC服务器协议供货采购项目（包件五）第二批订单 | AN36: XTBJR231113217 | AO36: 上海市浦东新区日版路91号 联系人：邹熙钢 15272024437 | AP36: liufengab | AS36: 700000003873.0 | AV36: 0 | AW36: =VLOOKUP(G36,[1]备料总表!$B:$GB,182,0) -> 99-001349
A37: 20240102018075 | B37: 45293 | C37: 600000004823.0 | D37: 完结 | E37: 302-001349 | F37: SSD | G37: 302-001349 | H37: 034BBR10P3108967 | I37: 45293 | J37: 45293 | K37: 备件库派送 | L37: 否 | M37: 0.0 | N37: 上海 | O37: 告警代码：0x02000007 The disk Disk9 failure | Q37: 302-001349 | R37: 034BBR10P8107596 | S37: SF1516732971531 | T37: 45296 | W37: 故障件确认故障 | AB37: 0 | AC37: SF1652310531773 | AD37: 45302 | AE37: 302-001349 | AF37: 034BBRN0P8006712 | AG37: 45302 | AH37: 鲲泰服务器产品 | AI37: KunTai R522 服务器 | AJ37: 2U5年标准+及介质保留和基础硬件安装 | AK37: 45373 | AL37: KS001310NC10000094 | AM37: 中国银联2023年PC服务器协议供货采购项目（包件五）第二批订单 | AN37: XTBJR231113217 | AO37: 上海市浦东新区日版路91号 联系人：邹熙钢 15272024437 | AP37: liufengab | AS37: 700000003874.0 | AV37: 0 | AW37: =VLOOKUP(G37,[1]备料总表!$B:$GB,182,0) -> 99-001349
A38: 20240102018076 | B38: 45293 | C38: 600000004824.0 | D38: 完结 | E38: 302-001349 | F38: SSD | G38: 302-001349 | H38: 034BBR10P9107055 | I38: 45293 | J38: 45293 | K38: 备件库派送 | L38: 否 | M38: 0.0 | N38: 上海 | O38: 告警：The disk Disk3 is missing。 | Q38: 302-001349 | R38: 034BBRN0P8007269 | S38: SF1516732971531 | T38: 45296 | W38: 故障件确认故障 | AB38: 0 | AC38: SF1652310531773 | AD38: 45302 | AE38: 302-001349 | AF38: 034BBRN0P8006736 | AG38: 45302 | AH38: 鲲泰服务器产品 | AI38: KunTai R522 服务器 | AJ38: 2U5年标准+及介质保留和基础硬件安装 | AK38: 45373 | AL38: KS001310NC10000098 | AM38: 中国银联2023年PC服务器协议供货采购项目（包件五）第二批订单 | AN38: XTBJR231113217 | AO38: 上海市浦东新区日版路91号 联系人：邹熙钢 15272024437 | AP38: liufengab | AS38: 700000003875.0 | AV38: 0 | AW38: =VLOOKUP(G38,[1]备料总表!$B:$GB,182,0) -> 99-001349
A39: 20240102018076 | B39: 45293 | C39: 无 | D39: 完结 | E39: 302-000288 | F39: 机箱(硬盘背板) | G39: 302-000288 | H39: 024MSGDUM9009242 | I39: 45293 | J39: 45293 | K39: 备件库派送 | L39: 否 | M39: 0.0 | N39: 上海 | O39: 告警：The disk Disk3 is missing。 | Q39: 302-000288 | R39: 备件未使用 | S39: / | V39: / | W39: 未使用备件测试正常 | Y39: / | Z39: / | AB39: 0 | AC39: / | AE39: / | AF39: / | AH39: 鲲泰服务器产品 | AI39: KunTai R522 服务器 | AJ39: 2U5年标准+及介质保留和基础硬件安装 | AK39: 45373 | AL39: KS001310NC10000098 | AM39: 中国银联2023年PC服务器协议供货采购项目（包件五）第二批订单 | AN39: XTBJR231113217 | AO39: 上海市浦东新区日版路91号 联系人：邹熙钢 15272024437 | AP39: liufengab | AR39: 备件未使用，到付返回上海库房。 | AV39: 0 | AW39: =VLOOKUP(G39,[1]备料总表!$B:$GB,182,0) -> 88-000288
A40: 20240102018076 | B40: 45293 | C40: 无 | D40: 完结 | E40: 302-000251 | F40: 其他部件 | G40: 302-000251 | H40: 1904051021/Z00A2R2049S001972 | I40: 45293 | J40: 45293 | K40: 备件库派送 | L40: 否 | M40: 0.0 | N40: 上海 | O40: 告警：The disk Disk3 is missing。 | Q40: 302-000251 | R40: 备件未使用 | S40: / | V40: / | W40: 未使用备件测试正常 | Y40: / | Z40: / | AB40: 0 | AC40: / | AE40: / | AF40: / | AH40: 鲲泰服务器产品 | AI40: KunTai R522 服务器 | AJ40: 2U5年标准+及介质保留和基础硬件安装 | AK40: 45373 | AL40: KS001310NC10000098 | AM40: 中国银联2023年PC服务器协议供货采购项目（包件五）第二批订单 | AN40: XTBJR231113217 | AO40: 上海市浦东新区日版路91号 联系人：邹熙钢 15272024437 | AP40: liufengab | AR40: 备件未使用，到付返回上海库房。 | AV40: 0 | AW40: =VLOOKUP(G40,[1]备料总表!$B:$GB,182,0) -> 99-000251
A41: 20240102018077 | B41: 45293 | C41: 600000004825.0 | D41: 完结 | E41: 302-000619 | F41: HDD | G41: 302-000619 | H41: 2102312RBS10N3100043 | I41: 45293 | J41: 45295 | K41: 备件库派送 | L41: 否 | M41: 180.0 | N41: 广州 | O41: 服务器硬盘故障，disk40状态miss，ibmc告警代码（0x0200002D） | Q41: 302-000619 | R41: 2102312VWQN0N4100349 | S41: SF1435066139460 | T41: 45296 | V41: 王义实测：The disk Disk2 link is abnormal. 0x0200002B | W41: 故障件确认故障 | X41: 45321 | Y41: 华为 | Z41: 华为自取 | AA41: 45322 | AB41: 19 | AC41: 11709810.0 | AD41: 45341 | AE41: 302-000619 | AF41: 2102312VWQN0N6100030 | AG41: 45364 | AH41: 鲲泰服务器产品 | AI41: KunTai R722 服务器 | AJ41: 2U3年标准+及基础硬件安装 | AK41: 44823 | AL41: KS001410M617000008 | AM41: 2022年中国联通广东骨干云池广州节点扩容一期工程 | AN41: XTBYYS220426149 | AO41: 广东省广州市黄埔区凤湖一路与狮龙大道交汇处东南角中国联通互联网应用创新基地枢纽楼3楼3号机房 | AP41: liufengab | AR41: 1/4收到客户需求，后续收到故障件，测试故障后反馈给赵文博。 | AS41: 700000003876.0 | AV41: 470 | AW41: =VLOOKUP(G41,[1]备料总表!$B:$GB,182,0) -> 99-001039
A42: 20240102018078 | B42: 45293 | C42: 600000004826.0 | D42: 完结 | E42: 302-000612 | F42: HDD | G42: 302-000619 | H42: WBN5HXMW | I42: 45293 | J42: 45293 | K42: 备件库派送 | L42: 否 | M42: 180.0 | N42: 郑州 | O42: iBMC内无硬盘告警，根据客户提供故障硬盘序列号，在iBMC日志中确定为disk4槽位硬盘，在日志中显示该硬盘为JBOD模式，且存在大量扇区错误 | Q42: 302-000612 | R42: 2102312VWRN0N4101982 | S42: SF1425921017305 | T42: 45296 | V42: 王义实测：The disk Disk5 failure (SN:WBN5M4S9). 0x02000007 和The disk Disk5 state is abnormal (SN:WBN5M4S9). 0x02000027 | W42: 故障件确认故障 | X42: 45321 | Y42: 华为 | Z42: 华为自取 | AA42: 45322 | AB42: 19 | AC42: 11709812.0 | AD42: 45341 | AE42: 302-000612 | AF42: 2102312VWR10N7100019 | AG42: 45364 | AH42: 鲲泰服务器产品 | AI42: KunTai R722 服务器 | AJ42: 2U3年标准+及基础硬件安装 | AK42: 44825 | AL42: KS001410M524000010 | AM42: 国网数字化集采（2022年--河南mrs节点12台） | AN42: XTBNY220512062 | AO42: 河南省电力公司数据中心-郑州市管城回族自治区货站街166号 李贺鹏 16692338651 | AP42: liufengab | AS42: 700000003881.0 | AV42: 468 | AW42: =VLOOKUP(G42,[1]备料总表!$B:$GB,182,0) -> 99-001039
A43: 20240102018080 | B43: 45293 | C43: 600000004829.0 | D43: 完结 | E43: 302-001376 | F43: SSD | G43: 302-001352 | H43: 2102550441N0MC106558 | I43: 45294 | J43: 45294 | K43: 备件库派送 | L43: 否 | M43: 100.0 | N43: 上海 | O43: 现场服务器硬盘故障，无法提供日志信息 | Q43: 302-001376 | R43: S47NNA0R903918 | S43: SF1419116292180 | T43: 45300 | V43: 王义实测：The disk Disk5 has foreign configuration (SN:S47NNA0R903918). 0x02000029 | W43: 故障件确认故障 | X43: 45321 | Y43: 赛特恩 | Z43: SF1527634331456 | AA43: 45341 | AB43: 10 | AC43: SF1508241048906 | AD43: 45351 | AE43: 302-001376 | AF43: S47NNA0R903918 | AH43: 鲲泰服务器产品 | AI43: KunTai R2280 服务器 | AJ43: 2U3年白金+及基础硬件安装 | AK43: 44831 | AL43: KS000310M623000014 | AM43: 国泰君安核心交易系统设备采购 | AN43: HDQJR211214095 | AO43: 上海市浦东新区龙沪路399号 | AP43: liufengab | AR43: 3/12修复件通电超时入废品库。 | AS43: 700000003935.0 | AV43: 462 | AW43: =VLOOKUP(G43,[1]备料总表!$B:$GB,182,0) -> 99-001349
A44: 20240102018081 | B44: 45293 | C44: 600000004830.0 | D44: 完结 | E44: 302-000147 | F44: Riser卡 | G44: 302-000147 | H44: 2102312VXU10L4000809 | I44: 45294 | J44: 45295 | K44: 备件库派送 | L44: 否 | M44: 100.0 | N44: 合肥 | O44: 现场服务器SAS线缆链接异常，前期已更换raid卡及SAS线 | Q44: 302-000147 | R44: 备件未使用 | S44: SF1444576115691 | T44: 45380 | U44: 45383 | V44: ok | W44: 未使用备件测试正常 | X44: 45408 | AB44: 0 | AH44: 鲲泰服务器产品 | AI44: KunTai R522-3 服务器 | AJ44: 2U3年标准+及基础硬件安装 | AK44: 45209 | AL44: KS002510N706000004 | AM44: 滁州应用技术学校服务器采购 | AN44: 商桥立项，无CRM编号 | AO44: 安徽省滁州市全椒县襄河镇大石潭路999号滁州市应用技术学校新校区 | AP44: liufengab | AQ44: 张蕾蕾/侯青山 | AS44: 700000005182.0 | AV44: 84 | AW44: =VLOOKUP(G44,[1]备料总表!$B:$GB,182,0) -> 99-000147
A45: 20240102018081 | B45: 45293 | C45: 600000004831.0 | D45: 完结 | E45: 302-001363 | F45: 主板 | G45: 302-000006 | H45: 028DYD10L9000154 | I45: 45294 | J45: 45295 | K45: 备件库派送 | L45: 否 | M45: 0.0 | N45: 合肥 | O45: 现场服务器SAS线缆链接异常，前期已更换raid卡及SAS线 | Q45: 302-001363 | R45: 2103050EMTFSN6100098 | S45: SF1445888227304 | T45: 45296 | W45: 故障件未复现故障 | X45: 45301 | Y45: / | Z45: / | AB45: 0 | AC45: / | AE45: / | AF45: / | AH45: 鲲泰服务器产品 | AI45: KunTai R522-3 服务器 | AJ45: 2U3年标准+及基础硬件安装 | AK45: 45209 | AL45: KS002510N706000004 | AM45: 滁州应用技术学校服务器采购 | AN45: 商桥立项，无CRM编号 | AO45: 安徽省滁州市全椒县襄河镇大石潭路999号滁州市应用技术学校新校区 | AP45: liufengab | AS45: 700000003877.0 | AV45: 84 | AW45: =VLOOKUP(G45,[1]备料总表!$B:$GB,182,0) -> 99-000708
A46: 20240103018082 | B46: 45294 | C46: 600000004832.0 | D46: 完结 | E46: 302-001672 | F46: HDD | G46: 302-001816 | H46: 2102540165N0PB103934 | I46: 45294 | J46: 45294 | K46: 备件库派送 | L46: 否 | M46: 180.0 | N46: 汕头 | O46: 现场服务器disk 10硬盘故障，导致raid降级 | Q46: 302-001672 | R46: X1K0A1CFFDEH | S46: SF1404869847747 | T46: 45300 | V46: 王义实测：The disk Disk8 is missing. 0x0200002D | W46: 故障件确认故障 | X46: 45321 | Y46: 喜和 | Z46: SF1527634331923 | AA46: 45348 | AB46: 35 | AC46: SF1676266240203 | AD46: 45383 | AE46: 302-001672 | AF46: 14P0A03UFDEH | AG46: 45384 | AH46: 鲲泰服务器产品 | AI46: KunTai R622 服务器 | AJ46: 2U3年标准+及基础硬件安装 | AK46: 44866 | AL46: KS004410M801000043 | AM46: IT云资源池（汕头粤东数据中心）三期工程（中国移动2021年至2022年PC服务器集 | AN46: XTBYYS220328228 | AO46: 广东省汕头市濠江区滨海街道达南路南山湾产业园区B02单元 | AP46: liufengab | AS46: 700000003936.0 | AV46: 428 | AW46: =VLOOKUP(G46,[1]备料总表!$B:$GB,182,0) -> 99-001043
A47: 20240103018083 | B47: 45294 | C47: 600000004833.0 | D47: 完结 | E47: 302-001672 | F47: HDD | G47: 302-001816 | H47: 2102540165N0PB103942 | I47: 45294 | J47: 45294 | K47: 备件库派送 | L47: 否 | M47: 100.0 | N47: 汕头 | O47: 服务器存在外部配置信息，需进行配置导入 | Q47: 302-001672 | R47: Y1C0A55UFDEH | S47: SF1404869847747 | T47: 45300 | V47: 王义实测：The disk Disk5 state is abnormal. 0x02000027 和The disk Disk5 is missing. 0x0200002D | W47: 故障件确认故障 | X47: 45321 | Y47: 喜和 | Z47: SF1527634331923 | AA47: 45348 | AB47: 35 | AC47: SF1676266240203 | AD47: 45383 | AE47: 302-001672 | AF47: 14P0A03XFDEH | AG47: 45384 | AH47: 鲲泰服务器产品 | AI47: KunTai 622 服务器 | AJ47: 2U3年标准+及基础硬件安装 | AK47: 44789 | AL47: KS004410M504000029 | AM47: 移动服务器集采落地-汕头-汕头落地项目 | AN47: XTBYYS220225157 | AO47: 广东省汕头市濠江区滨海街道达南路南山湾产业园区B02单元 | AP47: liufengab | AS47: 700000003937.0 | AV47: 505 | AW47: =VLOOKUP(G47,[1]备料总表!$B:$GB,182,0) -> 99-001043
A48: 20240103018084 | B48: 45294 | C48: 600000004834.0 | D48: 完结 | E48: 302-001241 | F48: HDD | G48: 302-001241 | H48: 210254016510P5113963 | I48: 45294 | J48: 45294 | K48: 备件库派送 | L48: 否 | M48: 100.0 | N48: 北京 | O48: 用户现场服务器硬盘丢失，无法收集日志信息 | Q48: 302-001241 | W48: 介质保留 | AB48: 0 | AH48: 鲲泰服务器产品 | AI48: KunTai R524-4 服务器 | AJ48: 4U5年金牌+及介质保留 | AK48: 45197 | AL48: KS003610N607000010 | AM48: 公A部A2工程项目 | AN48: XTBZF230414155 | AO48: 北京市通州区台湖镇光机电一体化产业基地嘉创一路21号 | AP48: liufengab | AT48: 介质保留 | AV48: 97 | AW48: =VLOOKUP(G48,[1]备料总表!$B:$GB,182,0) -> 99-001043
A49: 20240103018085 | B49: 45294 | C49: 600000004835.0 | D49: 完结 | E49: 302-000670 | F49: PCHDD | G49: 302-000670 | H49: 11DPPHJMSH1H | I49: 45294 | J49: 45294 | K49: 备件库派送 | L49: 否 | M49: 0.0 | N49: 厦门 | O49: bios识别不到硬盘 | Q49: 302-000670 | W49: 介质保留 | AB49: 0 | AH49: 鲲泰PC产品 | AI49: KunTai D220 台式机 | AJ49: 台式机4年标准+及介质保留 | AK49: 44406 | AL49: KD000210L724000114 | AM49: 厦门市某局XCPC采购 | AN49: FJZQ210322591 | AO49: 厦门市海沧分局钟山派出所 | AP49: liufengab | AT49: 介质保留 | AV49: 888 | AW49: =VLOOKUP(G49,[1]备料总表!$B:$GB,182,0) -> #N/A
A50: 20240103018086 | B50: 45294 | C50: 600000004836.0 | D50: 完结 | E50: 302-001627 | F50: 内存 | G50: 302-001627 | H50: 210251004910N4122538 | I50: 45294 | J50: 45294 | K50: 备件库派送 | L50: 否 | M50: 100.0 | N50: 汕头 | O50: 服务器内存错误率超过阈值，ibmc告警代码（0x0100002D） | Q50: 302-001627 | R50: 2102510049N0MC199333 | S50: SF1445584577067 | T50: 45321 | V50: 王义实测：SP测试失败。（有留存日志） | W50: 故障件确认故障 | X50: 45344 | Y50: 华为 | Z50: 华为自取 | AA50: 45348 | AB50: 3 | AC50: 11776984.0 | AD50: 45351 | AE50: 302-001627 | AF50: 2102510049N0PB104525 | AG50: 45352 | AH50: 鲲泰服务器产品 | AI50: KunTai R622 服务器 | AJ50: 2U3年标准+及基础硬件安装 | AK50: 44858 | AL50: KS004410M722000086 | AM50: 中国移动2021年至2022年PC服务器集中采购(第1批次)-IT公司-汕头落地项目1480 | AN50: XTBYYS220328228 | AO50: 广东省汕头市濠江区马窖街道南山湾工业园移动数据中心 | AP50: liufengab | AS50: 700000004209.0 | AV50: 436 | AW50: =VLOOKUP(G50,[1]备料总表!$B:$GB,182,0) -> 99-001627
A51: 20240103018088 | B51: 45294 | C51: 600000004837.0 | D51: 完结 | E51: 302-001672 | F51: HDD | G51: 302-001816 | H51: 2102540165N0PB103947 | I51: 45294 | J51: 45294 | K51: 备件库派送 | L51: 否 | M51: 0.0 | N51: 汕头 | O51: 服务器硬盘故障，disk6存在外部配置，状态FOREIGN | Q51: 302-001672 | R51: X1K0A2Q7FDEH | S51: SF1404869847747 | T51: 45300 | V51: 王义实测：The disk Disk11 link is abnormal. 0x0200002B | W51: 故障件确认故障 | X51: 45321 | Y51: 喜和 | Z51: SF1527634331923 | AA51: 45348 | AB51: 35 | AC51: SF1676266240203 | AD51: 45383 | AE51: 302-001672 | AF51: 14P0A03QFDEH | AG51: 45384 | AH51: 鲲泰服务器产品 | AI51: KunTai R622 服务器 | AJ51: 2U3年标准+及基础硬件安装 | AK51: 44861 | AL51: KS004410M727000153 | AM51: 中国移动2021年至2022年PC服务器集中采购(第1批次)-IT公司-汕头落地项目1480 | AN51: XTBYYS220328228 | AO51: 广东省汕头市濠江区马窖街道南山湾工业园移动数据中心 | AP51: liufengab | AS51: 700000003938.0 | AV51: 433 | AW51: =VLOOKUP(G51,[1]备料总表!$B:$GB,182,0) -> 99-001043
A52: 20240103018087 | B52: 45294 | C52: 600000004952.0 | D52: 完结 | E52: 302-002426 | F52: PC显卡 | G52: 302-002426 | H52: 6LLY23200910 | I52: 45302 | J52: 45302 | K52: 备件库派送 | L52: 否 | M52: 0.0 | N52: 厦门 | O52: 电脑使用一段时间就黑屏，交叉测试其他显示器也不亮 | Q52: 302-002426 | R52: 6LLY23261410 | S52: SF1513541650130 | T52: 45308 | V52: 王义实测：开机时能正常显示，一小时后就黑屏，并且显卡的风扇不转（电脑主板是正常状态） | W52: 故障件确认故障 | X52: 45321 | Y52: 凌宜 | Z52: SF1527634331483 | AA52: 45341 | AB52: 10 | AC52: SF1529553479136 | AD52: 45351 | AE52: 302-002426 | AF52: 6LLY23261410 | AG52: 45364 | AH52: 鲲泰PC产品 | AI52: KunTai D526-2 台式机 | AJ52: 台式机5年上门维保(7x24xND)及介质保留 | AK52: 45246 | AL52: KD000910N801000168 | AM52: 海沧区教育系统XC终端替换 | AN52: HNQ230506029 | AO52: 厦门双十中学海沧附属学校小学部 | AP52: liufengab | AR52: 1/4厦门库房反馈客户要求取消。1/10客户反馈复现问题，1/11重新派件。 | AS52: 700000004016.0 | AV52: 48 | AW52: =VLOOKUP(G52,[1]备料总表!$B:$GB,182,0) -> #N/A
A53: 20240103018089 | B53: 45294 | C53: 600000004839.0 | D53: 完结 | E53: 302-001514 | F53: 内存 | G53: 302-001514 | H53: 80AD012135857E227D | I53: 45294 | J53: 45294 | K53: 备件库派送 | L53: 否 | M53: 100.0 | N53: 重庆 | O53: 内存告警 | Q53: 302-001514 | R53: 80AD01220995F2C650 | S53: SF1446889847159 | T53: 45300 | V53: ok | W53: 故障件未复现故障 | X53: 45321 | AB53: 0 | AH53: 鲲泰服务器产品 | AI53: KunTai R622 服务器 | AJ53: 2U3年标准+及基础硬件安装 | AK53: 45350 | AL53: KS004410N914000010 | AM53: 移动集采落地项目-各省491台 | AN53: XTBYYS230901012 | AO53: 重庆市北碚区水土工业园中国移动数据中心 | AP53: liufengab | AS53: 700000003939.0 | AV53: 0 | AW53: =VLOOKUP(G53,[1]备料总表!$B:$GB,182,0) -> 99-001514
A54: 20240103018090 | B54: 45294 | C54: 600000004840.0 | D54: 武汉废品库 | E54: 302-000587 | F54: HDD | G54: 302-001043 | H54: 7230A1TDFDEH | I54: 45294 | J54: 45294 | K54: 备件库派送 | L54: 否 | M54: 100.0 | N54: 长沙 | O54: ibmc告警：0x02000007 The disk Disk9 failure. | Q54: 302-000587 | R54: 2102312VWTN0MA000108 | S54: SF1400839242354 | T54: 45296 | V54: 王义实测：The disk Disk11 is missing. 0x0200002D 和The disk Disk11 state is abnormal. 0x02000027 | W54: 故障件确认故障 | X54: 45323 | AB54: 0 | AH54: 鲲泰服务器产品 | AI54: KunTai R722 服务器 | AJ54: 2U3年标准+及基础硬件安装 | AK54: 44651 | AL54: KS001410M324000007 | AM54: 2021年中国联通网络IT网络数据采集硬件扩容项目_湖南省分公司单项工程 | AN54: XTBYYS220124107 | AO54: 湖南省-长沙市-长沙县-人民东路412号联通阅读中心4楼 | AP54: liufengab | AS54: 700000003878.0 | AV54: 643 | AW54: =VLOOKUP(G54,[1]备料总表!$B:$GB,182,0) -> 99-001043
A55: 20240102018079 | B55: 45293 | C55: 600000004827.0 | D55: 完结 | E55: 302-000296 | F55: 机箱(硬盘背板) | G55: 302-000296 | H55: 025VYUFSL2002056 | I55: 45295 | J55: 45295 | K55: 备件库派送 | L55: 否 | M55: 100.0 | N55: 北京 | O55: 现场服务器硬盘背板故障 | Q55: 302-000296 | R55: 025VYU10P3102906 | S55: SF1435147133612 | T55: 45308 | V55: 实测BMC报错：0x0200002B、The disk Disk9 link is abnormal. | W55: 故障件确认故障 | X55: 45317 | Y55: 华为 | Z55: SF1527634331401 | AA55: 45317 | AB55: 34 | AC55: 华为自运 | AD55: 45351 | AE55: 302-000296 | AF55: 025VYU10P3102906 | AG55: 45364 | AH55: 鲲泰服务器产品 | AI55: Y12-AH2-25D | AJ55: 2U4年金牌+及介质保留和基础硬件安装 | AK55: 45156 | AL55: KS000210N426000023 | AM55: 2023年百度鲲鹏服务器框架招标 | AN55: XTBNY230409079 | AO55: 北京市通州区宋庄镇徐尹路与富壁路交叉口汇天云端产业园4号楼101模块 | AP55: liufengab | AS55: 700000003972.0 | AV55: 137 | AW55: =VLOOKUP(G55,[1]备料总表!$B:$GB,182,0) -> 88-000296
A56: 20240103018091 | B56: 45294 | C56: 600000004841.0 | D56: 完结 | E56: 302-000296 | F56: 机箱(硬盘背板) | G56: 302-000296 | H56: 025VYUFSL6003569 | I56: 45295 | J56: 45295 | K56: 备件库派送 | L56: 否 | M56: 0.0 | N56: 北京 | O56: 现场服务器硬盘背板故障，现场暂时无法提供日志以及告警相关信息。 | Q56: 302-000296 | R56: 025VYU10P3102651 | S56: SF1435147133612 | T56: 45308 | V56: 实测BMC报错：0x0200002B、The The disk Disk4 link is abnormal. | W56: 故障件确认故障 | X56: 45317 | Y56: 华为 | Z56: SF1527634331401 | AA56: 45317 | AB56: 34 | AC56: 华为自运 | AD56: 45351 | AE56: 302-000296 | AF56: 025VYU10P3102651 | AG56: 45364 | AH56: 鲲泰服务器产品 | AI56: Y12-AH2-25D | AJ56: 2U4年金牌+及介质保留和基础硬件安装 | AK56: 45156 | AL56: KS000210N426000017 | AM56: 2023年百度鲲鹏服务器框架招标 | AN56: XTBNY230409079 | AO56: 北京市通州区宋庄镇汇天云端产业园 | AP56: liufengab | AS56: 700000003973.0 | AV56: 138 | AW56: =VLOOKUP(G56,[1]备料总表!$B:$GB,182,0) -> 88-000296
A57: 20240103018097 | B57: 45294 | C57: 600000004849.0 | D57: 完结 | E57: 305-000095 | F57: 笔记本 | G57: 305-000095 | H57: KN000110LA20000039 | I57: 45296 | J57: 45296 | K57: 备件库派送 | L57: 否 | M57: 0.0 | N57: 合肥 | O57: 升级系统后没有无线网卡驱动，重装系统之后就经常死机 | Q57: 305-000095 | R57: KN000110LA20000039 | S57: SF1518811877695 | T57: 45300 | V57: 王义实测：约两小时后自动死机、关机，重新按开关键看电池还有57%的电。（现场更换主板和SSD） | W57: 故障件确认故障 | X57: 45321 | Y57: 卓怡 | Z57: SF1527634331526 | AA57: 45341 | AB57: 42 | AC57: DPK211899340170 | AD57: 45383 | AE57: 305-000095 | AF57: KN000110LA20000039 | AG57: 45394 | AH57: 鲲泰PC产品 | AI57: KunTai L351 笔记本(含有线鼠标) | AJ57: 台式机3年上门(5x9xNBD) | AK57: 44494 | AL57: KN000110LA15000242 | AM57: 合肥市党政机关安可替代工程第三批F包 | AN57: HZQZF210721423 | AO57: 安徽省合肥市蜀山区东流路100号政务大楼A座4楼416 | AP57: liufengab | AR57: 更换主板和SSD。 | AS57: 700000003940.0 | AV57: 800 | AW57: =VLOOKUP(G57,[1]备料总表!$B:$GB,182,0) -> #N/A
A58: 20240103018098 | B58: 45294 | C58: 600000004842.0 | D58: 完结 | E58: 302-002576 | F58: 主板 | G58: 302-002753 | H58: 2103050MEDD9P8100001 | I58: 45294 | J58: 45295 | K58: SF1521754066503 | L58: 否 | M58: 0.0 | N58: 武汉 | O58: 服务器无法正常上电开机，管理口无法连接，无法提供日志 | Q58: 302-002576 | R58: 2103050EMSP0P6100519 | S58: SF1425913243914 | T58: 45301 | V58: 实测ok | W58: 故障件未复现故障 | X58: 45321 | AB58: 0 | AH58: 鲲泰服务器产品 | AI58: KunTai R522 服务器 | AJ58: 2U3年标准+ | AK58: 45361 | AL58: KS001310NC08000003 | AM58: 天心区政府监控系统服务器采购项目 | AN58: HZQ231201024 | AO58: 湖南长沙岳麓区尖山路39号中电软件园1期17栋6楼 | AP58: liufengab | AS58: 700000003941.0 | AV58: 0 | AW58: =VLOOKUP(G58,[1]备料总表!$B:$GB,182,0) -> 99-000707
A59: 20240103018102 | B59: 45294 | C59: 600000004843.0 | D59: 完结 | E59: 302-001043 | F59: HDD | G59: 302-001043 | H59: 6130A1AYFDEH | I59: 45294 | J59: 45294 | K59: 备件库派送 | L59: 否 | M59: 180.0 | N59: 西安 | O59: 告警代码为：0x02000007、0x02000027及0x2C000075 | Q59: 302-001043 | R59: 7220A0WZFDEH | S59: SF1442871847394 | T59: 45296 | V59: 王义实测：The disk Disk2 state is abnormal. 0x02000027 和The disk Disk2 is missing. 0x0200002D | W59: 故障件确认故障 | X59: 45321 | Y59: 喜和 | Z59: SF1527634331923 | AA59: 45348 | AB59: 35 | AC59: SF1676266240203 | AD59: 45383 | AE59: 302-001672 | AF59: 14P0A037FDEH | AG59: 45384 | AH59: 鲲泰服务器产品 | AI59: KunTai R722 服务器 | AJ59: 2U3年标准+及基础硬件安装 | AK59: 44924 | AL59: KS001410M928000019 | AM59: 2021年中国联通网络IT网络数据采集硬件扩容项目_陕西省分公司单项工程 | AN59: XTBYYS220819153 | AO59: 西安市雁塔区丰惠南路15号 韩老师 13060370066 | AP59: liufengab | AS59: 700000003879.0 | AV59: 370 | AW59: =VLOOKUP(G59,[1]备料总表!$B:$GB,182,0) -> 99-001043
A60: 20240103018102 | B60: 45294 | C60: 600000004844.0 | D60: 完结 | E60: 302-001043 | F60: HDD | G60: 302-001043 | H60: 73P0A2ZVFDEH | I60: 45294 | J60: 45294 | K60: 备件库派送 | L60: 否 | M60: 0.0 | N60: 西安 | O60: 告警代码为：0x02000007、0x02000027及0x2C000075 | Q60: 302-001043 | R60: 7220A0VXFDEH | S60: SF1442871847394 | T60: 45296 | V60: 王义实测：The disk Disk5 is missing. 0x0200002D 和The disk Disk5 state is abnormal. 0x02000027 | W60: 故障件确认故障 | X60: 45321 | Y60: 喜和 | Z60: SF1527634331923 | AA60: 45348 | AB60: 35 | AC60: SF1676266240203 | AD60: 45383 | AE60: 302-001672 | AF60: 14P0A03MFDEH | AG60: 45384 | AH60: 鲲泰服务器产品 | AI60: KunTai R722 服务器 | AJ60: 2U3年标准+及基础硬件安装 | AK60: 44924 | AL60: KS001410M928000019 | AM60: 2021年中国联通网络IT网络数据采集硬件扩容项目_陕西省分公司单项工程 | AN60: XTBYYS220819153 | AO60: 西安市雁塔区丰惠南路15号 韩老师 13060370066 | AP60: liufengab | AS60: 700000003880.0 | AV60: 370 | AW60: =VLOOKUP(G60,[1]备料总表!$B:$GB,182,0) -> 99-001043
A61: 20240103018103 | B61: 45294 | C61: 600000004845.0 | D61: 完结 | E61: 302-001043 | F61: HDD | G61: 302-001241 | H61: 210254016510P6111461 | I61: 45294 | J61: 45294 | K61: 现场保障备件 | L61: 否 | M61: 0.0 | N61: 郑州联通 | O61: disk11状态miss，ibmc告警代码（0x0200002D） | Q61: 302-001043 | R61: 7220A4SQFDEH | S61: SF1403819888528 | T61: 45301 | V61: 王义实测：The disk Disk1 state is abnormal. 0x02000027 和The disk Disk1 link is abnormal. 0x0200002B | W61: 故障件确认故障 | X61: 45321 | Y61: 喜和 | Z61: SF1527634331923 | AA61: 45348 | AB61: 35 | AC61: SF1676266240203 | AD61: 45383 | AE61: 302-001672 | AF61: 14P0A02QFDEH | AG61: 45384 | AH61: 鲲泰服务器产品 | AI61: KunTai R722 服务器 | AJ61: 2U3年标准+及基础硬件安装 | AK61: 44963 | AL61: KS001410MA15000042 | AM61: 2022年中国联通通信云中原DC通用资源池二期工程—集团总部单项工程（中国联通 | AN61: XTBYYS220721145 | AO61: 郑州市高新区中原数据基地 | AP61: liufengab | AS61: 700000003942.0 | AV61: 331 | AW61: =VLOOKUP(G61,[1]备料总表!$B:$GB,182,0) -> 99-001043
A62: 20240103018107 | B62: 45294 | C62: 600000004846.0 | D62: 完结 | E62: 302-001672 | F62: HDD | G62: 302-001816 | H62: 2102540165N0PB103933 | I62: 45294 | J62: 45294 | K62: 备件库派送 | L62: 否 | M62: 180.0 | N62: 汕头 | O62: 服务器disk 9硬盘故障，固件状态为“offline” | Q62: 302-001672 | R62: 32N0A7D0FDEH | S62: SF1404869847747 | T62: 45300 | V62: 王义实测：The disk Disk5 is missing. | W62: 故障件确认故障 | X62: 45321 | Y62: 喜和 | Z62: SF1527634331923 | AA62: 45348 | AB62: 35 | AC62: SF1676266240203 | AD62: 45383 | AE62: 302-001672 | AF62: 14P0A03WFDEH | AG62: 45384 | AH62: 鲲泰服务器产品 | AI62: KunTai R622 服务器 | AJ62: 2U3年标准+及基础硬件安装 | AK62: 44858 | AL62: KS004410M722000013 | AM62: 中国移动2021年至2022年PC服务器集中采购(第1批次)-IT公司-汕头落地项目1480 | AN62: XTBYYS220328228 | AO62: 广东省汕头市濠江区马窖街道南山湾工业园移动数据中心 | AP62: liufengab | AS62: 700000003943.0 | AV62: 436 | AW62: =VLOOKUP(G62,[1]备料总表!$B:$GB,182,0) -> 99-001043
A63: 20240104018113 | B63: 45295 | C63: 600000004847.0 | D63: 完结 | E63: 302-000519 | F63: Riser卡 | G63: 302-000519 | H63: 210258015010M5000047 | I63: 45295 | J63: 45295 | K63: 备件库派送 | L63: 否 | M63: 100.0 | N63: 北京 | O63: 现场测试机器缺备件 | Q63: 302-000519 | R63: 备件未使用 | S63: SF1435660366087 | T63: 45321 | V63: OK | W63: 未使用备件测试正常 | X63: 45364 | AB63: 0 | AH63: 鲲泰服务器产品 | AI63: HK3220 | AJ63: 2U5年金牌+及介质保留和基础硬件安装 | AK63: 45295 | AL63: CETC0810N810000003 | AM63: 某项目SZ47 | AN63: XTBGF230914158 | AO63: 北京市海淀区北四环中路211号中电十五所 | AP63: liufengab | AR63: 例外服务 | AS63: 700000004210.0 | AV63: 0 | AW63: =VLOOKUP(G63,[1]备料总表!$B:$GB,182,0) -> 99-001770
A64: 20240104018114 | B64: 45295 | C64: 600000004848.0 | D64: 完结 | E64: 302-000781 | F64: HDD | G64: 302-000781 | H64: X3G0A0TEFMBF | I64: 45295 | J64: 45295 | K64: 备件库派送 | L64: 否 | M64: 100.0 | N64: 呼和浩特 | O64: 服务器前面板显示H06，表示disk6槽位硬盘故障 | Q64: 302-000781 | W64: 介质保留 | AB64: 0 | AH64: 鲲泰服务器产品 | AI64: KunTai R2280 服务器 | AJ64: 2U3年白金+及介质保留 | AK64: 45365 | AL64: KS000310NC04000045 | AM64: 内蒙古自治区农村信用社联合社信创服务器改造 | AN64: HBQ231025280 | AO64: 内蒙古自治区呼和浩特市和林格尔县云展东街电信云数据中心 王瑞坤 15540746222 | AP64: liufengab | AT64: 介质保留 | AV64: 0 | AW64: =VLOOKUP(G64,[1]备料总表!$B:$GB,182,0) -> 99-000781
A65: 20240104018116 | B65: 45295 | C65: 600000004850.0 | D65: 完结 | E65: 302-001271 | F65: PC主板 | G65: 302-001271 | H65: 2102313RPSYPMB006397 | I65: 45295 | J65: 45296 | K65: 备件库派送 | L65: 否 | M65: 0.0 | N65: 北京 | O65: 台式机频繁死机 | Q65: 302-001271 | R65: 2102313RPS6RMA029399 | S65: SF1521825424430 | T65: 45308 | V65: 实测ok | W65: 故障件未复现故障 | X65: 45323 | AB65: 0 | AH65: 鲲泰PC产品 | AI65: D526-2台式机D2000-8G-256G-2G-13L-MK(无显示器) | AJ65: 台式机标准服务整机3年质保1年上门(5x9x2D) | AK65: 44985 | AL65: A220980003766403245 | AM65: 北京市公安局pc采购 | AN65: XTBZF220822166 | AO65: 北京市海淀区中关村南大街甲八号院 | AP65: liufengab | AS65: 700000003974.0 | AV65: 310 | AW65: =VLOOKUP(G65,[1]备料总表!$B:$GB,182,0) -> #N/A
A66: 20240104018117 | B66: 45295 | C66: 600000004851.0 | D66: 完结 | E66: 302-001241 | F66: HDD | G66: 302-001241 | H66: VYHG4E8M | I66: 45295 | J66: 45295 | K66: 备件库派送 | L66: 是 | M66: 100.0 | N66: 杭州 | O66: 无法登录iBMC及收集iBMC日志，服务器前面板显示H14，硬盘亮黄灯 | Q66: 302-001241 | W66: 介质保留 | AB66: 0 | AH66: 鲲泰服务器产品 | AI66: KunTai R524-4 服务器 | AJ66: 4U5年金牌+及介质保留 | AK66: 45193 | AL66: KS003610N614000003 | AM66: 公A部A2工程项目 | AN66: XTBZF230414155 | AO66: 浙江省杭州市富阳区太阳山路10号浙报传媒富春云互联网数据中心 梁志明18811086506 | AP66: liufengab | AT66: 介质保留 | AV66: 102 | AW66: =VLOOKUP(G66,[1]备料总表!$B:$GB,182,0) -> 99-001043
A67: 20240104018118 | B67: 45295 | C67: 600000004852.0 | D67: 完结 | E67: 302-000447 | F67: Riser卡 | G67: 302-000447 | H67: 2102580142N0P6100237 | I67: 45295 | J67: 45295 | K67: 备件库派送 | L67: 否 | M67: 100.0 | N67: 广州 | O67: 前期更换备件后，故障依旧，现场更换PCIE槽位后恢复正常 | Q67: 302-000447 | R67: 2102580142N0NC100265 | S67: SF1457922766472 | T67: 45321 | V67: OK | W67: 故障件未复现故障 | X67: 45320 | AB67: 0 | AH67: 鲲泰服务器产品 | AI67: KunTai R822 服务器 | AJ67: 2U5年金牌+及介质保留和高级硬件安装 | AK67: 45130 | AL67: KS002710N421000038 | AM67: 南方电网框架集采--50台典配 | AN67: XTBNY221207044 | AO67: 广州市白云区黄石西路西基大街27号 叶杰文 13622812144 | AP67: liufengab | AS67: 700000004211.0 | AV67: 165 | AW67: =VLOOKUP(G67,[1]备料总表!$B:$GB,182,0) -> 99-000447
A68: 20240104018119 | B68: 45295 | C68: 600000004853.0 | D68: 完结 | E68: 302-002612 | F68: RAID卡 | G68: 302-002613 | H68: SKD2837581 | I68: 45295 | J68: 45295 | K68: 现场保障备件 | L68: 否 | M68: 0.0 | N68: 廊坊软通 | O68: 服务器存在线缆告警，告警码0x28000001 | Q68: 302-002612 | R68: 返厦门工厂 | S68: / | V68: / | Y68: / | Z68: / | AB68: 0 | AC68: SF1644896817213 | AD68: 45302 | AE68: 302-002612 | AF68: 210256006010PA103674 | AG68: 45302 | AH68: 鲲泰服务器产品 | AI68: KunTai R722 服务器 | AJ68: 2U5年白金+及介质保留和基础硬件安装 | AK68: 45295 | AL68: KS001410NB03000164 | AM68: 邮储鲲鹏服务器423台采购 | AN68: XTBJR231019179 | AO68: 廊坊市安次区龙河移动云计算数据基地 | AP68: liufengab | AR68: DOA支持 | AS68: 700000003957.0 | AV68: 0 | AW68: =VLOOKUP(G68,[1]备料总表!$B:$GB,182,0) -> 99-001705
A69: 20240104018121 | B69: 45295 | C69: 600000004854.0 | D69: 完结 | E69: 302-000602 | F69: HDD | G69: 302-001056 | H69: WBM7RR1E | I69: 45295 | J69: 45295 | K69: 备件库派送 | L69: 否 | M69: 100.0 | N69: 上海 | O69: 服务器硬盘存在告警，无法提供日志 | Q69: 302-000602 | W69: 介质保留 | AB69: 0 | AH69: 鲲泰服务器产品 | AI69: KunTai R522 服务器 | AJ69: 2U5年金牌+及介质保留和基础硬件安装 | AK69: 44896 | AL69: KS001310M826000154 | AM69: 交通银行2022年鲲鹏框架采购第一批500台 | AN69: HDQJR220315154 | AO69: 上海市闵行区绿洲环路450号 | AP69: liufengab | AT69: 介质保留 | AV69: 399 | AW69: =VLOOKUP(G69,[1]备料总表!$B:$GB,182,0) -> 99-000781
A70: 20240104018122 | B70: 45295 | C70: 600000004855.0 | D70: 完结 | E70: 302-000602 | F70: HDD | G70: 302-001056 | H70: WBM7RGA2 | I70: 45295 | J70: 45295 | K70: 备件库派送 | L70: 否 | M70: 0.0 | N70: 上海 | O70: 服务器硬盘存在告警，无法提供日志 | Q70: 302-000602 | W70: 介质保留 | AB70: 0 | AH70: 鲲泰服务器产品 | AI70: KunTai R522 服务器 | AJ70: 2U5年金牌+及介质保留和基础硬件安装 | AK70: 44896 | AL70: KS001310M826000064 | AM70: 交通银行2022年鲲鹏框架采购第一批500台 | AN70: HDQJR220315154 | AO70: 上海市闵行区绿洲环路450号 | AP70: liufengab | AT70: 介质保留 | AV70: 399 | AW70: =VLOOKUP(G70,[1]备料总表!$B:$GB,182,0) -> 99-000781
A71: 20240104018123 | B71: 45295 | C71: 600000004856.0 | D71: 完结 | E71: 302-000602 | F71: HDD | G71: 302-001056 | H71: WBM7YPG1 | I71: 45295 | J71: 45295 | K71: 备件库派送 | L71: 否 | M71: 0.0 | N71: 上海 | O71: 服务器硬盘存在告警，无法提供日志 | Q71: 302-000602 | W71: 介质保留 | AB71: 0 | AH71: 鲲泰服务器产品 | AI71: KunTai R522 服务器 | AJ71: 2U5年金牌+及介质保留和基础硬件安装 | AK71: 44896 | AL71: KS001310M826000168 | AM71: 交通银行2022年鲲鹏框架采购第一批500台 | AN71: HDQJR220315154 | AO71: 上海市闵行区绿洲环路450号 | AP71: liufengab | AT71: 介质保留 | AV71: 399 | AW71: =VLOOKUP(G71,[1]备料总表!$B:$GB,182,0) -> 99-000781
A72: 20240104018124 | B72: 45295 | C72: 600000004857.0 | D72: 完结 | E72: 302-000602 | F72: HDD | G72: 302-001056 | H72: WBM7Z7CZ | I72: 45295 | J72: 45295 | K72: 备件库派送 | L72: 否 | M72: 0.0 | N72: 上海 | O72: 服务器硬盘存在告警，无法提供日志 | Q72: 302-000602 | W72: 介质保留 | AB72: 0 | AH72: 鲲泰服务器产品 | AI72: KunTai R522 服务器 | AJ72: 2U5年金牌+及介质保留和基础硬件安装 | AK72: 44896 | AL72: KS001310M826000065 | AM72: 交通银行2022年鲲鹏框架采购第一批500台 | AN72: HDQJR220315154 | AO72: 上海市闵行区绿洲环路450号 | AP72: liufengab | AT72: 介质保留 | AV72: 399 | AW72: =VLOOKUP(G72,[1]备料总表!$B:$GB,182,0) -> 99-000781
A73: 20240104018125 | B73: 45295 | C73: 600000004858.0 | D73: 完结 | E73: 302-001056 | F73: HDD | G73: 302-001056 | H73: WBM7RVLX | I73: 45295 | J73: 45295 | K73: 备件库派送 | L73: 否 | M73: 0.0 | N73: 上海 | O73: 服务器硬盘存在告警，无法提供日志 | Q73: 302-001056 | W73: 介质保留 | AB73: 0 | AH73: 鲲泰服务器产品 | AI73: KunTai R522 服务器 | AJ73: 2U5年金牌+及介质保留和基础硬件安装 | AK73: 45072 | AL73: KS001310MC15000295 | AM73: 交行2022年DWS容灾和MRS华为云鲲鹏服务器采购 | AN73: HDQJR220516085 | AO73: 上海市闵行区绿洲环路450号 | AP73: liufengab | AT73: 介质保留 | AV73: 223 | AW73: =VLOOKUP(G73,[1]备料总表!$B:$GB,182,0) -> 99-000781
A74: 20240104018128 | B74: 45295 | C74: 600000004859.0 | D74: 完结 | E74: 302-002060 | F74: HDD | G74: 302-002060 | H74: WRT0095V | I74: 45295 | J74: 45295 | K74: 备件库派送 | L74: 否 | M74: 100.0 | N74: 福州 | O74: 服务器被踢出服务器云平台 | Q74: 302-002060 | R74: 备件未使用 | S74: SF1449802527314 | T74: 45300 | V74: ok | W74: 未使用备件测试正常 | X74: 45321 | AB74: 0 | AH74: 鲲泰服务器产品 | AI74: KunTai R722 服务器 | AJ74: 2U3年标准+及介质保留 | AK74: 45167 | AL74: KS001410N112000035 | AM74: 福建省金税四期 | AN74: HNQZF221025164 | AO74: 福建省福州市长乐区文武砂路与万沙路交叉口中国移动福州移动数据中心A2栋406机房 | AP74: liufengab | AS74: 700000003944.0 | AV74: 128 | AW74: =VLOOKUP(G74,[1]备料总表!$B:$GB,182,0) -> 99-000737
A75: 20240104018128 | B75: 45295 | C75: 600000004860.0 | D75: 完结 | E75: 302-002060 | F75: HDD | G75: 302-002060 | H75: ZRT0RDHP | I75: 45295 | J75: 45295 | K75: 备件库派送 | L75: 否 | M75: 0.0 | N75: 福州 | O75: 服务器被踢出服务器云平台 | Q75: 302-002060 | W75: 介质保留 | AB75: 0 | AH75: 鲲泰服务器产品 | AI75: KunTai R722 服务器 | AJ75: 2U3年标准+及介质保留 | AK75: 45167 | AL75: KS001410N112000035 | AM75: 福建省金税四期 | AN75: HNQZF221025164 | AO75: 福建省福州市长乐区文武砂路与万沙路交叉口中国移动福州移动数据中心A2栋406机房 | AP75: liufengab | AT75: 介质保留 | AV75: 128 | AW75: =VLOOKUP(G75,[1]备料总表!$B:$GB,182,0) -> 99-000737
A76: 20240104018128 | B76: 45295 | C76: 600000004861.0 | D76: 完结 | E76: 302-002060 | F76: HDD | G76: 302-002060 | H76: ZRT0RBN7 | I76: 45295 | J76: 45295 | K76: 备件库派送 | L76: 否 | M76: 0.0 | N76: 福州 | O76: 服务器被踢出服务器云平台 | Q76: 302-002060 | W76: 介质保留 | AB76: 0 | AH76: 鲲泰服务器产品 | AI76: KunTai R722 服务器 | AJ76: 2U3年标准+及介质保留 | AK76: 45167 | AL76: KS001410N112000035 | AM76: 福建省金税四期 | AN76: HNQZF221025164 | AO76: 福建省福州市长乐区文武砂路与万沙路交叉口中国移动福州移动数据中心A2栋406机房 | AP76: liufengab | AT76: 介质保留 | AV76: 128 | AW76: =VLOOKUP(G76,[1]备料总表!$B:$GB,182,0) -> 99-000737
A77: 20240104018130 | B77: 45295 | C77: 600000004862.0 | D77: 完结 | E77: 301-000000 | F77: PC显示器 | G77: 301-000021 | H77: XS001210NA18001362 | I77: 45296 | J77: 45296 | K77: 备件库派送 | L77: 否 | M77: 0.0 | N77: 厦门 | O77: 显示器黑屏点不亮 | Q77: 301-000000 | R77: XS000210L328000753 | S77: SF1526633942135 | T77: 45300 | V77: 王义实测：不显示 | W77: 故障件确认故障 | X77: 45321 | Y77: 完美 | Z77: SF1527634331474 | AA77: 45341 | AB77: 42 | AD77: 45383 | AE77: 301-000000 | AF77: XS000210L328000753 | AG77: 45384 | AH77: 鲲泰PC产品 | AI77: KunTai D220 台式机 | AJ77: 台式机4年标准+及介质保留 | AK77: 44418 | AL77: KD000210L722000122 | AM77: 厦门市某局二期台式机采购 | AN77: FJFJ210128248 | AO77: 福建省厦门市思明区湖滨中路518号 | AP77: liufengab | AS77: 700000003945.0 | AV77: 877 | AW77: =VLOOKUP(G77,[1]备料总表!$B:$GB,182,0) -> 77-000021
A78: 20240104018131 | B78: 45295 | C78: 600000004863.0 | D78: 武汉废品库 | E78: 301-000011 | F78: PC键鼠套装 | G78: 301-000012 | H78: MK000410M706003982 | I78: 45296 | J78: 45296 | K78: 备件库派送 | L78: 否 | M78: 0.0 | N78: 厦门 | O78: 键盘个别按键失灵 | Q78: 301-000011 | R78: MK000310L329002247 | S78: SF1526633942135 | T78: 45300 | V78: 王义实测：小键盘的“7/8/9”失效。 | W78: 故障件确认故障 | X78: 45321 | Y78: 博骏 | Z78: 报废 | AA78: 45341 | AB78: 0 | AH78: 鲲泰PC产品 | AI78: KunTai D220 台式机 | AJ78: 台式机4年标准+及介质保留 | AK78: 44418 | AL78: KD000210L722000302 | AM78: 厦门市某局二期台式机采购 | AN78: FJFJ210128248 | AO78: 福建省厦门市思明区湖滨中路518号 | AP78: liufengab | AS78: 700000003946.0 | AV78: 877 | AW78: =VLOOKUP(G78,[1]备料总表!$B:$GB,182,0) -> #N/A
A79: 20240104018132 | B79: 45295 | C79: 600000004864.0 | D79: 完结 | E79: 302-000592 | F79: HDD | G79: 302-001672 | H79: 93E0A0ANSDEH | I79: 45295 | J79: 45295 | K79: 现场保障备件 | L79: 否 | M79: 0.0 | N79: 枣庄联通 | O79: 告警代码为：0x02000007、0x02000027及0x2C000075，硬盘固件状态为FAILED | Q79: 302-000592 | R79: 2102312VWTN0MC103666 | S79: SF1514239597274 | T79: 45300 | V79: 王义实测：The disk Disk11 state is abnormal. 0x02000027 和The disk Disk11 link is abnormal. 0x0200002B | W79: 故障件确认故障 | X79: 45321 | Y79: 华为 | Z79: 超微物料 | AA79: 45322 | AB79: 29 | AC79: 37641660，更换好件，故障件待处理 | AD79: 45351 | AE79: 302-001816 | AF79: 2102312VWTN0Q1100001 | AG79: 45364 | AH79: 鲲泰服务器产品 | AI79: KunTai R722 服务器 | AJ79: 2U3年标准+及基础硬件安装 | AK79: 44588 | AL79: KS001410M104000075 | AM79: 联通集团网络安全项目 | AN79: DBQYYS210902020 | AO79: 山东省枣庄市薛城区鲁南大数据中心(西门) 裴瑞泽 18600752271 | AP79: liufengab | AS79: 700000003947.0 | AV79: 707 | AW79: =VLOOKUP(G79,[1]备料总表!$B:$GB,182,0) -> 99-001043
A80: 20240104018133 | B80: 45295 | C80: 600000004865.0 | D80: 完结 | E80: 302-001345 | F80: 主板 | G80: 302-001345 | H80: 2103050FNE10P2100002 | I80: 45295 | J80: 45295 | K80: 备件库派送 | L80: 否 | M80: 180.0 | N80: 广州 | O80: 前期更换备件后，故障依旧，现场更换PCIE槽位后恢复正常 | Q80: 302-001345 | R80: 2103050FNEP0NC101288 | S80: SF1409939655028 | T80: 45308 | V80: 实测BMC告警：0x28000001、1. Check whether the SAS cables are connected in correct order. 2. Replace the SAS cables. 3. Replace the RAID controller card or the riser card holding the PCIe RAID card. 4. Replace the disk backplane. | W80: 故障件确认故障 | X80: 45317 | Y80: 华为 | Z80: SF1527634331378 | AA80: 45317 | AB80: 34 | AC80: 华为自运 | AD80: 45351 | AE80: 302-001345 | AF80: 2103050FNE10P8100017 | AG80: 45364 | AH80: 鲲泰服务器产品 | AI80: KunTai R822 服务器 | AJ80: 2U5年金牌+及介质保留和高级硬件安装 | AK80: 45130 | AL80: KS002710N421000038 | AM80: 南方电网框架集采--50台典配 | AN80: XTBNY221207044 | AO80: 广州市白云区黄石西路西基大街27号 叶杰文 13622812144 | AP80: liufengab | AS80: 700000003975.0 | AV80: 165 | AW80: =VLOOKUP(G80,[1]备料总表!$B:$GB,182,0) -> 99-000413
A81: 20240104018135 | B81: 45295 | C81: 600000004866.0 | D81: 完结 | E81: 302-001672 | F81: HDD | G81: 302-001672 | H81: 93E0A09BSDEH | I81: 45295 | J81: 45296 | K81: 备件库派送 | L81: 否 | M81: 100.0 | N81: 杭州 | O81: 告警代码为：0x02000007、0x02000027及0x2C000075，硬盘固件状态为OFFLINE，硬盘日志显示有扇区错误 | Q81: 302-001672 | R81: X210A065FDEH | S81: SF1435140482552 | T81: 45308 | V81: 王义实测：The disk Disk5 is missing. 0x0200002D 和The disk Disk5 state is abnormal. 0x02000027 | W81: 故障件确认故障 | X81: 45321 | Y81: 喜和 | Z81: SF1527634331923 | AA81: 45348 | AB81: 35 | AC81: SF1676266240203 | AD81: 45383 | AE81: 302-001672 | AF81: 14P0A03KFDEH | AG81: 45384 | AH81: 鲲泰服务器产品 | AI81: KunTai R622 服务器 | AJ81: 2U3年标准+及基础硬件安装 | AK81: 45197 | AL81: KS004410N212000194 | AM81: 中国移动2021年至2022年PC服务器集中采购补充采购第二期（IT云四期） | AN81: XTBYYS221206034 | AO81: 浙江省宁波市慈溪市杭州湾新区滨海六路1208号浙东信息产业园 常建鑫 17634600645 | AP81: liufengab | AS81: 700000003976.0 | AV81: 98 | AW81: =VLOOKUP(G81,[1]备料总表!$B:$GB,182,0) -> 99-001043
A82: 20240104018137 | B82: 45295 | C82: 600000004867.0 | D82: 完结 | E82: 302-000174 | F82: 光模块 | G82: 302-000381 | H82: 2012020198.0 | I82: 45295 | J82: 45295 | K82: 备件库派送 | L82: 否 | M82: 180.0 | N82: 杭州 | O82: 客户系统中显示光模块数据有误，iBMC内无告警，客户系统平台报错 | Q82: 302-000174 | R82: 备件未使用 | S82: SF1425945456551 | T82: 45308 | V82: 实测ok | W82: 未使用备件测试正常 | X82: 45321 | AB82: 0 | AH82: 鲲泰服务器产品 | AI82: KunTai R622 服务器 | AJ82: 2U3年标准+及基础硬件安装 | AK82: 45197 | AL82: KS004410N215000028 | AM82: 中国移动2021年至2022年PC服务器集中采购补充采购第二期（IT云四期） | AN82: XTBYYS221206034 | AO82: 浙江省宁波市慈溪市杭州湾新区滨海六路1208号 王梦杰 19560538984 | AP82: liufengab | AS82: 700000003977.0 | AV82: 98 | AW82: =VLOOKUP(G82,[1]备料总表!$B:$GB,182,0) -> 99-000381
A83: 20240104018137 | B83: 45295 | C83: 600000004868.0 | D83: 完结 | E83: 302-000174 | F83: 光模块 | G83: 302-000381 | H83: 2103236413.0 | I83: 45295 | J83: 45295 | K83: 备件库派送 | L83: 否 | M83: 0.0 | N83: 杭州 | O83: 客户系统中显示光模块数据有误，iBMC内无告警，客户系统平台报错 | Q83: 302-000174 | R83: 备件未使用 | S83: SF1425945456551 | T83: 45308 | V83: 实测ok | W83: 未使用备件测试正常 | X83: 45321 | AB83: 0 | AH83: 鲲泰服务器产品 | AI83: KunTai R622 服务器 | AJ83: 2U3年标准+及基础硬件安装 | AK83: 45197 | AL83: KS004410N215000028 | AM83: 中国移动2021年至2022年PC服务器集中采购补充采购第二期（IT云四期） | AN83: XTBYYS221206034 | AO83: 浙江省宁波市慈溪市杭州湾新区滨海六路1208号 王梦杰 19560538984 | AP83: liufengab | AS83: 700000003978.0 | AV83: 98 | AW83: =VLOOKUP(G83,[1]备料总表!$B:$GB,182,0) -> 99-000381
A84: 20240104018143 | B84: 45295 | C84: 600000004869.0 | D84: 完结 | E84: 302-000756 | F84: 网卡 | G84: 302-000756 | H84: 210257004510MC011358 | I84: 45295 | J84: 45295 | K84: 备件库派送 | L84: 否 | M84: 0.0 | N84: 杭州 | O84: 用户服务器RAID卡存在PHY报错，告警码0x2B000003 | Q84: 302-000756 | R84: 2102570045N0NC103608 | S84: SF1425945456551 | T84: 45308 | V84: 实测ok | W84: 故障件未复现故障 | X84: 45321 | AB84: 0 | AH84: 鲲泰服务器产品 | AI84: KunTai R622 服务器 | AJ84: 2U3年标准+及基础硬件安装 | AK84: 45197 | AL84: KS004410N209000105 | AM84: 中国移动2021年至2022年PC服务器集中采购补充采购第二期（IT云四期） | AN84: XTBYYS221206034 | AO84: 杭州市西湖区花园南村8-2-502 | AP84: liufengab | AS84: 700000003979.0 | AV84: 98 | AW84: =VLOOKUP(G84,[1]备料总表!$B:$GB,182,0) -> 99-000756
A85: 20240104018143 | B85: 45295 | C85: 600000004870.0 | D85: 完结 | E85: 302-001705 | F85: RAID卡 | G85: 302-001705 | H85: 210256006010N5106489 | I85: 45295 | J85: 45295 | K85: 备件库派送 | L85: 否 | M85: 0.0 | N85: 杭州 | O85: 用户服务器RAID卡存在PHY报错，告警码0x2B000003 | Q85: 302-001705 | R85: 210256006010NA102535 | S85: SF1425945456551 | T85: 45308 | V85: 实测BMC告警：0x08000095、1. Restart the server and open BIOS Device Manager in UEFI mode. Enter the Driver Health menu, and select Repair the whole platform. 2. Check and upgrade the firmware and driver of the RAID controller card to the latest version in the OS. 3. Check whether the OptionRom space in legacy mode is sufficient in the OS. 4. Replace the RAID controller card. | W85: 故障件确认故障 | X85: 45317 | Y85: 华为 | AB85: 0 | AD85: 45383 | AE85: 302-001705 | AF85: 210256006010P9105271 | AG85: 45384 | AH85: 鲲泰服务器产品 | AI85: KunTai R622 服务器 | AJ85: 2U3年标准+及基础硬件安装 | AK85: 45197 | AL85: KS004410N209000105 | AM85: 中国移动2021年至2022年PC服务器集中采购补充采购第二期（IT云四期） | AN85: XTBYYS221206034 | AO85: 杭州市西湖区花园南村8-2-502 | AP85: liufengab | AS85: 700000003980.0 | AV85: 98 | AW85: =VLOOKUP(G85,[1]备料总表!$B:$GB,182,0) -> 99-001705
A86: 20240104018143 | B86: 45295 | C86: 600000004871.0 | D86: 完结 | E86: 302-001780 | F86: 其他部件 | G86: 302-001780 | H86: 1904052867-004/Z039WM2234S000060 | I86: 45295 | J86: 45295 | K86: 备件库派送 | L86: 否 | M86: 0.0 | N86: 杭州 | O86: 用户服务器RAID卡存在PHY报错，告警码0x2B000003 | Q86: 302-001780 | R86: 备件未使用 | S86: SF1425945456551 | T86: 45308 | V86: 实测ok | W86: 未使用备件测试正常 | X86: 45321 | AB86: 0 | AH86: 鲲泰服务器产品 | AI86: KunTai R622 服务器 | AJ86: 2U3年标准+及基础硬件安装 | AK86: 45197 | AL86: KS004410N209000105 | AM86: 中国移动2021年至2022年PC服务器集中采购补充采购第二期（IT云四期） | AN86: XTBYYS221206034 | AO86: 杭州市西湖区花园南村8-2-502 | AP86: liufengab | AS86: 700000003981.0 | AV86: 98 | AW86: =VLOOKUP(G86,[1]备料总表!$B:$GB,182,0) -> 0
A87: 20240104018141 | B87: 45295 | C87: 600000004872.0 | D87: 完结 | E87: 302-001815 | F87: HDD | G87: 302-001815 | H87: WS244FQC | I87: 45296 | J87: 45296 | K87: 备件库派送 | L87: 否 | M87: 100.0 | N87: 北京 | O87: 服务器disk6存在告警，查看BMC无告警，disk6存在错误扇区 | Q87: 302-001815 | R87: 2102540166N0P6105698 | S87: SF1445930057541 | T87: 45308 | V87: 王义实测：The disk Disk5 state is abnormal. 0x02000027 和The disk Disk5 link is abnormal. 0x0200002B | W87: 故障件确认故障 | X87: 45321 | Y87: 华为 | Z87: 华为自取 | AA87: 45322 | AB87: 19 | AC87: 11709587.0 | AD87: 45341 | AE87: 302-001815 | AF87: 2102540166N0P8100053 | AG87: 45364 | AH87: 鲲泰服务器产品 | AI87: KunTai R722 服务器 | AJ87: 2U3年标准+及基础硬件安装 | AK87: 45379 | AL87: KS001410NA14000024 | AM87: 北京联通zx项目-38台 | AN87: XTBYYS230925280 | AO87: 北京市西城区西长安街11号(西单地铁站C东北口步行250米) 电报大楼 余嘉奥 17532060135 | AP87: liufengab | AS87: 700000003982.0 | AV87: 0 | AW87: =VLOOKUP(G87,[1]备料总表!$B:$GB,182,0) -> 99-001049
A88: 20240104018144 | B88: 45295 | C88: 600000004873.0 | D88: 完结 | E88: 302-001346 | F88: SSD | G88: 302-001346 | H88: 2102550437N0N4101047 | I88: 45295 | J88: 45296 | K88: 备件库派送 | L88: 否 | M88: 180.0 | N88: 合肥 | O88: 硬盘DISK0出现告警，交叉测试告警跟着盘走，告警码0x0200002B | Q88: 302-001346 | R88: 034BBT10NB102108 | S88: SF1441796555870 | T88: 45373 | U88: 45376 | V88: 王义实测：The disk Disk8 link is abnormal. 0x0200002B | W88: 故障件确认故障 | X88: 45380 | Y88: 华为 | Z88: SF1519154094591 | AA88: 45384 | AB88: 17 | AC88: 华为自运 | AD88: 45401 | AE88: 302-001346 | AF88: 034BBTN0P8016425 | AG88: 45420 | AH88: 鲲泰服务器产品 | AI88: KunTai R522-3 服务器 | AJ88: 2U3年标准+及基础硬件安装 | AK88: 45209 | AL88: KS002510N706000004 | AM88: 滁州应用技术学校服务器采购 | AN88: 商桥立项，无CRM编号 | AO88: 安徽省滁州市全椒县襄河镇大石潭路999号滁州市应用技术学校新校区 | AP88: liufengab | AQ88: 张蕾蕾/侯青山 | AS88: 700000004951.0 | AV88: 86 | AW88: =VLOOKUP(G88,[1]备料总表!$B:$GB,182,0) -> 99-001346
A89: 20240104018146 | B89: 45295 | C89: 600000004874.0 | D89: 武汉维修库雷战国 | E89: 302-000143 | F89: 机箱(硬盘背板) | G89: 302-000143 | H89: 2102312VXN10L6000099 | I89: 45295 | J89: 45296 | K89: 备件库派送 | L89: 否 | M89: 180.0 | N89: 汕头 | O89: 硬盘故障，无iBMC日志 | Q89: 302-000143 | R89: 2102312VXNN0NA100405 | S89: SF1435114305764 | T89: 45321 | AB89: 0 | AH89: 鲲泰服务器产品 | AI89: 华科凌云 HK3220-2 服务器 | AJ89: 2U5年金牌+及介质保留 | AK89: 44999 | AL89: CETC0810MB04000060 | AM89: xns项目 | AN89: XTBZF221031216 | AO89: 汕头市金平区汇强外加剂公司南100米(X071南) 唐建波 13981835879 | AP89: liufengab | AR89: 1/19提前拆出给董梦星测试。 | AS89: 700000004212.0 | AV89: 296 | AW89: =VLOOKUP(G89,[1]备料总表!$B:$GB,182,0) -> 99-000143
A90: 20240104018146 | B90: 45295 | C90: 600000004875.0 | D90: 完结 | E90: 302-000637 | F90: HDD | G90: 302-000637 | H90: WFJ5XXTY | I90: 45295 | J90: 45296 | K90: 备件库派送 | L90: 否 | M90: 0.0 | N90: 汕头 | O90: 硬盘故障，无iBMC日志 | Q90: 302-000637 | R90: 备件未使用 | S90: SF1425019242397 | T90: 45321 | V90: 实测ok | W90: 未使用备件测试正常 | X90: 45323 | AB90: 0 | AH90: 鲲泰服务器产品 | AI90: 华科凌云 HK3220-2 服务器 | AJ90: 2U5年金牌+及介质保留 | AK90: 44999 | AL90: CETC0810MB04000060 | AM90: xns项目 | AN90: XTBZF221031216 | AO90: 汕头市金平区汇强外加剂公司南100米(X071南) 唐建波 13981835879 | AP90: liufengab | AS90: 700000004213.0 | AV90: 296 | AW90: =VLOOKUP(G90,[1]备料总表!$B:$GB,182,0) -> 99-001041
A91: 20240104018146 | B91: 45295 | C91: 600000004876.0 | D91: 完结 | E91: 302-000637 | F91: HDD | G91: 302-000637 | H91: WFJ5XYDN | I91: 45295 | J91: 45296 | K91: 备件库派送 | L91: 否 | M91: 0.0 | N91: 汕头 | O91: 硬盘故障，无iBMC日志 | Q91: 302-000637 | W91: 介质保留 | AB91: 0 | AH91: 鲲泰服务器产品 | AI91: 华科凌云 HK3220-2 服务器 | AJ91: 2U5年金牌+及介质保留 | AK91: 44999 | AL91: CETC0810MB04000060 | AM91: xns项目 | AN91: XTBZF221031216 | AO91: 汕头市金平区汇强外加剂公司南100米(X071南) 唐建波 13981835879 | AP91: liufengab | AT91: 介质保留 | AV91: 296 | AW91: =VLOOKUP(G91,[1]备料总表!$B:$GB,182,0) -> 99-001041
A92: 20240105018149 | B92: 45296 | C92: 600000004877.0 | D92: 完结 | E92: 302-000577 | F92: HDD | G92: 302-002093 | H92: 2BJJNNYN | I92: 45296 | J92: 45296 | K92: 备件库派送 | L92: 否 | M92: 100.0 | N92: 上海 | O92: 服务器硬盘存在告警，无法提供日志 | Q92: 302-000577 | R92: 2102540004N0N9100046 | S92: SF1419116292180 | T92: 45300 | V92: 王义实测：The disk Disk11 failure (SN:ZL2LEJ6M). 0x02000007 和The disk Disk11 state is abnormal (SN:ZL2LEJ6M). 0x02000027 | W92: 故障件确认故障 | X92: 45321 | Y92: 华为 | Z92: 华为自取 | AA92: 45322 | AB92: 19 | AC92: 11709577.0 | AD92: 45341 | AE92: 302-000577 | AF92: 2102540004N0P6100001 | AG92: 45364 | AH92: 鲲泰服务器产品 | AI92: KunTai R524 服务器 | AJ92: 4U3年金牌+ | AK92: 45014 | AL92: KS001510MB15000007 | AM92: 上海人工智能计算中心项目 | AN92: HDQZF210923153 | AO92: 上海市浦东新区郭守敬路585上海超级计算中心 | AP92: liufengab | AS92: 700000003948.0 | AV92: 282 | AW92: =VLOOKUP(G92,[1]备料总表!$B:$GB,182,0) -> 99-001163
A93: 20240105018153 | B93: 45296 | C93: 600000004878.0 | D93: 完结 | E93: 302-000711 | F93: 主板 | G93: 302-000711 | H93: 2103050CSH10M5000323 | I93: 45296 | J93: 45296 | K93: 备件库派送 | L93: 否 | M93: 100.0 | N93: 南京 | O93: iBMC日志中告警代码为：0x00000011 | Q93: 302-000711 | R93: 2103050CSHP0NB100421 | S93: SF1522104043968 | T93: 45301 | V93: BIOS密码被改，无法进入BMC测试，客户保修有故障图和日志：客户保修：BMC报错：0x00000011、 Replace the mainboard | W93: 故障件确认故障 | X93: 45317 | Y93: 华为 | Z93: SF1527634331332 | AA93: 45317 | AB93: 34 | AC93: 华为自运 | AD93: 45351 | AE93: 302-002031 | AF93: 2103050JKV10PB100332 | AH93: 鲲泰服务器产品 | AI93: KunTai R722 （NC1K-3-25GE） | AJ93: 2U3年标准+及基础硬件安装 | AK93: 45259 | AL93: KS001410N227000099 | AM93: 中国移动网络云四期采购项目1 | AN93: XTBYYS220407027 | AO93: 江苏省南京市浦口区星火路与学府路交叉口西一百米江北数据中心（中国移动通信集团江苏有限公司） 毛一恒 13673364241 | AP93: liufengab | AS93: 700000003949.0 | AV93: 37 | AW93: =VLOOKUP(G93,[1]备料总表!$B:$GB,182,0) -> 99-000711
A94: 20240105018155 | B94: 45296 | C94: 600000004879.0 | D94: 完结 | E94: 302-000201 | F94: PC电源 | G94: 302-000201 | H94: PS000110NB14001120 | I94: 45296 | J94: 45297 | K94: 备件库派送 | L94: 否 | M94: 0.0 | N94: 武汉 | O94: 台式机无法开机，按开机键没反应，电源灯不亮 | Q94: 302-000201 | R94: 备件未使用 | S94: SF1521679954837 | T94: 45301 | V94: ok | W94: 未使用备件测试正常 | X94: 45321 | AB94: 0 | AH94: 鲲泰PC产品 | AI94: D526-2台式机D2000/8/256/2/13/NMKS/KOS/V1.1 | AJ94: 青松台式机3年质保1年上门(5x9x2D) | AK94: 45145 | AL94: A220980003766400237 | AM94: 渠道PC分销（销售员：郭冬冬） | AN94: 渠道项目，无CRM编号 | AO94: 湖南省长沙市芙蓉区朝阳路227号新浪潮电子商厦二楼左边 | AP94: liufengab | AS94: 700000003950.0 | AV94: 151 | AW94: =VLOOKUP(G94,[1]备料总表!$B:$GB,182,0) -> #N/A
A95: 20240105018155 | B95: 45296 | C95: 600000004880.0 | D95: 完结 | E95: 302-001271 | F95: PC主板 | G95: 302-001271 | H95: 2102313RPSYPMB026183 | I95: 45296 | J95: 45297 | K95: 备件库派送 | L95: 否 | M95: 0.0 | N95: 武汉 | O95: 台式机无法开机，按开机键没反应，电源灯不亮 | Q95: 302-001271 | R95: 2102313RPS6RMA042148 | S95: SF1521679954837 | T95: 45301 | V95: 王义实测：上电后马上掉电不起。 | W95: 故障件确认故障 | X95: 45323 | Y95: 华为 | Z95: SF1527634331429 | AA95: 45324 | AB95: 35 | AC95: 华为自运 | AD95: 45359 | AE95: 302-001271 | AF95: 2102313RPSZENB005239 | AG95: 45363 | AH95: 鲲泰PC产品 | AI95: D526-2台式机D2000/8/256/2/13/NMKS/KOS/V1.1 | AJ95: 青松台式机3年质保1年上门(5x9x2D) | AK95: 45145 | AL95: A220980003766400237 | AM95: 渠道PC分销（销售员：郭冬冬） | AN95: 渠道项目，无CRM编号 | AO95: 湖南省长沙市芙蓉区朝阳路227号新浪潮电子商厦二楼左边 | AP95: liufengab | AS95: 700000003951.0 | AV95: 151 | AW95: =VLOOKUP(G95,[1]备料总表!$B:$GB,182,0) -> #N/A
A96: 20240105018158 | B96: 45296 | C96: 600000004881.0 | D96: 派件出库 | E96: 301-000012 | F96: PC键鼠套装 | G96: 301-000012 | H96: MK000410M706007418 | I96: 45296 | J96: 45296 | K96: 备件库派送 | L96: 否 | M96: 100.0 | N96: 厦门 | O96: 部分按键失灵 | Q96: 301-000012 | AB96: 0 | AH96: 鲲泰PC产品 | AI96: KunTai D526-2 台式机 | AJ96: 青松台式机4年上门(5x24xND)及介质保留 | AK96: 45215 | AL96: KD000910N712000001 | AM96: 万翔PC采购项目（第一批） | AN96: HNQZF230321148 | AO96: 厦门市思明区莲花北路21号2楼 | AP96: liufengab | AQ96: 朱春霞 | AV96: 81 | AW96: =VLOOKUP(G96,[1]备料总表!$B:$GB,182,0) -> #N/A
A97: 20240105018159 | B97: 45296 | C97: 无 | D97: 完结 | E97: 302-001056 | F97: HDD | G97: 302-001056 | H97: 现场备件 | I97: 45296 | J97: 45296 | K97: 现场保障备件 | L97: 否 | M97: 0.0 | N97: 广州WA | O97: 存在告警，无法提供日志 | Q97: 302-001056 | R97: / | S97: / | W97: 故障件未复现故障 | Y97: / | Z97: / | AB97: 0 | AC97: / | AE97: / | AF97: / | AH97: 鲲泰服务器产品 | AI97: KunTai R522 服务器 | AJ97: 2U3年金牌+及介质保留和高级硬件安装 | AK97: 44873 | AL97: KS001310M804000040 | AM97: 拓展八部鲲鹏项目-5—场景12_548 | AN97: XTBZF210927205 | AO97: 广州市黄埔区建业六路10号 | AP97: liufengab | AV97: 423 | AW97: =VLOOKUP(G97,[1]备料总表!$B:$GB,182,0) -> 99-000781
A98: 20240105018160 | B98: 45296 | C98: 无 | D98: 完结 | E98: 302-001056 | F98: HDD | G98: 302-001056 | H98: 现场备件 | I98: 45296 | J98: 45296 | K98: 现场保障备件 | L98: 否 | M98: 0.0 | N98: 广州WA | O98: 存在告警，无法提供日志 | Q98: 302-001056 | R98: / | S98: / | W98: 故障件未复现故障 | Y98: / | Z98: / | AB98: 0 | AC98: / | AE98: / | AF98: / | AH98: 鲲泰服务器产品 | AI98: KunTai R522 服务器 | AJ98: 2U3年金牌+及介质保留和高级硬件安装 | AK98: 44873 | AL98: KS001310M804000021 | AM98: 拓展八部鲲鹏项目-5—场景12_548 | AN98: XTBZF210927205 | AO98: 广州市黄埔区建业六路10号 | AP98: liufengab | AV98: 423 | AW98: =VLOOKUP(G98,[1]备料总表!$B:$GB,182,0) -> 99-000781
A99: 20240105018161 | B99: 45296 | C99: 600000004882.0 | D99: 完结 | E99: 302-001627 | F99: 内存 | G99: 302-001627 | H99: 2102510049N0MC204131 | I99: 45296 | J99: 45296 | K99: 备件库派送 | L99: 否 | M99: 180.0 | N99: 广州 | O99: 服务器DIM111内存存在UCE告警，无法提供日志 | Q99: 302-001627 | R99: 210251004910MC138559 | S99: SF1419486071985 | T99: 45308 | V99: 王义实测：SP测试失败。（有留存日志） | W99: 故障件确认故障 | X99: 45321 | Y99: 华为 | Z99: 华为自取 | AA99: 45322 | AB99: 19 | AC99: 11709831.0 | AD99: 45341 | AE99: 302-001627 | AF99: 2102510049N0PB104541 | AG99: 45341 | AH99: 鲲泰服务器产品 | AI99: KunTai R522 服务器 | AJ99: 2U3年金牌+及介质保留和高级硬件安装 | AK99: 44873 | AL99: KS001310M731000067 | AM99: 拓展八部鲲鹏项目-5—场景12_548 | AN99: XTBZF210927205 | AO99: 广州市黄埔区建业六路10号 | AP99: liufengab | AS99: 700000003983.0 | AV99: 423 | AW99: =VLOOKUP(G99,[1]备料总表!$B:$GB,182,0) -> 99-001627
A100: 20240105018162 | B100: 45296 | C100: 600000004883.0 | D100: 完结 | E100: 302-001357 | F100: 主板 | G100: 302-001601 | H100: 2103050GFA10P1100001 | I100: 45296 | J100: 45296 | K100: 现场保障备件 | L100: 否 | M100: 0.0 | N100: 郑州联通 | O100: 服务器再次异常重启，iBMC内无当前告警，历史事件中存在网卡告警并异常重启记录，代码为：0x08000001、0x08000065，服务器重启后恢复，且记录中有多次CPU2健康状态异常显示，前期已派单（工单号：20231231018037）更换网卡，一周内故障再次出现 | Q100: 302-001357 | R100: 2103050FNAP0NB100223 | S100: SF2052281430011 | T100: 45301 | V100: 实测ok | W100: 故障件未复现故障 | X100: 45321 | AB100: 0 | AH100: 鲲泰服务器产品 | AI100: KunTai R722 服务器 | AJ100: 2U3年标准+及基础硬件安装 | AK100: 45014 | AL100: KS001410MC28000031 | AM100: 2022年中国联通通信云中原DC通用资源池扩容五期工程——集团总部单项工程（联 | AN100: DBQYYS221128203 | AO100: 郑州市高新区中原数据基地 王于涵 18538180936 | AP100: liufengab | AS100: 700000003952.0 | AV100: 282 | AW100: =VLOOKUP(G100,[1]备料总表!$B:$GB,182,0) -> 99-000712
...

Sheet sheet3-需求字段及处理逻辑说明-400派件补库单
A1: 是否补库 | B1: 派件日期 | C1: 料号 | D1: 描述 | E1: 名称 | F1: 物料属性 | G1: 出库库房简称 | H1: 发货数量 | I1: 捆绑料号 | J1: 补库单状态 | K1: 补库日期 | L1: 出库库房剩余库存数量 | M1: 今日武汉库存数量 | N1: 推荐补库料号 | O1: 备注 | P1: 项目 | Q1: CRM立项编号 | R1: CRM工单号 | S1: 换件单号 | T1: 序号 | U1: 转出库房编码 | V1: 转出工厂编码 | W1: 转入库房编码 | X1: 转入工厂编码 | Y1: 单据类型名称 | Z1: 外部单据号 | AA1: 配送方式（不配送，入库仓提货，出库仓发货） | AB1: 备注 | AC1: 转出物料编码 | AD1: 转出物料外部编码 | AE1: 转出库存地编码 | AF1: 转出物料正残属性（正品、残品） | AG1: 转出物料状态（正常、质检、冻结、在途） | AH1: 转出批号 | AI1: 转出生产日期（yyyy-mm-dd) | AJ1: 转出到期日期（yyyy-mm-dd) | AK1: 转出指定标签标识 | AL1: 转出自定义批属性1 | AM1: 转出自定义批属性2 | AN1: 转出自定义批属性3 | AO1: 转出自定义批属性4 | AP1: 转出自定义批属性5 | AQ1: 转入物料编码 | AR1: 转入物料外部编码 | AS1: 转入库存地编码 | AT1: 转入物料正残属性（正品、残品） | AU1: 转入物料状态（正常、质检、冻结、在途） | AV1: 转储数量 | AW1: 提货联系人 | AX1: 省 | AY1: 市 | AZ1: 提货地址 | BA1: 电话 | BB1: 手机号 | BC1: 转入批号 | BD1: 转入生产日期（yyyy-mm-dd) | BE1: 转入到期日期（yyyy-mm-dd) | BF1: 转入自定义批属性1 | BG1: 转入自定义批属性2 | BH1: 转入自定义批属性3 | BI1: 转入自定义批属性4 | BJ1: 转入自定义批属性5 | BM1: 显示界面功能上导出需求
A2: 今日勾选√，则代表今日生效需要补库，不√则代表未生效不补库 | B2: WMS--单据--出库单--高级查询（详见Sheet2序号2）--频率每日，每日拉取创建时间区间在1个月内的且单据类型“备件出库单”且过账时间为昨日已过账的，满足这些条件的则抓取系统数据，再根据系统过账日期生成对应派件日期 | C2: 根据B列派件日期条件导出的出库单明细，关联出库单明细“外部物料号”,去掉前面9个0，外加-，生成料号，需求人可自由编辑和修改此料号 | D2: 关联测算表物料基础数据“物料描述” | E2: 关联测算表物料基础数据“名称” | F2: 现阶段暂美丽手动填写，刘峰已给WMS IT团队提了标注特殊物料属性的需求，待后续IT开发完成后，再关联此字段 | G2: 关联出库单明细“库存地编码”再关联sheet4-WMS库房分配表根据“库存地编码”，得出库房简称（库存地） | H2: 根据B列导出条件获得数据，再判断当派件日期&物料号&库存简称都相同时，则汇总出库单明细“过账数量” | I2: 根据C列料号，关联测算系统物料逻辑“捆绑料号”，有捆绑料号显示捆绑料号，无捆绑料号显示原物料号 | J2: 4个选项状态：Closed,Ongoing,Cancel,Dely，当日生成的数据默认状态为：Dely：需求人可手动选择和修改状态，A列勾选后，J列补库单状态自动状态变为Closed | K2: 补库单状态当日变Closed，则补库日期自动填充当日 | L2: 根据“捆绑料号”和“库房简称（库存地）”2个条件，显示出派件库房对应当日的“各库区库存”或者“其他库区库存”的汇总后库存数量，无库存则显示0 | M2: 根据“捆绑料号”，抓取“各库区库存”汇总后的武汉库存总数，无库存则显示0 | N2: 根据“捆绑料号”，找出同一捆绑料号下多个子料号，再判断“各库区库存”中武汉库中哪个子料号库存数量最多，则显示出对应料号，如库存都为0，则显示0 | O2: 可填写备注内容 | P2: 逻辑同Q列，根据Q列CRM立项编号，同步抓取出计算维修收发货报表1里的AM列“项目名称”。若条件不成立，则由需求人自己手动填写 | Q2: ①抓取计算维修收发货报表1表里，B列“报修时间”离当前日期最近的。②把维修收发货报表1表G列“备件物料号”，关联测算表“捆绑料号”转化成对应“捆绑料号”，然后再判断：当维修报表的捆绑料号=此表I列捆绑料号时，满足条件。③本表的派件库房简称（库存地）和维修收发货报表1表N列“备件出库地”相同，条件成立。最后根据①②③条件都成立，则抓取出维修收发货报表1对应CRM立项编号。若条件不成立，则显示“无”，由需求人自己手动填写。 | R2: 逻辑同Q列，根据Q列CRM立项编号，同步抓取出计算维修收发货报表1里的A列“CRM工单号”。若条件不成立，则空由需求人自己手动填写 | S2: 逻辑同Q列，根据Q列CRM立项编号，同步抓取出计算维修收发货报表1里的c列“CRM工单号”。若条件不成立，则由需求人自己手动填写 | T2: 空 | U2: 自动填充：BJ-WHBJC | V2: 自动填充：1200004260 | W2: 根据G列“派件库房简称（库存地）”，关联“sheet4-WMS库房分配表”派件库房简称（库存地）”，得出“库房编码” | X2: 自动填充：1200004260 | Y2: 自动填充：备件库间转储 | Z2: 自动创建外部单据号逻辑说明：创建规则KJ+当日补库日期的年月日+09开始往后顺延。首次导入时一个“转入库房编码”对应一个外部单据号（简单理解：1个城市对应1个外包单据号），当日同一批次导入“转入库房编码”库房编码相同时，则外部单据号相同（简单理解：同一批次的，相同城市的外部单据号也相同）。如遇今日二次导入或者多次导入，不是同一个批次导入的，编码生成和分配规律同上。不同之处在于同一个城市不同批次导入的，不能再延用上一次已经生成外包单据号，需要从上一批次最后一单外包单据号顺延之后生产新建外部单据号给不同批次使用 | AA2: 自动填充：出库仓发货 | AB2: 空 | AC2: 空 | AD2: 按C列料号，自动去“-”，302前面自动填充9个0，如下图案例 | AE2: 自动填充：KCDBJ-WHBJC | AF2: 自动填充：正品 | AG2: 自动填充：正常 | AR2: 等于AD列转出物料外部编码 | AS2: 根据W列“转入库房编码”，关联“sheet4-WMS库房分配表”，得出“转入库存地编码” | AT2: 自动填充;正品 | AU2: 自动填充;正常 | AV2: 等于H列“发货数量”，需求人可以手工修改 | BM2: ①页面上，有派件日期时间区间的选项和补库单状态，需求人可以根据日期选择，导出。 ②A列-S列字段都可输入搜索框，根据条件筛选出所需数据并导出 ③前期开发测试阶段和试运营阶段，可以通过手动导出数据，上传至WMS库间单形成发料单。试运行无误后需留有接口，试运行无误后，系统需跟进需求人A列√后，自动导入补库单导WMS系统形成库房发料单。
A3: √ | B3: 45504 | C3: 302-000910 | D3: =VLOOKUP(C3,[1]备料总表!$B:$GB,2,0) -> SP382网卡25GE(Mellanox CX5)DP(无光模块) | E3: =VLOOKUP(C3,[1]备料总表!$B:$GB,4,0) -> 网卡 | F3: 建行专用，*** | G3: 南京 | H3: 1 | I3: =VLOOKUP(C3,[1]备料总表!$B:$GB,182,0) -> 99-000910 | J3: Closed | K3: 45504 | L3: 2 | M3: 10 | N3: 302-000910 | U3: BJ-WHBJC | V3: 1200004260 | W3: BJ-NJBJC | X3: 1200004260 | Y3: 备件库间转储 | Z3: KJ2024073109 | AA3: 出库仓发货 | AD3: 000000000302000910 | AE3: KCDBJ-WHBJC | AF3: 正品 | AG3: 正常 | AR3: 000000000302000910 | AS3: KCDBJ-NJBJC | AT3: 正品 | AU3: 正常 | AV3: 1
A4: √ | B4: 45504 | C4: 302-001799 | D4: =VLOOKUP(C4,[1]备料总表!$B:$GB,2,0) -> 光模块-SFP28-25G-多模(850nm,0.1km,LC)-NDD | E4: =VLOOKUP(C4,[1]备料总表!$B:$GB,4,0) -> 光模块 | G4: 南京 | H4: 2 | I4: =VLOOKUP(C4,[1]备料总表!$B:$GB,182,0) -> 99-000380 | J4: Closed | K4: 45504 | L4: 5 | M4: 15 | N4: 302-000380 | P4: 移动网络云五期集采项目 | Q4: XTBYYS230516121 | R4: 20240702021954 | S4: 600000009273.0 | U4: BJ-WHBJC | V4: 1200004260 | W4: BJ-NJBJC | X4: 1200004260 | Y4: 备件库间转储 | Z4: KJ2024073109 | AA4: 出库仓发货 | AD4: 000000000302001799 | AE4: KCDBJ-WHBJC | AF4: 正品 | AG4: 正常 | AR4: 000000000302001799 | AS4: KCDBJ-NJBJC | AT4: 正品 | AU4: 正常 | AV4: 2
A5: √ | B5: 45504 | C5: 302-000910 | D5: =VLOOKUP(C5,[1]备料总表!$B:$GB,2,0) -> SP382网卡25GE(Mellanox CX5)DP(无光模块) | E5: =VLOOKUP(C5,[1]备料总表!$B:$GB,4,0) -> 网卡 | G5: 合肥 | H5: 1 | I5: =VLOOKUP(C5,[1]备料总表!$B:$GB,182,0) -> 99-000910 | J5: Closed | K5: 45504 | U5: BJ-WHBJC | V5: 1200004260 | W5: BJ-HFBJC | X5: 1200004260 | Y5: 备件库间转储 | Z5: KJ2024073110 | AA5: 出库仓发货 | AD5: 000000000302000910 | AE5: KCDBJ-WHBJC | AF5: 正品 | AG5: 正常 | AR5: 000000000302000910 | AS5: KCDBJ-HFBJC | AT5: 正品 | AU5: 正常 | AV5: 1
A6: √ | B6: 45504 | C6: 302-003132 | D6: =VLOOKUP(C6,[1]备料总表!$B:$GB,2,0) -> 光模块-SFP28-25G-多模(850nm,0.3km,LC)-HX | E6: =VLOOKUP(C6,[1]备料总表!$B:$GB,4,0) -> 光模块 | G6: 合肥 | H6: 1 | I6: =VLOOKUP(C6,[1]备料总表!$B:$GB,182,0) -> 99-000380 | J6: Closed | K6: 45504 | U6: BJ-WHBJC | V6: 1200004260 | W6: BJ-HFBJC | X6: 1200004260 | Y6: 备件库间转储 | Z6: KJ2024073110 | AA6: 出库仓发货 | AD6: 000000000302003132 | AE6: KCDBJ-WHBJC | AF6: 正品 | AG6: 正常 | AR6: 000000000302003132 | AS6: KCDBJ-HFBJC | AT6: 正品 | AU6: 正常 | AV6: 1
A7: √ | B7: 45504 | C7: 302-001797 | D7: =VLOOKUP(C7,[1]备料总表!$B:$GB,2,0) -> 光模块-SFP+-10G-多模(850nm,0.3km,LC)-NDD | E7: =VLOOKUP(C7,[1]备料总表!$B:$GB,4,0) -> 光模块 | G7: 长沙 | H7: 1 | I7: =VLOOKUP(C7,[1]备料总表!$B:$GB,182,0) -> 99-000381 | J7: Closed | K7: 45504
B8: 45504 | C8: 302-001043 | D8: =VLOOKUP(C8,[1]备料总表!$B:$GB,2,0) -> S硬盘8T-3.5SATA-6G7.2K-256M-DZ V1.0 | E8: =VLOOKUP(C8,[1]备料总表!$B:$GB,4,0) -> 硬盘 | G8: 杭州 | H8: 1 | I8: =VLOOKUP(C8,[1]备料总表!$B:$GB,182,0) -> 99-001043 | J8: Dely
A9: √ | B9: 45504 | C9: 302-001701 | D9: =VLOOKUP(C9,[1]备料总表!$B:$GB,2,0) -> SAS线-RAID卡专用1分2 mini SAS-0.8&0.7m | E9: =VLOOKUP(C9,[1]备料总表!$B:$GB,4,0) -> 线缆 | G9: 佛山 | H9: 1 | I9: =C9 -> 302-001701 | J9: Closed | K9: 45504
A10: √ | B10: 45504 | C10: 302-000289 | D10: =VLOOKUP(C10,[1]备料总表!$B:$GB,2,0) -> 硬盘背板-RH2288H V3-BC11THBHB | E10: =VLOOKUP(C10,[1]备料总表!$B:$GB,4,0) -> 机箱/硬盘背板 | G10: 佛山 | H10: 1 | I10: =VLOOKUP(C10,[1]备料总表!$B:$GB,182,0) -> 88-000289 | J10: Closed | K10: 45504
A11: √ | B11: 45504 | C11: 302-002638 | D11: =VLOOKUP(C11,[1]备料总表!$B:$GB,2,0) -> S主板 S920X00-2*7265F(64C@3.0)-AH-VD | E11: =VLOOKUP(C11,[1]备料总表!$B:$GB,4,0) -> 主板 | G11: 福州 | H11: 1 | I11: =VLOOKUP(C11,[1]备料总表!$B:$GB,182,0) -> 99-001877 | J11: Closed | K11: 45504
B12: 45504 | C12: 302-000149 | D12: =VLOOKUP(C12,[1]备料总表!$B:$GB,2,0) -> Riser3模组 2*16X(X8) | E12: =VLOOKUP(C12,[1]备料总表!$B:$GB,4,0) -> Riser模组 | G12: 南宁 | H12: 1 | I12: =VLOOKUP(C12,[1]备料总表!$B:$GB,182,0) -> 99-000149 | J12: Dely
B13: 45504 | C13: 302-002612 | D13: =VLOOKUP(C13,[1]备料总表!$B:$GB,2,0) -> RAID标卡9560-8i-4G PCIe4.0x8 NMP-HW | E13: =VLOOKUP(C13,[1]备料总表!$B:$GB,4,0) -> RAID卡 | G13: 南宁 | H13: 1 | I13: =VLOOKUP(C13,[1]备料总表!$B:$GB,182,0) -> 99-001705 | J13: Dely
B14: 45504 | C14: 302-000739 | D14: =VLOOKUP(C14,[1]备料总表!$B:$GB,2,0) -> 网卡25G双口SFP28-SP380-CX-4 Lx无光模块 | E14: =VLOOKUP(C14,[1]备料总表!$B:$GB,4,0) -> 网卡 | G14: 济南 | H14: 1 | I14: =VLOOKUP(C14,[1]备料总表!$B:$GB,182,0) -> 99-000739 | J14: Dely
B15: 45504 | C15: 302-001243 | D15: =VLOOKUP(C15,[1]备料总表!$B:$GB,2,0) -> S硬盘16T-3.5SATA-6G7.2K-512M-XS V1.0 | E15: =VLOOKUP(C15,[1]备料总表!$B:$GB,4,0) -> 硬盘 | G15: 北京 | H15: 1 | I15: =VLOOKUP(C15,[1]备料总表!$B:$GB,182,0) -> 99-001163 | J15: Dely
A16: √ | B16: 45482 | C16: 302-000160 | D16: =VLOOKUP(C16,[1]备料总表!$B:$GB,2,0) -> 网卡10Gb双口SFP+Mellanox MT27712A0+2光模 | E16: =VLOOKUP(C16,[1]备料总表!$B:$GB,4,0) -> 网卡 | G16: 枣庄联通 | H16: 1 | I16: =VLOOKUP(C16,[1]备料总表!$B:$GB,182,0) -> 99-000160 | J16: Closed | K16: 45483
A17: √ | B17: 45482 | C17: 302-001705 | D17: =VLOOKUP(C17,[1]备料总表!$B:$GB,2,0) -> RAID标卡 9560-8i-4G Cache | E17: =VLOOKUP(C17,[1]备料总表!$B:$GB,4,0) -> RAID卡 | G17: 南京 | H17: 1 | I17: =VLOOKUP(C17,[1]备料总表!$B:$GB,182,0) -> 99-001705 | J17: Closed | K17: 45483
A18: √ | B18: 45482 | C18: 302-001815 | D18: =VLOOKUP(C18,[1]备料总表!$B:$GB,2,0) -> S硬盘4T-3.5SATA-6G7.2K-256M-XJ V1.0 | E18: =VLOOKUP(C18,[1]备料总表!$B:$GB,4,0) -> 硬盘 | G18: 长沙 | H18: 1 | I18: =VLOOKUP(C18,[1]备料总表!$B:$GB,182,0) -> 99-001049 | J18: Closed | K18: 45483
A19: √ | B19: 45482 | C19: 302-001164 | D19: =VLOOKUP(C19,[1]备料总表!$B:$GB,2,0) -> RAID标卡 9460-8i PCIe3.0X8-2GB Cache | E19: =VLOOKUP(C19,[1]备料总表!$B:$GB,4,0) -> RAID卡 | G19: 长沙 | H19: 1 | I19: =VLOOKUP(C19,[1]备料总表!$B:$GB,182,0) -> 99-001066 | J19: Closed | K19: 45483
A20: √ | B20: 45482 | C20: 302-000781 | D20: =VLOOKUP(C20,[1]备料总表!$B:$GB,2,0) -> S硬盘2.4T-2.5SAS-12G10K-128M-DZ V1.0 | E20: =VLOOKUP(C20,[1]备料总表!$B:$GB,4,0) -> 硬盘 | G20: 上海 | H20: 1 | I20: =VLOOKUP(C20,[1]备料总表!$B:$GB,182,0) -> 99-000781 | J20: Closed | K20: 45483
A21: √ | B21: 45482 | C21: 302-000544 | D21: =VLOOKUP(C21,[1]备料总表!$B:$GB,2,0) -> S内存DDR4-32G-2933-2Rank(2G*4bit) MG | E21: =VLOOKUP(C21,[1]备料总表!$B:$GB,4,0) -> 内存 | G21: 福州 | H21: 1 | I21: =VLOOKUP(C21,[1]备料总表!$B:$GB,182,0) -> 99-001067 | J21: Closed | K21: 45483
A22: √ | B22: 45482 | C22: 302-000448 | D22: =VLOOKUP(C22,[1]备料总表!$B:$GB,2,0) -> 服务器白金900W B版本交流电源 | E22: =VLOOKUP(C22,[1]备料总表!$B:$GB,4,0) -> 电源 | G22: 广州 | H22: 1 | I22: =VLOOKUP(C22,[1]备料总表!$B:$GB,182,0) -> 99-000448 | J22: Closed | K22: 45483
B23: 45482 | C23: 302-001800 | D23: =VLOOKUP(C23,[1]备料总表!$B:$GB,2,0) -> SSD H101-IY-256G-SATA-6G-2.5读写HD V1.0 | E23: =VLOOKUP(C23,[1]备料总表!$B:$GB,4,0) -> 硬盘 | G23: 西安 | H23: 1 | I23: =C23 -> 302-001800 | J23: Dely
A24: √ | B24: 45482 | C24: 302-000985 | D24: =VLOOKUP(C24,[1]备料总表!$B:$GB,2,0) -> S内存DDR4-32G-2933-1Rx4-RD HLS V1.0 | E24: =VLOOKUP(C24,[1]备料总表!$B:$GB,4,0) -> 内存 | F24: 余3 | G24: 呼和浩特联通云基地 | H24: 1 | I24: =C24 -> 302-000985 | J24: Closed | K24: 45503
A25: √ | B25: 45483 | C25: 302-000781 | D25: =VLOOKUP(C25,[1]备料总表!$B:$GB,2,0) -> S硬盘2.4T-2.5SAS-12G10K-128M-DZ V1.0 | E25: =VLOOKUP(C25,[1]备料总表!$B:$GB,4,0) -> 硬盘 | G25: 上海 | H25: 4 | I25: =VLOOKUP(C25,[1]备料总表!$B:$GB,182,0) -> 99-000781 | J25: Closed | K25: 45483
A26: √ | B26: 45483 | C26: 302-002116 | D26: =VLOOKUP(C26,[1]备料总表!$B:$GB,2,0) -> FC HBA卡-32Gb-LPe32002-AP-双口-SFP+2光模块 | E26: =VLOOKUP(C26,[1]备料总表!$B:$GB,4,0) -> HBA卡 | G26: 合肥 | H26: 1 | I26: =VLOOKUP(C26,[1]备料总表!$B:$GB,182,0) -> 99-001187 | J26: Closed | K26: 45483
A27: √ | B27: 45483 | C27: 302-001813 | D27: =VLOOKUP(C27,[1]备料总表!$B:$GB,2,0) -> S内存DDR4-32G-3200-2Rx4-RD SX V1.0 | E27: =VLOOKUP(C27,[1]备料总表!$B:$GB,4,0) -> 内存 | G27: 合肥 | H27: 1 | I27: =VLOOKUP(C27,[1]备料总表!$B:$GB,182,0) -> 99-001115 | J27: Closed | K27: 45483
A28: √ | B28: 45483 | C28: 302-001040 | D28: =VLOOKUP(C28,[1]备料总表!$B:$GB,2,0) -> S硬盘1.2T-2.5SAS-12G10K-128M-DZ V1.1 | E28: =VLOOKUP(C28,[1]备料总表!$B:$GB,4,0) -> 硬盘 | G28: 杭州 | H28: 1 | I28: =VLOOKUP(C28,[1]备料总表!$B:$GB,182,0) -> 99-001040 | J28: Closed | K28: 45483
A29: √ | B29: 45483 | C29: 302-001705 | D29: =VLOOKUP(C29,[1]备料总表!$B:$GB,2,0) -> RAID标卡 9560-8i-4G Cache | E29: =VLOOKUP(C29,[1]备料总表!$B:$GB,4,0) -> RAID卡 | G29: 杭州 | H29: 1 | I29: =VLOOKUP(C29,[1]备料总表!$B:$GB,182,0) -> 99-001705 | J29: Closed | K29: 45483
A30: √ | B30: 45483 | C30: 302-001701 | D30: =VLOOKUP(C30,[1]备料总表!$B:$GB,2,0) -> SAS线-RAID卡专用1分2 mini SAS-0.8&0.7m | E30: =VLOOKUP(C30,[1]备料总表!$B:$GB,4,0) -> 线缆 | G30: 杭州 | H30: 1 | I30: =C30 -> 302-001701 | J30: Closed | K30: 45483
A31: √ | B31: 45483 | C31: 302-002587 | D31: =VLOOKUP(C31,[1]备料总表!$B:$GB,2,0) -> 背板-S920X00-12*3.5 双RAID EXP硬盘背板 | E31: =VLOOKUP(C31,[1]备料总表!$B:$GB,4,0) -> 机箱/硬盘背板 | G31: 杭州 | H31: 1 | I31: =VLOOKUP(C31,[1]备料总表!$B:$GB,182,0) -> 88-000288 | J31: Closed | K31: 45483
B32: 45483 | C32: 302-001241 | D32: =VLOOKUP(C32,[1]备料总表!$B:$GB,2,0) -> S硬盘8T-3.5SATA-6G7.2K-256M-XS-[AVAP] | E32: =VLOOKUP(C32,[1]备料总表!$B:$GB,4,0) -> 硬盘 | G32: 杭州 | H32: 1 | I32: =VLOOKUP(C32,[1]备料总表!$B:$GB,182,0) -> 99-001043 | J32: Cancel
A33: √ | B33: 45483 | C33: 302-001153 | D33: =VLOOKUP(C33,[1]备料总表!$B:$GB,2,0) -> FC HBA卡-16Gb-LPe31002-双口-SFP+2光模块 | E33: =VLOOKUP(C33,[1]备料总表!$B:$GB,4,0) -> HBA卡 | G33: 佛山 | H33: 1 | I33: =VLOOKUP(C33,[1]备料总表!$B:$GB,182,0) -> 99-001019 | J33: Closed | K33: 45483
A34: √ | B34: 45483 | C34: 302-001627 | D34: =VLOOKUP(C34,[1]备料总表!$B:$GB,2,0) -> S内存DDR4-32GB-3200-2Rank(2G*4bit) HLS | E34: =VLOOKUP(C34,[1]备料总表!$B:$GB,4,0) -> 内存 | G34: 福州 | H34: 1 | I34: =VLOOKUP(C34,[1]备料总表!$B:$GB,182,0) -> 99-001627 | J34: Closed | K34: 45483
A35: √ | B35: 45483 | C35: 302-001844 | D35: =VLOOKUP(C35,[1]备料总表!$B:$GB,2,0) -> SAS线-RAID卡专用1分2 mini SAS-1.0m&0.9m | E35: =VLOOKUP(C35,[1]备料总表!$B:$GB,4,0) -> 线缆 | G35: 福州 | H35: 1 | I35: =VLOOKUP(C35,[1]备料总表!$B:$GB,182,0) -> 99-001844 | J35: Closed | K35: 45483
A36: √ | B36: 45483 | C36: 302-000288 | D36: =VLOOKUP(C36,[1]备料总表!$B:$GB,2,0) -> 硬盘背板-RH2288H V3-BC11THBQB | E36: =VLOOKUP(C36,[1]备料总表!$B:$GB,4,0) -> 机箱/硬盘背板 | G36: 福州 | H36: 1 | I36: =VLOOKUP(C36,[1]备料总表!$B:$GB,182,0) -> 88-000288 | J36: Closed | K36: 45483
A37: √ | B37: 45483 | C37: 302-000983 | D37: =VLOOKUP(C37,[1]备料总表!$B:$GB,2,0) -> SSD PM1725B读写6.4TB-NVMe 2.5 无托企业级 | E37: =VLOOKUP(C37,[1]备料总表!$B:$GB,4,0) -> 硬盘 | G37: 厦门 | H37: 1 | I37: =VLOOKUP(C37,[1]备料总表!$B:$GB,182,0) -> 99-002843 | J37: Closed | K37: 45484 | O37: 补替代料2843
A38: √ | B38: 45483 | C38: 302-001627 | D38: =VLOOKUP(C38,[1]备料总表!$B:$GB,2,0) -> S内存DDR4-32GB-3200-2Rank(2G*4bit) HLS | E38: =VLOOKUP(C38,[1]备料总表!$B:$GB,4,0) -> 内存 | G38: 汕头 | H38: 1 | I38: =VLOOKUP(C38,[1]备料总表!$B:$GB,182,0) -> 99-001627 | J38: Closed | K38: 45484
A39: √ | B39: 45483 | C39: 302-001241 | D39: =VLOOKUP(C39,[1]备料总表!$B:$GB,2,0) -> S硬盘8T-3.5SATA-6G7.2K-256M-XS-[AVAP] | E39: =VLOOKUP(C39,[1]备料总表!$B:$GB,4,0) -> 硬盘 | F39: 余10 | G39: 南宁 | H39: 2 | I39: =VLOOKUP(C39,[1]备料总表!$B:$GB,182,0) -> 99-001043 | J39: Closed | K39: 45492
A40: √ | B40: 45483 | C40: 302-002049 | D40: =VLOOKUP(C40,[1]备料总表!$B:$GB,2,0) -> S硬盘8T-3.5SATA-6G7.2K-256M-XJ-[AVAP] | E40: =VLOOKUP(C40,[1]备料总表!$B:$GB,4,0) -> 硬盘 | F40: 余7 | G40: 成都 | H40: 1 | I40: =VLOOKUP(C40,[1]备料总表!$B:$GB,182,0) -> 99-001043 | J40: Closed | K40: 45492
A41: √ | B41: 45483 | C41: 302-000987 | D41: =VLOOKUP(C41,[1]备料总表!$B:$GB,2,0) -> S内存DDR4-32G-3200-2Rx8-RD ZG V1.0 | E41: =VLOOKUP(C41,[1]备料总表!$B:$GB,4,0) -> 内存 | G41: 成都 | H41: 1 | I41: =C41 -> 302-000987 | J41: Closed | K41: 45483
A42: √ | B42: 45483 | C42: 302-001627 | D42: =VLOOKUP(C42,[1]备料总表!$B:$GB,2,0) -> S内存DDR4-32GB-3200-2Rank(2G*4bit) HLS | E42: =VLOOKUP(C42,[1]备料总表!$B:$GB,4,0) -> 内存 | G42: 西安 | H42: 1 | I42: =VLOOKUP(C42,[1]备料总表!$B:$GB,182,0) -> 99-001627 | J42: Closed | K42: 45483
A43: √ | B43: 45483 | C43: 302-002062 | D43: =VLOOKUP(C43,[1]备料总表!$B:$GB,2,0) -> SSD PM9A3-3.84TB-NVMe4.0-2.5读取SX V1.0 | E43: =VLOOKUP(C43,[1]备料总表!$B:$GB,4,0) -> 硬盘 | G43: 北京 | H43: 1 | I43: =VLOOKUP(C43,[1]备料总表!$B:$GB,182,0) -> 99-002062 | J43: Closed | K43: 45483
A44: √ | B44: 45483 | C44: 302-001043 | D44: =VLOOKUP(C44,[1]备料总表!$B:$GB,2,0) -> S硬盘8T-3.5SATA-6G7.2K-256M-DZ V1.0 | E44: =VLOOKUP(C44,[1]备料总表!$B:$GB,4,0) -> 硬盘 | F44: 余6 | G44: 呼和浩特联通云基地 | H44: 1 | I44: =VLOOKUP(C44,[1]备料总表!$B:$GB,182,0) -> 99-001043 | J44: Closed | K44: 45503
A45: √ | B45: 45483 | C45: 302-001655 | D45: =VLOOKUP(C45,[1]备料总表!$B:$GB,2,0) -> 3508/3516 RAID卡超级电容 | E45: =VLOOKUP(C45,[1]备料总表!$B:$GB,4,0) -> 超级电容 | G45: 北京 | H45: 4 | I45: =VLOOKUP(C45,[1]备料总表!$B:$GB,182,0) -> 99-001655 | J45: Closed | K45: 45483
A46: √ | B46: 45483 | C46: 302-000910 | D46: =VLOOKUP(C46,[1]备料总表!$B:$GB,2,0) -> SP382网卡25GE(Mellanox CX5)DP(无光模块) | E46: =VLOOKUP(C46,[1]备料总表!$B:$GB,4,0) -> 网卡 | G46: 北京 | H46: 1 | I46: =VLOOKUP(C46,[1]备料总表!$B:$GB,182,0) -> 99-000910 | J46: Closed | K46: 45483
A47: √ | B47: 45483 | C47: 302-000380 | D47: =VLOOKUP(C47,[1]备料总表!$B:$GB,2,0) -> XGIGA光模块-SFP28-25G多模850nm,0.1km,LC | E47: =VLOOKUP(C47,[1]备料总表!$B:$GB,4,0) -> 光模块 | G47: 北京 | H47: 1 | I47: =VLOOKUP(C47,[1]备料总表!$B:$GB,182,0) -> 99-000380 | J47: Closed | K47: 45490
A48: √ | B48: 45483 | C48: 302-000426 | D48: =VLOOKUP(C48,[1]备料总表!$B:$GB,2,0) -> #S主板S920X02-4*7260(64C@2.6)-AD-1711 | E48: =VLOOKUP(C48,[1]备料总表!$B:$GB,4,0) -> 主板 | G48: 北京亦庄 | H48: 1 | I48: =VLOOKUP(C48,[1]备料总表!$B:$GB,182,0) -> 99-000426 | J48: Closed | K48: 45488 | O48: 2024/7/15补426把战国测试环境发走了
A49: √ | B49: 45484 | C49: 302-001112 | D49: =VLOOKUP(C49,[1]备料总表!$B:$GB,2,0) -> 硬盘16T-SATA 6Gb/s-7.2K-3.5无托 XJ | E49: =VLOOKUP(C49,[1]备料总表!$B:$GB,4,0) -> 硬盘 | G49: 上海 | H49: 1 | I49: =VLOOKUP(C49,[1]备料总表!$B:$GB,182,0) -> 99-001163 | J49: Closed | K49: 45489
A50: √ | B50: 45484 | C50: 302-001346 | D50: =VLOOKUP(C50,[1]备料总表!$B:$GB,2,0) -> SSD ES3521AV6-480G-SATA-6G-2.5读取HW V1.3 | E50: =VLOOKUP(C50,[1]备料总表!$B:$GB,4,0) -> 硬盘 | G50: 长沙 | H50: 1 | I50: =VLOOKUP(C50,[1]备料总表!$B:$GB,182,0) -> 99-001346 | J50: Closed | K50: 45484
A51: √ | B51: 45484 | C51: 302-001332 | D51: =VLOOKUP(C51,[1]备料总表!$B:$GB,2,0) -> RAID标卡-2GB 9460-8i-PCIe | E51: =VLOOKUP(C51,[1]备料总表!$B:$GB,4,0) -> RAID卡 | G51: 杭州 | H51: 1 | I51: =VLOOKUP(C51,[1]备料总表!$B:$GB,182,0) -> 99-001066 | J51: Closed | K51: 45484
A52: √ | B52: 45484 | C52: 302-000781 | D52: =VLOOKUP(C52,[1]备料总表!$B:$GB,2,0) -> S硬盘2.4T-2.5SAS-12G10K-128M-DZ V1.0 | E52: =VLOOKUP(C52,[1]备料总表!$B:$GB,4,0) -> 硬盘 | G52: 广州 | H52: 1 | I52: =VLOOKUP(C52,[1]备料总表!$B:$GB,182,0) -> 99-000781 | J52: Closed | K52: 45485
A53: √ | B53: 45484 | C53: 302-001163 | D53: =VLOOKUP(C53,[1]备料总表!$B:$GB,2,0) -> 硬盘16T-SATA 6Gb/s-7.2K-3.5无托 DZ | E53: =VLOOKUP(C53,[1]备料总表!$B:$GB,4,0) -> 硬盘 | G53: 广州 | H53: 1 | I53: =VLOOKUP(C53,[1]备料总表!$B:$GB,182,0) -> 99-001163 | J53: Closed | K53: 45485
A54: √ | B54: 45484 | C54: 302-001070 | D54: =VLOOKUP(C54,[1]备料总表!$B:$GB,2,0) -> S硬盘4T-3.5SATA-6G7.2K-256M-XS V1.0 | E54: =VLOOKUP(C54,[1]备料总表!$B:$GB,4,0) -> 硬盘 | G54: 肇庆 | H54: 1 | I54: =VLOOKUP(C54,[1]备料总表!$B:$GB,182,0) -> 99-001049 | J54: Closed | K54: 45484
A55: √ | B55: 45484 | C55: 302-001240 | D55: =VLOOKUP(C55,[1]备料总表!$B:$GB,2,0) -> S硬盘16T-3.5SATA-6G7.2K-256M-XJ-[AVAP] | E55: =VLOOKUP(C55,[1]备料总表!$B:$GB,4,0) -> 硬盘 | G55: 西安 | H55: 1 | I55: =VLOOKUP(C55,[1]备料总表!$B:$GB,182,0) -> 99-001163 | J55: Closed | K55: 45484
A56: √ | B56: 45484 | C56: 302-000179 | D56: =VLOOKUP(C56,[1]备料总表!$B:$GB,2,0) -> 高速电缆内部Mini SAS HD 0.9m 弯-直 | E56: =VLOOKUP(C56,[1]备料总表!$B:$GB,4,0) -> 线缆 | G56: 西安 | H56: 1 | I56: =C56 -> 302-000179 | J56: Closed | K56: 45484
A57: √ | B57: 45484 | C57: 302-002660 | D57: =VLOOKUP(C57,[1]备料总表!$B:$GB,2,0) -> 4U机箱前置硬盘背板-24 | E57: =VLOOKUP(C57,[1]备料总表!$B:$GB,4,0) -> 机箱/硬盘背板 | G57: 西安 | H57: 1 | I57: =VLOOKUP(C57,[1]备料总表!$B:$GB,182,0) -> 88-002660 | J57: Closed | K57: 45484
A58: √ | B58: 45484 | C58: 302-000296 | D58: =VLOOKUP(C58,[1]备料总表!$B:$GB,2,0) -> 12*3.5英寸硬盘背板-BC82HBBC | E58: =VLOOKUP(C58,[1]备料总表!$B:$GB,4,0) -> 机箱/硬盘背板 | G58: 西安 | H58: 1 | I58: =VLOOKUP(C58,[1]备料总表!$B:$GB,182,0) -> 88-000296 | J58: Closed | K58: 45484
A59: √ | B59: 45484 | C59: 302-001582 | D59: =VLOOKUP(C59,[1]备料总表!$B:$GB,2,0) -> 9440-8i RAID标卡-PCIE 3.0 X8 -no cache | E59: =VLOOKUP(C59,[1]备料总表!$B:$GB,4,0) -> RAID卡 | G59: 西安 | H59: 1 | I59: =VLOOKUP(C59,[1]备料总表!$B:$GB,182,0) -> 99-000135 | J59: Closed | K59: 45484
A60: √ | B60: 45484 | C60: 302-000160 | D60: =VLOOKUP(C60,[1]备料总表!$B:$GB,2,0) -> 网卡10Gb双口SFP+Mellanox MT27712A0+2光模 | E60: =VLOOKUP(C60,[1]备料总表!$B:$GB,4,0) -> 网卡 | G60: 西安 | H60: 1 | I60: =VLOOKUP(C60,[1]备料总表!$B:$GB,182,0) -> 99-000160 | J60: Closed | K60: 45484
A61: √ | B61: 45484 | C61: 302-000775 | D61: =VLOOKUP(C61,[1]备料总表!$B:$GB,2,0) -> SSD PM883-480G-SATA-6G-2.5读取SX V1.0 | E61: =VLOOKUP(C61,[1]备料总表!$B:$GB,4,0) -> 硬盘 | G61: 西安 | H61: 1 | I61: =VLOOKUP(C61,[1]备料总表!$B:$GB,182,0) -> 99-000750 | J61: Closed | K61: 45484
A62: √ | B62: 45484 | C62: 302-001862 | D62: =VLOOKUP(C62,[1]备料总表!$B:$GB,2,0) -> S内存DDR4-64G-3200-2Rx4-RD HLS V1.0 | E62: =VLOOKUP(C62,[1]备料总表!$B:$GB,4,0) -> 内存 | G62: 廊坊软通 | H62: 1 | I62: =VLOOKUP(C62,[1]备料总表!$B:$GB,182,0) -> 99-001862 | J62: Closed | K62: 45484
A63: √ | B63: 45485 | C63: 302-000864 | D63: =VLOOKUP(C63,[1]备料总表!$B:$GB,2,0) -> 固态盘-3840G-SATA PM883 2.5无托 | E63: =VLOOKUP(C63,[1]备料总表!$B:$GB,4,0) -> 硬盘 | G63: 上海 | H63: 2 | I63: =VLOOKUP(C63,[1]备料总表!$B:$GB,182,0) -> 99-000864 | J63: Closed | K63: 45489
A64: √ | B64: 45485 | C64: 302-003146 | D64: =VLOOKUP(C64,[1]备料总表!$B:$GB,2,0) -> 制成板-BP52 V5-BC11THBKD-24硬盘背板 | E64: =VLOOKUP(C64,[1]备料总表!$B:$GB,4,0) -> 机箱/硬盘背板 | G64: 上海 | H64: 2 | I64: =VLOOKUP(C64,[1]备料总表!$B:$GB,182,0) -> 88-002660 | J64: Closed | K64: 45485
A65: √ | B65: 45485 | C65: 302-000296 | D65: =VLOOKUP(C65,[1]备料总表!$B:$GB,2,0) -> 12*3.5英寸硬盘背板-BC82HBBC | E65: =VLOOKUP(C65,[1]备料总表!$B:$GB,4,0) -> 机箱/硬盘背板 | G65: 上海 | H65: 2 | I65: =VLOOKUP(C65,[1]备料总表!$B:$GB,182,0) -> 88-000296 | J65: Closed | K65: 45485
A66: √ | B66: 45485 | C66: 302-000730 | D66: =VLOOKUP(C66,[1]备料总表!$B:$GB,2,0) -> IT信号线0.75m-4U-EXP-S920X00 | E66: =VLOOKUP(C66,[1]备料总表!$B:$GB,4,0) -> 线缆 | G66: 上海 | H66: 1 | I66: =C66 -> 302-000730 | J66: Closed | K66: 45489
A67: √ | B67: 45485 | C67: 302-000726 | D67: =VLOOKUP(C67,[1]备料总表!$B:$GB,2,0) -> Mini SAS 4i线0.86m-4U-EXP-S920X00 | E67: =VLOOKUP(C67,[1]备料总表!$B:$GB,4,0) -> 线缆 | G67: 上海 | H67: 1 | I67: =C67 -> 302-000726 | J67: Closed | K67: 45489
A68: √ | B68: 45485 | C68: 302-000308 | D68: =VLOOKUP(C68,[1]备料总表!$B:$GB,2,0) -> 监控和告警电缆-信号电缆-0.3m | E68: =VLOOKUP(C68,[1]备料总表!$B:$GB,4,0) -> 线缆 | G68: 上海 | H68: 1 | I68: =C68 -> 302-000308 | J68: Closed | K68: 45489
A69: √ | B69: 45485 | C69: 302-000729 | D69: =VLOOKUP(C69,[1]备料总表!$B:$GB,2,0) -> IT信号线0.36m-EXP-S920X00/S00 | E69: =VLOOKUP(C69,[1]备料总表!$B:$GB,4,0) -> 线缆 | G69: 上海 | H69: 1 | I69: =C69 -> 302-000729 | J69: Closed | K69: 45489
A70: √ | B70: 45485 | C70: 302-000734 | D70: =VLOOKUP(C70,[1]备料总表!$B:$GB,2,0) -> 电源电缆-1.0m&0.5m-S920X00-4U- EXP | E70: =VLOOKUP(C70,[1]备料总表!$B:$GB,4,0) -> 线缆 | G70: 上海 | H70: 1 | I70: =C70 -> 302-000734 | J70: Closed | K70: 45489
A71: √ | B71: 45485 | C71: 302-000733 | D71: =VLOOKUP(C71,[1]备料总表!$B:$GB,2,0) -> 电源电缆-0.3m-S920X00-4U-EXP | E71: =VLOOKUP(C71,[1]备料总表!$B:$GB,4,0) -> 线缆 | G71: 上海 | H71: 1 | I71: =C71 -> 302-000733 | J71: Closed | K71: 45489
A72: √ | B72: 45485 | C72: 302-001400 | D72: =VLOOKUP(C72,[1]备料总表!$B:$GB,2,0) -> SSD SM883读写-1.92TB-SATA 2.5无托 | E72: =VLOOKUP(C72,[1]备料总表!$B:$GB,4,0) -> 硬盘 | G72: 上海 | H72: 3 | I72: =VLOOKUP(C72,[1]备料总表!$B:$GB,182,0) -> 99-001400 | J72: Closed | K72: 45485
A73: √ | B73: 45485 | C73: 302-001815 | D73: =VLOOKUP(C73,[1]备料总表!$B:$GB,2,0) -> S硬盘4T-3.5SATA-6G7.2K-256M-XJ V1.0 | E73: =VLOOKUP(C73,[1]备料总表!$B:$GB,4,0) -> 硬盘 | F73: 余8 | G73: 上海 | H73: 1 | I73: =VLOOKUP(C73,[1]备料总表!$B:$GB,182,0) -> 99-001049 | J73: Closed | K73: 45491
A74: √ | B74: 45485 | C74: 302-001238 | D74: =VLOOKUP(C74,[1]备料总表!$B:$GB,2,0) -> 硬盘8T-SATA 6Gb/s-7.2K-3.5无托 XJ | E74: =VLOOKUP(C74,[1]备料总表!$B:$GB,4,0) -> 硬盘 | F74: 余17 | G74: 广州 | H74: 1 | I74: =VLOOKUP(C74,[1]备料总表!$B:$GB,182,0) -> 99-001043 | J74: Closed | K74: 45492
A75: √ | B75: 45485 | C75: 302-000286 | D75: =VLOOKUP(C75,[1]备料总表!$B:$GB,2,0) -> 风扇-风扇框-2288H V5-BC1M05FAN-8038 | E75: =VLOOKUP(C75,[1]备料总表!$B:$GB,4,0) -> 风扇 | G75: 汕头 | H75: 1 | I75: =VLOOKUP(C75,[1]备料总表!$B:$GB,182,0) -> 99-000434 | J75: Closed | K75: 45492
A76: √ | B76: 45485 | C76: 302-000289 | D76: =VLOOKUP(C76,[1]备料总表!$B:$GB,2,0) -> 硬盘背板-RH2288H V3-BC11THBHB | E76: =VLOOKUP(C76,[1]备料总表!$B:$GB,4,0) -> 机箱/硬盘背板 | G76: 福州 | H76: 1 | I76: =VLOOKUP(C76,[1]备料总表!$B:$GB,182,0) -> 88-000289 | J76: Closed | K76: 45485
A77: √ | B77: 45485 | C77: 302-000253 | D77: =VLOOKUP(C77,[1]备料总表!$B:$GB,2,0) -> IT设备电缆-信号线缆-0.3m | E77: =VLOOKUP(C77,[1]备料总表!$B:$GB,4,0) -> 线缆 | G77: 福州 | H77: 1 | I77: =C77 -> 302-000253 | J77: Closed | K77: 45485
A78: √ | B78: 45485 | C78: 302-000259 | D78: =VLOOKUP(C78,[1]备料总表!$B:$GB,2,0) -> 电源电缆-0.3m-14pin 4.2转14pin 3.0 | E78: =VLOOKUP(C78,[1]备料总表!$B:$GB,4,0) -> 线缆 | G78: 福州 | H78: 1 | I78: =VLOOKUP(C78,[1]备料总表!$B:$GB,182,0) -> 99-000259 | J78: Closed | K78: 45485
A79: √ | B79: 45485 | C79: 302-001170 | D79: =VLOOKUP(C79,[1]备料总表!$B:$GB,2,0) -> PAC900S12-B2-服务器白金900W交流电源 | E79: =VLOOKUP(C79,[1]备料总表!$B:$GB,4,0) -> 电源 | G79: 南宁 | H79: 1 | I79: =VLOOKUP(C79,[1]备料总表!$B:$GB,182,0) -> 99-000448 | J79: Closed | K79: 45489
A80: √ | B80: 45485 | C80: 302-000611 | D80: =VLOOKUP(C80,[1]备料总表!$B:$GB,2,0) -> S硬盘1.8T-2.5SAS-12G10K-128M-DZ V1.1 | E80: =VLOOKUP(C80,[1]备料总表!$B:$GB,4,0) -> 硬盘 | G80: 厦门 | H80: 1 | I80: =VLOOKUP(C80,[1]备料总表!$B:$GB,182,0) -> 99-001039 | J80: Closed | K80: 45503
A81: √ | B81: 45485 | C81: 302-001240 | D81: =VLOOKUP(C81,[1]备料总表!$B:$GB,2,0) -> S硬盘16T-3.5SATA-6G7.2K-256M-XJ-[AVAP] | E81: =VLOOKUP(C81,[1]备料总表!$B:$GB,4,0) -> 硬盘 | G81: 西安 | H81: 2 | I81: =VLOOKUP(C81,[1]备料总表!$B:$GB,182,0) -> 99-001163 | J81: Closed | K81: 45492
A82: √ | B82: 45485 | C82: 302-001815 | D82: =VLOOKUP(C82,[1]备料总表!$B:$GB,2,0) -> S硬盘4T-3.5SATA-6G7.2K-256M-XJ V1.0 | E82: =VLOOKUP(C82,[1]备料总表!$B:$GB,4,0) -> 硬盘 | G82: 西安 | H82: 1 | I82: =VLOOKUP(C82,[1]备料总表!$B:$GB,182,0) -> 99-001049 | J82: Closed | K82: 45491
A83: √ | B83: 45485 | C83: 302-001349 | D83: =VLOOKUP(C83,[1]备料总表!$B:$GB,2,0) -> SSD ES3521AV6-960G-SATA-6G-2.5读取HW V1.0 | E83: =VLOOKUP(C83,[1]备料总表!$B:$GB,4,0) -> 硬盘 | G83: 西安 | H83: 1 | I83: =VLOOKUP(C83,[1]备料总表!$B:$GB,182,0) -> 99-001349 | J83: Closed | K83: 45489
B84: 45485 | C84: 302-001800 | D84: =VLOOKUP(C84,[1]备料总表!$B:$GB,2,0) -> SSD H101-IY-256G-SATA-6G-2.5读写HD V1.0 | E84: =VLOOKUP(C84,[1]备料总表!$B:$GB,4,0) -> 硬盘 | G84: 西安 | H84: 1 | I84: =C84 -> 302-001800 | J84: Dely
B85: 45485 | C85: 302-002062 | D85: =VLOOKUP(C85,[1]备料总表!$B:$GB,2,0) -> SSD PM9A3-3.84TB-NVMe4.0-2.5读取SX V1.0 | E85: =VLOOKUP(C85,[1]备料总表!$B:$GB,4,0) -> 硬盘 | F85: 余6，有固件版本要求建行 | G85: 北京 | H85: 1 | I85: =VLOOKUP(C85,[1]备料总表!$B:$GB,182,0) -> 99-002062 | J85: Dely
A86: √ | B86: 45488 | C86: 302-000134 | D86: =VLOOKUP(C86,[1]备料总表!$B:$GB,2,0) -> RAID扣卡 SR450C-M 2G(Avago3508) | E86: =VLOOKUP(C86,[1]备料总表!$B:$GB,4,0) -> RAID卡 | G86: 上海 | H86: 1 | I86: =VLOOKUP(C86,[1]备料总表!$B:$GB,182,0) -> 99-000134 | J86: Closed | K86: 45489
A87: √ | B87: 45488 | C87: 302-000857 | D87: =VLOOKUP(C87,[1]备料总表!$B:$GB,2,0) -> Internal Mini SAS HD 线-1.0m-R62X | E87: =VLOOKUP(C87,[1]备料总表!$B:$GB,4,0) -> 线缆 | G87: 上海 | H87: 1 | I87: =C87 -> 302-000857 | J87: Closed | K87: 45489
A88: √ | B88: 45488 | C88: 302-000592 | D88: =VLOOKUP(C88,[1]备料总表!$B:$GB,2,0) -> S硬盘8T-3.5SATA-6G7.2K-256M-DZ V1.0 | E88: =VLOOKUP(C88,[1]备料总表!$B:$GB,4,0) -> 硬盘 | F88: 余8 | G88: 郑州 | H88: 1 | I88: =VLOOKUP(C88,[1]备料总表!$B:$GB,182,0) -> 99-001043 | J88: Closed | K88: 45492
A89: √ | B89: 45488 | C89: 302-002116 | D89: =VLOOKUP(C89,[1]备料总表!$B:$GB,2,0) -> FC HBA卡-32Gb-LPe32002-AP-双口-SFP+2光模块 | E89: =VLOOKUP(C89,[1]备料总表!$B:$GB,4,0) -> HBA卡 | G89: 合肥 | H89: 1 | I89: =VLOOKUP(C89,[1]备料总表!$B:$GB,182,0) -> 99-001187 | J89: Closed | K89: 45488
A90: √ | B90: 45488 | C90: 302-002418 | D90: =VLOOKUP(C90,[1]备料总表!$B:$GB,2,0) -> S内存DDR4-32G-3200-2Rx4-RD CX V1.0 | E90: =VLOOKUP(C90,[1]备料总表!$B:$GB,4,0) -> 内存 | G90: 上海 | H90: 1 | I90: =C90 -> 302-002418 | J90: Closed | K90: 45489
B91: 45488 | C91: 302-000584 | D91: =VLOOKUP(C91,[1]备料总表!$B:$GB,2,0) -> S硬盘10T-3.5SATA-6G7.2K-256M-XS V1.0 | E91: =VLOOKUP(C91,[1]备料总表!$B:$GB,4,0) -> 硬盘 | F91: 余4 | G91: 郑州联通 | H91: 1 | I91: =VLOOKUP(C91,[1]备料总表!$B:$GB,182,0) -> 99-001042 | J91: Dely
A92: √ | B92: 45488 | C92: 302-000619 | D92: =VLOOKUP(C92,[1]备料总表!$B:$GB,2,0) -> S硬盘1.8T-2.5SAS-12G10K-256M-XJ V1.1 | E92: =VLOOKUP(C92,[1]备料总表!$B:$GB,4,0) -> 硬盘 | G92: 上海 | H92: 1 | I92: =VLOOKUP(C92,[1]备料总表!$B:$GB,182,0) -> 99-001039 | J92: Closed | K92: 45489
A93: √ | B93: 45488 | C93: 302-001056 | D93: =VLOOKUP(C93,[1]备料总表!$B:$GB,2,0) -> S硬盘2.4T-2.5SAS-12G10K-256M-XJ V1.0 | E93: =VLOOKUP(C93,[1]备料总表!$B:$GB,4,0) -> 硬盘 | G93: 佛山 | H93: 1 | I93: =VLOOKUP(C93,[1]备料总表!$B:$GB,182,0) -> 99-000781 | J93: Closed | K93: 45489
A94: √ | B94: 45488 | C94: 302-001346 | D94: =VLOOKUP(C94,[1]备料总表!$B:$GB,2,0) -> SSD ES3521AV6-480G-SATA-6G-2.5读取HW V1.3 | E94: =VLOOKUP(C94,[1]备料总表!$B:$GB,4,0) -> 硬盘 | G94: 广州 | H94: 2 | I94: =VLOOKUP(C94,[1]备料总表!$B:$GB,182,0) -> 99-001346 | J94: Closed | K94: 45503
A95: √ | B95: 45488 | C95: 302-000448 | D95: =VLOOKUP(C95,[1]备料总表!$B:$GB,2,0) -> 服务器白金900W B版本交流电源 | E95: =VLOOKUP(C95,[1]备料总表!$B:$GB,4,0) -> 电源 | G95: 汕头 | H95: 1 | I95: =VLOOKUP(C95,[1]备料总表!$B:$GB,182,0) -> 99-000448 | J95: Closed | K95: 45492
A96: √ | B96: 45488 | C96: 302-001815 | D96: =VLOOKUP(C96,[1]备料总表!$B:$GB,2,0) -> S硬盘4T-3.5SATA-6G7.2K-256M-XJ V1.0 | E96: =VLOOKUP(C96,[1]备料总表!$B:$GB,4,0) -> 硬盘 | G96: 肇庆 | H96: 1 | I96: =VLOOKUP(C96,[1]备料总表!$B:$GB,182,0) -> 99-001049 | J96: Closed | K96: 45488
A97: √ | B97: 45488 | C97: 302-001815 | D97: =VLOOKUP(C97,[1]备料总表!$B:$GB,2,0) -> S硬盘4T-3.5SATA-6G7.2K-256M-XJ V1.0 | E97: =VLOOKUP(C97,[1]备料总表!$B:$GB,4,0) -> 硬盘 | G97: 银川 | H97: 2 | I97: =VLOOKUP(C97,[1]备料总表!$B:$GB,182,0) -> 99-001049 | J97: Closed | K97: 45488
B98: 45488 | C98: 302-000786 | D98: =VLOOKUP(C98,[1]备料总表!$B:$GB,2,0) -> 网卡 MCX512A-ACUT 25G/10G双口SFP28 | E98: =VLOOKUP(C98,[1]备料总表!$B:$GB,4,0) -> 网卡 | G98: 北京 | H98: 1 | I98: =VLOOKUP(C98,[1]备料总表!$B:$GB,182,0) -> 99-000786 | J98: Cancel
A99: √ | B99: 45488 | C99: 302-002164 | D99: =VLOOKUP(C99,[1]备料总表!$B:$GB,2,0) -> XGIGA光模块-SFP28-25G多模850nm,0.1km,LC-V2 | E99: =VLOOKUP(C99,[1]备料总表!$B:$GB,4,0) -> 光模块 | G99: 北京 | H99: 1 | I99: =VLOOKUP(C99,[1]备料总表!$B:$GB,182,0) -> 99-000380 | J99: Closed | K99: 45490
A100: √ | B100: 45488 | C100: 302-001644 | D100: =VLOOKUP(C100,[1]备料总表!$B:$GB,2,0) -> S内存DDR4-32G-3200-2Rx4-RD HLS V1.0 | E100: =VLOOKUP(C100,[1]备料总表!$B:$GB,4,0) -> 内存 | G100: 北京 | H100: 1 | I100: =VLOOKUP(C100,[1]备料总表!$B:$GB,182,0) -> 99-001627 | J100: Closed | K100: 45490
...

Sheet wms导出-出库单
A1: 库房名称 | B1: 工厂 | C1: 出库单号 | D1: 订单号 | E1: 外部单据号 | F1: 交易单号 | G1: 创单时间 | H1: 修改时间 | I1: 发货考核时间 | J1: 揽收考核时间 | K1: 单据状态 | L1: 过账状态 | M1: 单据类型 | N1: 撤单状态 | O1: 买方编码 | P1: 买方 | Q1: 买方联系人 | R1: 买方电话 | S1: 买方邮编 | T1: 指定承运商 | U1: 显示收货联系人 | V1: 收货人 | W1: 收货人电话 | X1: 收货人手机 | Y1: 收货人省份 | Z1: 收货人城市 | AA1: 收货人区域 | AB1: 收货地 | AC1: 收货地址 | AD1: 配送服务级别 | AE1: 运输方式 | AF1: 复核完成时间 | AG1: 理论重量 | AH1: 签收标准 | AI1: 体积 | AJ1: 商品总数 | AK1: 总箱数 | AL1: 店铺 | AM1: 备注 | AN1: 自定义1 | AO1: 自定义2 | AP1: 自定义3 | AQ1: 自定义4 | AR1: 自定义5 | AS1: 制单人 | AT1: 是否货到付款 | AU1: 货到付款金额 | AV1: 接单时间
A2: 备件业务-南京备件仓 | B2: 服务中心武汉备件 | C2: 330053161553 | E2: 600000010460_BC | G2: 2024-07-3117:47:05 | H2: 45504.745 | K2: 完成 | L2: 已过账 | M2: 备件出库单 | N2: 正常 | AF2: 45504.745 | AG2: 0 | AI2: 0.001 | AJ2: 1 | AK2: 1 | AS2: GROUP_ORDER_7 | AT2: 否 | AV2: 45504.741
A3: 备件业务-南京备件仓 | B3: 服务中心武汉备件 | C3: 330053161507 | E3: 600000010458_BC | G3: 45504.491 | H3: 45504.509 | K3: 完成 | L3: 已过账 | M3: 备件出库单 | N3: 正常 | AF3: 45504.509 | AG3: 0.01 | AI3: 0 | AJ3: 1 | AK3: 1 | AS3: GROUP_ORDER_3 | AT3: 否 | AV3: 45504.491
A4: 备件业务-上海备件仓 | B4: 服务中心武汉备件 | C4: 330053161506 | E4: 600000010457_BC | G4: 2024-08-12 11:47:05 | H4: 2024-08-12 12:13:20 | K4: 完成 | L4: 已过账 | M4: 备件出库单 | N4: 正常 | AF4: 2024-08-12 12:13:20 | AG4: 5.15 | AI4: 0.001 | AJ4: 1 | AK4: 1 | AS4: GROUP_ORDER_2 | AT4: 否 | AV4: 2024-08-12 11:47:05
A5: 备件业务-上海备件仓 | B5: 服务中心武汉备件 | C5: 330053161505 | E5: 600000010456_BC | G5: 2024-08-12 11:45:05 | H5: 2024-08-12 12:13:20 | K5: 完成 | L5: 已过账 | M5: 备件出库单 | N5: 正常 | AF5: 2024-08-12 12:13:20 | AG5: 0 | AI5: 0.001 | AJ5: 1 | AK5: 1 | AS5: GROUP_ORDER_1 | AT5: 否 | AV5: 2024-08-12 11:45:05
A6: 备件业务-北京备件仓 | B6: 服务中心武汉备件 | C6: 330053161498 | E6: 600000010455_BC | G6: 2024-08-12 11:27:05 | H6: 2024-08-12 11:44:20 | K6: 完成 | L6: 已过账 | M6: 备件出库单 | N6: 正常 | AF6: 2024-08-12 11:44:20 | AG6: 0 | AI6: 0.001 | AJ6: 1 | AK6: 1 | AS6: GROUP_ORDER_4 | AT6: 否 | AV6: 2024-08-12 11:27:05
A7: 备件业务-北京备件仓 | B7: 服务中心武汉备件 | C7: 330053161490 | E7: 600000010454_BC | G7: 2024-08-12 10:31:05 | H7: 2024-08-12 11:44:20 | K7: 完成 | L7: 已过账 | M7: 备件出库单 | N7: 正常 | AF7: 2024-08-12 11:44:20 | AG7: 0.783 | AI7: 1.509 | AJ7: 1 | AK7: 1 | AS7: GROUP_ORDER_9 | AT7: 否 | AV7: 2024-08-12 10:31:05
A8: 备件业务-北京备件仓 | B8: 服务中心武汉备件 | C8: 330053161489 | E8: 600000010453_BC | G8: 2024-08-12 10:31:05 | H8: 2024-08-12 11:44:20 | K8: 完成 | L8: 已过账 | M8: 备件出库单 | N8: 正常 | AF8: 2024-08-12 11:44:20 | AG8: 0.783 | AI8: 1.509 | AJ8: 1 | AK8: 1 | AS8: GROUP_ORDER_8 | AT8: 否 | AV8: 2024-08-12 10:31:05
A9: 备件业务-玉溪维修站 | B9: 服务中心武汉备件 | C9: 330053161418 | E9: 600000010450_BC | G9: 2024-08-12 08:23:06 | H9: 2024-08-12 08:44:20 | K9: 完成 | L9: 已过账 | M9: 备件出库单 | N9: 正常 | AF9: 2024-08-12 08:44:20 | AG9: 0 | AI9: 0.001 | AJ9: 1 | AK9: 1 | AS9: GROUP_ORDER_7 | AT9: 否 | AV9: 2024-08-12 08:23:05
A10: 备件业务-玉溪维修站 | B10: 服务中心武汉备件 | C10: 330053161417 | E10: 600000010451_BC | G10: 2024-08-12 08:23:06 | H10: 2024-08-12 08:44:20 | K10: 完成 | L10: 已过账 | M10: 备件出库单 | N10: 正常 | AF10: 2024-08-12 08:44:20 | AG10: 0 | AI10: 0.001 | AJ10: 1 | AK10: 1 | AS10: GROUP_ORDER_5 | AT10: 否 | AV10: 2024-08-12 08:23:05
A11: 备件业务-玉溪维修站 | B11: 服务中心武汉备件 | C11: 330053161416 | E11: 600000010452_BC | G11: 2024-08-12 08:23:06 | H11: 2024-08-12 08:44:20 | K11: 完成 | L11: 已过账 | M11: 备件出库单 | N11: 正常 | AF11: 2024-08-12 08:44:20 | AG11: 0 | AI11: 0.001 | AJ11: 1 | AK11: 1 | AS11: GROUP_ORDER_6 | AT11: 否 | AV11: 2024-08-12 08:23:05
A12: 备件业务-郑州联通备件仓 | B12: 服务中心武汉备件 | C12: 330053161135 | E12: 600000010405_BC | G12: 2024-08-08 11:39:05 | H12: 2024-08-12 08:42:20 | K12: 完成 | L12: 已过账 | M12: 备件出库单 | N12: 正常 | AF12: 2024-08-12 08:42:20 | AG12: 3 | AI12: 0.004 | AJ12: 1 | AK12: 1 | AS12: GROUP_ORDER_3 | AT12: 否 | AV12: 2024-08-08 11:39:05
A13: 备件业务-郑州联通备件仓 | B13: 服务中心武汉备件 | C13: 330053161134 | E13: 600000010404_BC | G13: 2024-08-08 11:39:05 | H13: 2024-08-12 08:42:20 | K13: 完成 | L13: 已过账 | M13: 备件出库单 | N13: 正常 | AF13: 2024-08-12 08:42:20 | AG13: 0 | AI13: 0.001 | AJ13: 1 | AK13: 1 | AS13: GROUP_ORDER_2 | AT13: 否 | AV13: 2024-08-08 11:39:05
A14: 备件业务-郑州联通备件仓 | B14: 服务中心武汉备件 | C14: 330053161132 | E14: 600000010406_BC | G14: 2024-08-08 11:39:05 | H14: 2024-08-12 08:42:20 | K14: 完成 | L14: 已过账 | M14: 备件出库单 | N14: 正常 | AF14: 2024-08-12 08:42:20 | AG14: 0 | AI14: 0.001 | AJ14: 1 | AK14: 1 | AS14: GROUP_ORDER_10 | AT14: 否 | AV14: 2024-08-08 11:39:05
A15: 备件业务-郑州联通备件仓 | B15: 服务中心武汉备件 | C15: 330053161131 | E15: 600000010407_BC | G15: 2024-08-08 11:39:05 | H15: 2024-08-12 08:42:20 | K15: 完成 | L15: 已过账 | M15: 备件出库单 | N15: 正常 | AF15: 2024-08-12 08:42:20 | AG15: 0 | AI15: 0.001 | AJ15: 1 | AK15: 1 | AS15: GROUP_ORDER_9 | AT15: 否 | AV15: 2024-08-08 11:39:05
A16: 备件业务-北京建设银行备件仓 | B16: 服务中心武汉备件 | C16: 330053160431 | E16: 600000010286_BC | G16: 2024-08-05 11:46:05 | H16: 2024-08-12 08:42:20 | K16: 完成 | L16: 已过账 | M16: 备件出库单 | N16: 正常 | AF16: 2024-08-12 08:42:20 | AG16: 5.15 | AI16: 0.001 | AJ16: 1 | AK16: 1 | AS16: GROUP_ORDER_5 | AT16: 否 | AV16: 2024-08-05 11:46:05

Sheet wms导出-出库单明细
A1: 出库单号 | B1: 外部单据号 | C1: 单据类型 | D1: 单据状态 | E1: 状态 | F1: 过账状态 | G1: 行号 | H1: 库房 | I1: 工厂 | J1: 物料编码 | K1: 外部物料号 | L1: 物料名称 | M1: pn | N1: 库存地编码 | O1: 库存地名称 | P1: 过账数量 | Q1: 最小单位数量 | R1: 最大单位数量 | S1: 重量（KG） | T1: 体积(M3) | U1: 物料类型 | V1: 品牌 | W1: 批号 | X1: 生产日期 | Y1: 到期日期 | Z1: 批属性一 | AA1: 批属性二 | AB1: 批属性三 | AC1: 批属性四 | AD1: 批属性五 | AE1: 批属性六 | AF1: 批属性七 | AG1: 批属性八 | AH1: 批属性九 | AI1: 批属性十 | AJ1: 批属性十一 | AK1: 批属性十二 | AL1: 批属性十三 | AM1: 批属性十四 | AN1: 批属性十五 | AO1: 批属性十六 | AP1: 批属性十七 | AQ1: 批属性十八 | AR1: 批属性十九 | AS1: 批属性二十 | AT1: 行备注一 | AU1: 整零标识 | AV1: 行备注二 | AW1: 行备注三 | AX1: 创建时间 | AY1: 修改时间
A2: 330053160431 | B2: 600000010286_BC | C2: 备件出库单 | D2: 完成 | E2: 正常 | F2: 已过账 | G2: 1 | H2: 备件业务-南京备件仓 | I2: 服务中心武汉备件 | J2: 170000222761 | K2: 000000000302000910 | L2: S内存DDR4-32G-3200-2Rx4-RD HLS V1.0 | M2: 99013VWT,HMA84GR7DJR4N-XN | N2: KCDBJ-NJBJC | O2: 备件业务-南京备件仓默认库存地 | P2: 1 | Q2: 1 | R2: 0 | S2: 5.15 | T2: 0.001 | U2: 1105 | AX2: 45535.49 | AY2: 45535.363
A3: 330053161131 | B3: 600000010407_BC | C3: 备件出库单 | D3: 完成 | E3: 正常 | F3: 已过账 | G3: 1 | H3: 备件业务-南京备件仓 | I3: 服务中心武汉备件 | J3: 170000596378 | K3: 000000000302001799 | L3: S内存DDR4-64GB-3200-2Rank(4G*4bit) SX | M3: M393A8G40AB2-CWE | N3: KCDBJ-NJBJC | O3: 备件业务-南京备件仓默认库存地 | P3: 1 | Q3: 1 | R3: 0 | S3: 0 | T3: 0.001 | U3: 1105 | AX3: 45535.485 | AY3: 45535.363
A4: 330053161131 | B4: 600000010407_BC | C4: 备件出库单 | D4: 完成 | E4: 正常 | F4: 已过账 | G4: 1 | H4: 备件业务-南京备件仓 | I4: 服务中心武汉备件 | J4: 170000596378 | K4: 000000000302001799 | L4: S内存DDR4-64GB-3200-2Rank(4G*4bit) SX | M4: M393A8G40AB2-CWE | N4: KCDBJ-NJBJC | O4: 备件业务-南京备件仓默认库存地 | P4: 1 | Q4: 1 | R4: 0 | S4: 0 | T4: 0.001 | U4: 1105 | AX4: 45535.485 | AY4: 45535.363
A5: 330053161132 | B5: 600000010406_BC | C5: 备件出库单 | D5: 完成 | E5: 正常 | F5: 已过账 | G5: 1 | H5: 备件业务-郑州联通备件仓 | I5: 服务中心武汉备件 | J5: 170000099439 | K5: 000000000302000286 | L5: 风扇-风扇框-2288H V5-BC1M05FAN-8038 | M5: 02311VSF | N5: KCDBJ-ZZLTBJC | O5: 备件业务-郑州联通备件仓默认库存地 | P5: 1 | Q5: 1 | R5: 0 | S5: 0 | T5: 0.001 | U5: 1105 | AX5: 2024-08-08 11:39:05 | AY5: 2024-08-12 08:42:20
A6: 330053161134 | B6: 600000010404_BC | C6: 备件出库单 | D6: 完成 | E6: 正常 | F6: 已过账 | G6: 1 | H6: 备件业务-郑州联通备件仓 | I6: 服务中心武汉备件 | J6: 170000699791 | K6: 000000000302002030 | L6: #S主板S920X00-2*7260(64C@2.6)BF-1711-3A-VD | M6: 03050JKT | N6: KCDBJ-ZZLTBJC | O6: 备件业务-郑州联通备件仓默认库存地 | P6: 1 | Q6: 1 | R6: 0 | S6: 0 | T6: 0.001 | U6: 1105 | AX6: 2024-08-08 11:39:05 | AY6: 2024-08-12 08:42:20
A7: 330053161135 | B7: 600000010405_BC | C7: 备件出库单 | D7: 完成 | E7: 正常 | F7: 已过账 | G7: 1 | H7: 备件业务-郑州联通备件仓 | I7: 服务中心武汉备件 | J7: 170000185140 | K7: 000000000302001170 | L7: PAC900S12-B2-服务器白金900W交流电源 | M7: 02312XWK | N7: KCDBJ-ZZLTBJC | O7: 备件业务-郑州联通备件仓默认库存地 | P7: 1 | Q7: 1 | R7: 0 | S7: 3 | T7: 0.004 | U7: 1105 | AX7: 2024-08-08 11:39:05 | AY7: 2024-08-12 08:42:20
A8: 330053161416 | B8: 600000010452_BC | C8: 备件出库单 | D8: 完成 | E8: 正常 | F8: 已过账 | G8: 1 | H8: 备件业务-玉溪维修站 | I8: 服务中心武汉备件 | J8: 170000510050 | K8: 000000000302001740 | L8: 电源线/2*TYPE-C/2m/5A/白/L351 | M8: W0500240012 | N8: KCDBJ-YXWXZ | O8: 备件业务-玉溪维修站默认库存地 | P8: 1 | Q8: 1 | R8: 0 | S8: 0 | T8: 0.001 | U8: 1105 | AX8: 2024-08-12 08:23:06 | AY8: 2024-08-12 08:44:20
A9: 330053161417 | B9: 600000010451_BC | C9: 备件出库单 | D9: 完成 | E9: 正常 | F9: 已过账 | G9: 1 | H9: 备件业务-玉溪维修站 | I9: 服务中心武汉备件 | J9: 170000510050 | K9: 000000000302001740 | L9: 电源线/2*TYPE-C/2m/5A/白/L351 | M9: W0500240012 | N9: KCDBJ-YXWXZ | O9: 备件业务-玉溪维修站默认库存地 | P9: 1 | Q9: 1 | R9: 0 | S9: 0 | T9: 0.001 | U9: 1105 | AX9: 2024-08-12 08:23:06 | AY9: 2024-08-12 08:44:20
A10: 330053161418 | B10: 600000010450_BC | C10: 备件出库单 | D10: 完成 | E10: 正常 | F10: 已过账 | G10: 1 | H10: 备件业务-玉溪维修站 | I10: 服务中心武汉备件 | J10: 170000510245 | K10: 000000000302001739 | L10: 适配器/PD65W/20V 3.25A/L351 | M10: PD65W-1,PD65W | N10: KCDBJ-YXWXZ | O10: 备件业务-玉溪维修站默认库存地 | P10: 1 | Q10: 1 | R10: 0 | S10: 0 | T10: 0.001 | U10: 1105 | AX10: 2024-08-12 08:23:06 | AY10: 2024-08-12 08:44:20
A11: 330053161489 | B11: 600000010453_BC | C11: 备件出库单 | D11: 完成 | E11: 正常 | F11: 已过账 | G11: 1 | H11: 备件业务-北京备件仓 | I11: 服务中心武汉备件 | J11: 170000179592 | K11: 000000000302001043 | L11: S硬盘8T-3.5SATA-6G7.2K-256M-DZ V1.0 | M11: MG08ADA800E | N11: KCDBJ-BJBJC | O11: 备件业务-北京备件仓默认库存地 | P11: 1 | Q11: 1 | R11: 0 | S11: 0.783 | T11: 1.509 | U11: 1105 | AX11: 2024-08-12 10:31:05 | AY11: 2024-08-12 11:44:20
A12: 330053161490 | B12: 600000010454_BC | C12: 备件出库单 | D12: 完成 | E12: 正常 | F12: 已过账 | G12: 1 | H12: 备件业务-北京备件仓 | I12: 服务中心武汉备件 | J12: 170000179592 | K12: 000000000302001043 | L12: S硬盘8T-3.5SATA-6G7.2K-256M-DZ V1.0 | M12: MG08ADA800E | N12: KCDBJ-BJBJC | O12: 备件业务-北京备件仓默认库存地 | P12: 1 | Q12: 1 | R12: 0 | S12: 0.783 | T12: 1.509 | U12: 1105 | AX12: 2024-08-12 10:31:05 | AY12: 2024-08-12 11:44:20
A13: 330053161498 | B13: 600000010455_BC | C13: 备件出库单 | D13: 完成 | E13: 正常 | F13: 已过账 | G13: 1 | H13: 备件业务-北京备件仓 | I13: 服务中心武汉备件 | J13: 170000101723 | K13: 000000000302000577 | L13: S硬盘16T-3.5SATA-6G7.2K-256M-XJ V1.1 | M13: 2KK103-177,2540004/510601294,2540004 | N13: KCDBJ-BJBJC | O13: 备件业务-北京备件仓默认库存地 | P13: 1 | Q13: 1 | R13: 0 | S13: 0 | T13: 0.001 | U13: 1105 | AX13: 2024-08-12 11:27:05 | AY13: 2024-08-12 11:44:20
A14: 330053161505 | B14: 600000010456_BC | C14: 备件出库单 | D14: 完成 | E14: 正常 | F14: 已过账 | G14: 1 | H14: 备件业务-上海备件仓 | I14: 服务中心武汉备件 | J14: 170000690088 | K14: 000000000302001996 | L14: FC卡-LPe31002-2x16G-SFP+ PCIe3.0x8-2光模块 | M14: 99014YLP | N14: KCDBJ-SHBJC | O14: 备件业务-上海备件仓默认库存地 | P14: 1 | Q14: 1 | R14: 0 | S14: 0 | T14: 0.001 | U14: 1105 | AX14: 2024-08-12 11:45:05 | AY14: 2024-08-12 12:13:20
A15: 330053161506 | B15: 600000010457_BC | C15: 备件出库单 | D15: 完成 | E15: 正常 | F15: 已过账 | G15: 1 | H15: 备件业务-上海备件仓 | I15: 服务中心武汉备件 | J15: 170000183873 | K15: 000000000302001164 | L15: RAID标卡 9460-8i PCIe3.0X8-2GB Cache | M15: 9460-8I,05-50011-02,03-50011-33 | N15: KCDBJ-SHBJC | O15: 备件业务-上海备件仓默认库存地 | P15: 1 | Q15: 1 | R15: 0 | S15: 5.15 | T15: 0.001 | U15: 1105 | AX15: 2024-08-12 11:47:05 | AY15: 2024-08-12 12:13:20
A16: 330053161507 | B16: 600000010458_BC | C16: 备件出库单 | D16: 完成 | E16: 正常 | F16: 已过账 | G16: 1 | H16: 备件业务-上海备件仓 | I16: 服务中心武汉备件 | J16: 170000098961 | K16: 000000000302000140 | L16: 3508/3516 RAID卡超级电容 | M16: 02311WDP | N16: KCDBJ-SHBJC | O16: 备件业务-上海备件仓默认库存地 | P16: 1 | Q16: 1 | R16: 0 | S16: 0.01 | T16: 0 | U16: 1105 | AX16: 2024-08-12 11:47:05 | AY16: 2024-08-12 12:13:20
A17: 330053161553 | B17: 600000010460_BC | C17: 备件出库单 | D17: 完成 | E17: 正常 | F17: 已过账 | G17: 1 | H17: 备件业务-乌鲁木齐备件仓 | I17: 服务中心武汉备件 | J17: 170000103549 | K17: 000000000302000741 | L17: SSD DSS200-B-480G-SATA-6G-2.5读取DT V1.0 | M17: F480GSTT05S1009C75,DSS200-B | N17: KCDBJ-WLMQBJC | O17: 备件业务-乌鲁木齐备件仓默认库存地 | P17: 1 | Q17: 1 | R17: 0 | S17: 0 | T17: 0.001 | U17: 1105 | AX17: 2024-08-12 17:47:05 | AY17: 2024-08-12 17:52:20

Sheet sheet4-WMS库房分配表
A1: 库房名称 | B1: 库房简称（库存地） | C1: 库房编码 | D1: 库存地编码 | E1: 各库区 | F1: 其他库区 | G1: 所有库区 | H1: 备选库 | I1: 备选库编码 | J1: 备选库存地编码
A2: 备件业务-武汉备件仓 | B2: 武汉 | C2: BJ-WHBJC | D2: KCDBJ-WHBJC | E2: 是 | F2: 否 | G2: 是 | J2: KCDBJ-SHBJC
A3: 备件业务-阿克苏备件仓 | B3: 阿克苏 | C3: BJ-AKSBJC | D3: KCDBJ-AKSBJC | E3: 是 | F3: 否 | G3: 是 | J3: KCDBJ-WLMQBJC
A4: 备件业务-北京备件仓 | B4: 北京 | C4: BJ-BJBJC | D4: KCDBJ-BJBJC | E4: 是 | F4: 否 | G4: 是 | J4: KCDBJ-WHBJC
A5: 备件业务-成都备件仓 | B5: 成都 | C5: BJ-CDBJC | D5: KCDBJ-CDBJC | E5: 是 | F5: 否 | G5: 是 | J5: KCDBJ-WHBJC
A6: 备件业务-大连备件仓 | B6: 大连 | C6: BJ-DLBJC | D6: KCDBJ-DLBJC | E6: 是 | F6: 否 | G6: 是 | J6: KCDBJ-SYBJC
A7: 备件业务-东莞备件仓 | B7: 东莞 | C7: BJ-DGBJC | D7: KCDBJ-DGBJC | E7: 是 | F7: 否 | G7: 是 | J7: KCDBJ-GZBJC
A8: 备件业务-福州备件仓 | B8: 福州 | C8: BJ-FZBJC | D8: KCDBJ-FZBJC | E8: 是 | F8: 否 | G8: 是 | J8: KCDBJ-XMBJC
A9: 备件业务-广州备件仓 | B9: 广州 | C9: BJ-GZBJC | D9: KCDBJ-GZBJC | E9: 是 | F9: 否 | G9: 是 | J9: KCDBJ-WHBJC
A10: 备件业务-哈尔滨备件仓 | B10: 哈尔滨 | C10: BJ-HEBBJC | D10: KCDBJ-HEBBJC | E10: 是 | F10: 否 | G10: 是 | J10: KCDBJ-CCBJC
A11: 备件业务-海口备件仓 | B11: 海口 | C11: BJ-HKBJC | D11: KCDBJ-HKBJC | E11: 是 | F11: 否 | G11: 是 | J11: KCDBJ-GZBJC
A12: 备件业务-合肥备件仓 | B12: 合肥 | C12: BJ-HFBJC | D12: KCDBJ-HFBJC | E12: 是 | F12: 否 | G12: 是 | J12: KCDBJ-SHBJC
A13: 备件业务-呼和浩特备件仓 | B13: 呼和浩特 | C13: BJ-HHHTBJC | D13: KCDBJ-HHHTBJC | E13: 是 | F13: 否 | G13: 是 | J13: KCDBJ-BJBJC
... A77: 备件业务-上海光大证券备件仓 | B77: 上海光大证券 | C77: BJ-SHGDZQBJC | D77: KCDBJ-SHGDZQBJC | E77: 否 | F77: 是 | G77: 是 | J77: KCDBJ-SHBJC
A78: 备件业务-超时硬盘仓 | B78: 超时硬盘 | C78: BJ-CSYPC | D78: KCDBJ-CSYPC | E78: 否 | F78: 是 | G78: 否
A79: 备件业务-武汉废品仓 | B79: 武汉废品 | C79: BJ-WHFPC | D79: KCDBJ-WHFPC | E79: 否 | F79: 是 | G79: 否
A80: 备件业务-武汉测试仓 | B80: 武汉测试 | C80: BJ-WHCSC | D80: KCDBJ-WHCSC | E80: 否 | F80: 是 | G80: 否
A81: 备件业务-武汉借用仓 | B81: 武汉借用 | C81: BJ-WHJYC | D81: KCDBJ-WHJYC | E81: 否 | F81: 是 | G81: 否
A82: 备件业务-武汉维修仓 | B82: 维修在途 | C82: WHWXC-WXZT | D82: WHWXC-WXZT | E82: 否 | F82: 是 | G82: 否
A83: 备件业务-武汉维修仓 | B83: 委外维修 | C83: WHWXC-WWWX | D83: WHWXC-WWWX | E83: 否 | F83: 是 | G83: 否

Sheet 换件在途举例
A1: 库存地 | B1: 库存地编码
A2: 北京备件仓-换件在途 | B2: BJBJC-WXZT
A3: 北京建设银行备件仓-换件在途 | B3: BJJSYHBJC-WXZT
A4: 成都备件仓-换件在途 | B4: CDBJC-WXZT
A5: 佛山备件仓-换件在途 | B5: FSBJC-WXZT
A6: 福州备件仓-换件在途 | B6: FZBJC-WXZT
A7: 广州备件仓-换件在途 | B7: GZBJC-WXZT
A8: 贵阳备件仓-换件在途 | B8: GYBJC-WXZT
A9: 哈尔滨备件仓-换件在途 | B9: HEBBJC-WXZT
A10: 杭州备件仓-换件在途 | B10: HZBJC-WXZT
A11: 合肥备件仓-换件在途 | B11: HFBJC-WXZT
A12: 呼和浩特备件仓-换件在途 | B12: HHHTBJC-WXZT
... A34: 重庆备件仓-换件在途 | B34: CQBJC-WXZT

Sheet Sheet1
A1: 物料类别 | B1: 产品名称 | C1: 料号 | D1: 描述 | E1: 单套数量 | F1: 总数量 | G1: 捆绑料号 | H1: 非电子料
A2: 基础物料 | B2: 服务器机箱 | C2: 302-001687 | D2: 机箱 25*2.5硬盘EXP 2U2P-无RAID SAS线1620S | E2: 1 | F2: 6 | G2: 88-000289
A3: 基础物料 | B3: 2.6G常规主板 | C3: 302-001363 | D3: S主板 S920S00-5220-AJ 2*(920,32C) 1711 | E3: 1 | F3: 6 | G3: 99-000708
A4: 基础物料 | B4: 内存 | C4: 302-001862 | D4: S内存DDR4-64G-3200-2Rx4-RD HLS V1.0 | E4: 16 | F4: 96 | G4: 99-001862
A5: 基础物料 | B5: Riser卡 | C5: 302-000147 | D5: 3*16X SLOT (PCIE X8) Riser1&2 模组 | E5: 2 | F5: 12 | G5: 99-000147
A6: 基础物料 | B6: 后硬盘背板 | C6: 302-000146 | D6: 后置 PSU 4*2.5寸硬盘背板组件(仅支持NVME) | E6: 1 | F6: 6 | G6: 99-000146
A7: 基础物料 | B7: SATA SSD | C7: 302-001346 | D7: SSD ES3521AV6-480G-SATA-6G-2.5读取HW V1.0 | E7: 2 | F7: 12 | G7: 99-001346
A8: 基础物料 | B8: SAS HDD | C8: 302-001056 | D8: S硬盘2.4T-2.5SAS-12G10K-256M-XJ V1.0 | E8: 10 | F8: 60 | G8: 99-000781
A9: 基础物料 | B9: NVMe SSD | C9: 302-003066 | D9: NVMeSSD UH831a-1.6TB-PCIe4-2.5读写YL-K | E9: 2 | F9: 12 | G9: 302-003066
A10: 基础物料 | B10: RAID标卡 | C10: 302-001332 | D10: RAID标卡-2GB 9460-8i-PCIe | E10: 1 | F10: 6 | G10: 99-001066
A11: 基础物料 | B11: 超级电容 | C11: 302-001655 | D11: 3508/3516 RAID卡超级电容 | E11: 1 | F11: 6 | G11: 99-001655
A12: 基础物料 | B12: RAID卡线缆 | C12: 302-000251 | D12: 高速电缆 Mini SAS HD Cable-0.85m | E12: 2 | F12: 12 | G12: 99-000251
A13: 基础物料 | B13: 灵活网卡 | C13: 302-002934 | D13: 灵活网卡-TM210 4*GE 接口卡 | E13: 1 | F13: 6 | G13: 99-000142
... A18: 基础物料 | B18: 光模块 | C18: 302-002431 | D18: XGIGA光模块-SFP+-10G-多模850nm,0.3km,LC，COB | E18: 4 | F18: 24 | G18: 99-000381
A19: 基础物料 | B19: 滑轨 | C19: 302-000187 | D19: 2U静态滑轨套件 | E19: 1 | F19: 6 | G19: 302-000187 | H19: 剔除
A20: 基础物料 | B20: 网卡 | C20: 302-003373 | D20: 网卡-SP680-4*25G-SFP28-pcie4.0x16-无模 | E20: 1 | F20: 860 | G20: 302-003373
A21: 辅助料信息 | B21: 标签包装 | C21: 69-001309 | D21: KunTai R522 服务器标准标签包装 | E21: 1 | F21: 6 | G21: 69-001309 | H21: 剔除
A22: 辅助料信息 | B22: 常规固件 | C22: 68-000009 | D22: S920X00/X01/S00 2.6G BIOS 1711BMC CPLD | E22: 1 | F22: 6 | G22: 68-000009 | H22: 剔除
A23: 服务类信息 | B23: 鲲泰服务器维保服务 | C23: 80-008589 | D23: 鲲泰服务器维保服务：金牌+服务包-2U-3年, 7×24×4H | E23: 1 | F23: 6 | G23: 80-008589
A24: 基础物料 | B24: 整机安装服务（中国大陆） | C24: 80-008592 | D24: 鲲泰服务器基础硬件安装服务-2U | E24: 1 | F24: 6 | G24: 80-008592
A25: 小计
A27: 2 | B27: 305-000026 | C27: R522 | D27: 8T容量服务器
A28: 物料类别 | B28: 产品名称 | C28: 料号 | D28: 描述 | E28: 单套数量 | F28: 总数量
A29: 基础物料 | B29: 服务器机箱 | C29: 302-001687 | D29: 机箱 25*2.5硬盘EXP 2U2P-无RAID SAS线1620S | E29: 1 | F29: 1 | G29: 88-000289
A30: 基础物料 | B30: 2.6G常规主板 | C30: 302-001363 | D30: S主板 S920S00-5220-AJ 2*(920,32C) 1711 | E30: 1 | F30: 1 | G30: 99-000708
A31: 基础物料 | B31: 内存 | C31: 302-001644 | D31: S内存DDR4-32GB-3200-2Rank(2G*4bit) HLS | E31: 4 | F31: 4 | G31: 99-001627
A32: 基础物料 | B32: Riser卡 | C32: 302-000147 | D32: 3*16X SLOT (PCIE X8) Riser1&2 模组 | E32: 2 | F32: 2 | G32: 99-000147
A33: 基础物料 | B33: 后硬盘背板 | C33: 302-000146 | D33: 后置 PSU 4*2.5寸硬盘背板组件(仅支持NVME) | E33: 1 | F33: 1 | G33: 99-000146
A34: 基础物料 | B34: SAS HDD | C34: 302-000637 | D34: S硬盘600G-2.5SAS-12G10K-256M-XJ V1.0 | E34: 3 | F34: 3 | G34: 99-001041
A35: 基础物料 | B35: NVMe SSD | C35: 302-003065 | D35: NVMeSSD UH811a-3.84TB-PCIe4-2.5读取YL-K | E35: 3 | F35: 3 | G35: 99-002080
A36: 基础物料 | B36: RAID标卡 | C36: 302-001332 | D36: RAID标卡-2GB 9460-8i-PCIe | E36: 1 | F36: 1 | G36: 99-001066
A37: 基础物料 | B37: 超级电容 | C37: 302-001655 | D37: 3508/3516 RAID卡超级电容 | E37: 1 | F37: 1 | G37: 99-001655
A38: 基础物料 | B38: RAID卡线缆 | C38: 302-000251 | D38: 高速电缆 Mini SAS HD Cable-0.85m | E38: 2 | F38: 2 | G38: 99-000251
A39: 基础物料 | B39: 灵活网卡 | C39: 302-002934 | D39: 灵活网卡-TM210 4*GE 接口卡 | E39: 1 | F39: 1 | G39: 99-000142
A40: 基础物料 | B40: 电源模块 | C40: 302-001170 | D40: 服务器白金900W 2.0 版本交流电源 | E40: 2 | F40: 2 | G40: 99-000448
... A44: 基础物料 | B44: 光模块 | C44: 302-002431 | D44: XGIGA光模块-SFP+-10G-多模850nm,0.3km,LC，COB | E44: 4 | F44: 4 | G44: 99-000381
A45: 基础物料 | B45: 滑轨 | C45: 302-000187 | D45: 2U静态滑轨套件 | E45: 1 | F45: 1 | G45: 302-000187 | H45: 剔除
A46: 基础物料 | B46: 网卡 | C46: 302-003373 | D46: 网卡-SP680-4*25G-SFP28-pcie4.0x16-无模 | E46: 1 | F46: 1 | G46: 302-003373
A47: 辅助料信息 | B47: 标签包装 | C47: 69-001309 | D47: KunTai R522 服务器标准标签包装 | E47: 1 | F47: 1 | G47: 69-001309 | H47: 剔除
A48: 辅助料信息 | B48: 常规固件 | C48: 68-000009 | D48: S920X00/X01/S00 2.6G BIOS 1711BMC CPLD | E48: 1 | F48: 1 | G48: 68-000009 | H48: 剔除
A49: 服务类信息 | B49: 鲲泰服务器维保服务 | C49: 80-008589 | D49: 鲲泰服务器维保服务：金牌+服务包-2U-3年, 7×24×4H | E49: 1 | F49: 1 | G49: 80-008589
A50: 基础物料 | B50: 整机安装服务（中国大陆） | C50: 80-008592 | D50: 鲲泰服务器基础硬件安装服务-2U | E50: 1 | F50: 1 | G50: 80-008592
A51: 小计
A53: 3 | B53: 305-000026 | C53: R522 | D53: 14T容量服务器
A54: 物料类别 | B54: 产品名称 | C54: 料号 | D54: 描述 | E54: 单套数量 | F54: 总数量
A55: 基础物料 | B55: 服务器机箱 | C55: 302-001687 | D55: 机箱 25*2.5硬盘EXP 2U2P-无RAID SAS线1620S | E55: 1 | F55: 1 | G55: 88-000289
A56: 基础物料 | B56: 2.6G常规主板 | C56: 302-001363 | D56: S主板 S920S00-5220-AJ 2*(920,32C) 1711 | E56: 1 | F56: 1 | G56: 99-000708
A57: 基础物料 | B57: 内存 | C57: 302-001644 | D57: S内存DDR4-32GB-3200-2Rank(2G*4bit) HLS | E57: 4 | F57: 4 | G57: 99-001627
A58: 基础物料 | B58: Riser卡 | C58: 302-000147 | D58: 3*16X SLOT (PCIE X8) Riser1&2 模组 | E58: 2 | F58: 2 | G58: 99-000147
A59: 基础物料 | B59: 后硬盘背板 | C59: 302-000146 | D59: 后置 PSU 4*2.5寸硬盘背板组件(仅支持NVME) | E59: 1 | F59: 1 | G59: 99-000146
A60: 基础物料 | B60: SAS HDD | C60: 302-000637 | D60: S硬盘600G-2.5SAS-12G10K-256M-XJ V1.0 | E60: 3 | F60: 3 | G60: 99-001041
A61: 基础物料 | B61: NVMe SSD | C61: 302-003065 | D61: NVMeSSD UH811a-3.84TB-PCIe4-2.5读取YL-K | E61: 4 | F61: 4 | G61: 99-002080
A62: 基础物料 | B62: RAID标卡 | C62: 302-001332 | D62: RAID标卡-2GB 9460-8i-PCIe | E62: 1 | F62: 1 | G62: 99-001066
A63: 基础物料 | B63: 超级电容 | C63: 302-001655 | D63: 3508/3516 RAID卡超级电容 | E63: 1 | F63: 1 | G63: 99-001655
A64: 基础物料 | B64: RAID卡线缆 | C64: 302-000251 | D64: 高速电缆 Mini SAS HD Cable-0.85m | E64: 2 | F64: 2 | G64: 99-000251
A65: 基础物料 | B65: 灵活网卡 | C65: 302-002934 | D65: 灵活网卡-TM210 4*GE 接口卡 | E65: 1 | F65: 1 | G65: 99-000142
A66: 基础物料 | B66: 电源模块 | C66: 302-001170 | D66: 服务器白金900W 2.0 版本交流电源 | E66: 2 | F66: 2 | G66: 99-000448
... A70: 基础物料 | B70: 光模块 | C70: 302-002431 | D70: XGIGA光模块-SFP+-10G-多模850nm,0.3km,LC，COB | E70: 4 | F70: 4 | G70: 99-000381
A71: 基础物料 | B71: 滑轨 | C71: 302-000187 | D71: 2U静态滑轨套件 | E71: 1 | F71: 1 | G71: 302-000187 | H71: 剔除
A72: 基础物料 | B72: 网卡 | C72: 302-003373 | D72: 网卡-SP680-4*25G-SFP28-pcie4.0x16-无模 | E72: 1 | F72: 1 | G72: 302-003373
A73: 辅助料信息 | B73: 标签包装 | C73: 69-001309 | D73: KunTai R522 服务器标准标签包装 | E73: 1 | F73: 1 | G73: 69-001309 | H73: 剔除
A74: 辅助料信息 | B74: 常规固件 | C74: 68-000009 | D74: S920X00/X01/S00 2.6G BIOS 1711BMC CPLD | E74: 1 | F74: 1 | G74: 68-000009 | H74: 剔除
A75: 服务类信息 | B75: 鲲泰服务器维保服务 | C75: 80-008589 | D75: 鲲泰服务器维保服务：金牌+服务包-2U-3年, 7×24×4H | E75: 1 | F75: 1 | G75: 80-008589
A76: 基础物料 | B76: 整机安装服务（中国大陆） | C76: 80-008592 | D76: 鲲泰服务器基础硬件安装服务-2U | E76: 1 | F76: 1 | G76: 80-008592
A77: 小计
A79: 1 | B79: 305-000026 | C79: R522 | D79: KunTai R522 服务器
A80: 物料类别 | B80: 产品名称 | C80: 料号 | D80: 描述 | E80: 单套数量 | F80: 总数量
A81: 基础物料 | B81: 服务器机箱 | C81: 302-001690 | D81: 机箱 12*3.5硬盘EXP 2U2P-无RAID SAS线1620S | E81: 1 | F81: 2 | G81: 88-000288
A82: 基础物料 | B82: 2.6G常规主板 | C82: 302-001363 | D82: S主板 S920S00-5220-AJ 2*(920,32C) 1711 | E82: 1 | F82: 2 | G82: 99-000708
A83: 基础物料 | B83: 内存 | C83: 302-001644 | D83: S内存DDR4-32GB-3200-2Rank(2G*4bit) HLS | E83: 2 | F83: 4 | G83: 99-001627
A84: 基础物料 | B84: Riser卡 | C84: 302-000147 | D84: 3*16X SLOT (PCIE X8) Riser1&2 模组 | E84: 1 | F84: 2 | G84: 99-000147
A85: 基础物料 | B85: SATA SSD | C85: 302-001354 | D85: SSD ES3521A V6读取-1.92T-SATA 2.5及托 | E85: 1 | F85: 2 | G85: 99-001354
A86: 基础物料 | B86: RAID标卡 | C86: 302-001582 | D86: 9440-8i RAID标卡-PCIE 3.0 X8 -no cache | E86: 1 | F86: 2 | G86: 99-000135
A87: 基础物料 | B87: RAID卡线缆 | C87: 302-000251 | D87: 高速电缆 Mini SAS HD Cable-0.85m | E87: 2 | F87: 4 | G87: 99-000251
A88: 基础物料 | B88: 灵活网卡 | C88: 302-002934 | D88: 灵活网卡-TM210 4*GE 接口卡 | E88: 1 | F88: 2 | G88: 99-000142
A89: 基础物料 | B89: 电源模块 | C89: 302-001170 | D89: 服务器白金900W 2.0 版本交流电源 | E89: 2 | F89: 4 | G89: 99-000448
A90: 基础物料 | B90: 外接电源线 | C90: 302-000247 | D90: S电源线墙插国标-PI直公-C13直母-250V10A-3.0m黑-交流 | E90: 2 | F90: 4 | G90: 99-000247
A91: 基础物料 | B91: 外接电源线 | C91: 302-000248 | D91: S电源线PDU国标-C14直公-C13直母-250V10A-1.5m黑-交流 | E91: 2 | F91: 4 | G91: 99-000248
A92: 基础物料 | B92: 滑轨 | C92: 302-000187 | D92: 2U静态滑轨套件 | E92: 1 | F92: 2 | G92: 302-000187 | H92: 剔除
A93: 基础物料 | B93: 网卡 | C93: 302-003373 | D93: 网卡-SP680-4*25G-SFP28-pcie4.0x16-无模 | E93: 1 | F93: 2 | G93: 302-003373
A94: 辅助料信息 | B94: 标签包装 | C94: 69-001309 | D94: KunTai R522 服务器标准标签包装 | E94: 1 | F94: 2 | G94: 69-001309 | H94: 剔除
A95: 辅助料信息 | B95: 常规固件 | C95: 68-000009 | D95: S920X00/X01/S00 2.6G BIOS 1711BMC CPLD | E95: 1 | F95: 2 | G95: 68-000009 | H95: 剔除
A96: 服务类信息 | B96: 鲲泰服务器维保服务 | C96: 80-008588 | D96: 鲲泰服务器维保服务：标准+服务包-2U-3年,7×24×ND | E96: 1 | F96: 2 | G96: 80-008588
A97: 基础物料 | B97: 整机安装服务（中国大陆） | C97: 80-008592 | D97: 鲲泰服务器基础硬件安装服务-2U | E97: 1 | F97: 2 | G97: 80-008592
A99: 1 | B99: 305-000028 | C99: R522 | D99: KunTai R522 服务器
A100: 物料类别 | B100: 产品名称 | C100: 料号 | D100: 描述 | E100: 单套数量 | F100: 总数量
A101: 基础物料 | B101: 服务器机箱 | C101: 302-001690 | D101: 机箱 12*3.5硬盘EXP 2U2P-无RAID SAS线1620S | E101: 1 | F101: 2 | G101: 88-000288
A102: 基础物料 | B102: 2.6G常规主板 | C102: 302-001363 | D102: S主板 S920S00-5220-AJ 2*(920,32C) 1711 | E102: 1 | F102: 2 | G102: 99-000708
A103: 基础物料 | B103: 内存 | C103: 302-001644 | D103: S内存DDR4-32GB-3200-2Rank(2G*4bit) HLS | E103: 2 | F103: 4 | G103: 99-001627
A104: 基础物料 | B104: Riser卡 | C104: 302-000147 | D104: 3*16X SLOT (PCIE X8) Riser1&2 模组 | E104: 1 | F104: 2 | G104: 99-000147
A105: 基础物料 | B105: SATA SSD | C105: 302-001354 | D105: SSD ES3521A V6读取-1.92T-SATA 2.5及托 | E105: 1 | F105: 2 | G105: 99-001354
A106: 基础物料 | B106: RAID标卡 | C106: 302-001582 | D106: 9440-8i RAID标卡-PCIE 3.0 X8 -no cache | E106: 1 | F106: 2 | G106: 99-000135
A107: 基础物料 | B107: RAID卡线缆 | C107: 302-000251 | D107: 高速电缆 Mini SAS HD Cable-0.85m | E107: 2 | F107: 4 | G107: 99-000251
A108: 基础物料 | B108: 灵活网卡 | C108: 302-002934 | D108: 灵活网卡-TM210 4*GE 接口卡 | E108: 1 | F108: 2 | G108: 99-000142
A109: 基础物料 | B109: 电源模块 | C109: 302-001170 | D109: 服务器白金900W 2.0 版本交流电源 | E109: 2 | F109: 4 | G109: 99-000448
A110: 基础物料 | B110: 外接电源线 | C110: 302-000247 | D110: S电源线墙插国标-PI直公-C13直母-250V10A-3.0m黑-交流 | E110: 2 | F110: 4 | G110: 99-000247
A111: 基础物料 | B111: 外接电源线 | C111: 302-000248 | D111: S电源线PDU国标-C14直公-C13直母-250V10A-1.5m黑-交流 | E111: 2 | F111: 4 | G111: 99-000248
A112: 基础物料 | B112: 滑轨 | C112: 302-000187 | D112: 2U静态滑轨套件 | E112: 1 | F112: 2 | G112: 302-000187 | H112: 剔除
A113: 基础物料 | B113: 网卡 | C113: 302-003373 | D113: 网卡-SP680-4*25G-SFP28-pcie4.0x16-无模 | E113: 1 | F113: 2 | G113: 302-003373
A114: 辅助料信息 | B114: 标签包装 | C114: 69-001309 | D114: KunTai R522 服务器标准标签包装 | E114: 1 | F114: 2 | G114: 69-001309 | H114: 剔除
...

Sheet Sheet2
A1: 物料类别 | B1: 产品名称 | C1: 料号 | D1: 描述 | E1: 单套数量 | F1: 总数量
A2: 基础物料 | B2: 服务器机箱 | C2: 302-001687 | D2: 机箱 25*2.5硬盘EXP 2U2P-无RAID SAS线1620S | E2: 1 | F2: 6
A3: 基础物料 | B3: 2.6G常规主板 | C3: 302-001363 | D3: S主板 S920S00-5220-AJ 2*(920,32C) 1711 | E3: 1 | F3: 6
A4: 基础物料 | B4: 内存 | C4: 302-001862 | D4: S内存DDR4-64G-3200-2Rx4-RD HLS V1.0 | E4: 16 | F4: 96
A5: 基础物料 | B5: Riser卡 | C5: 302-000147 | D5: 3*16X SLOT (PCIE X8) Riser1&2 模组 | E5: 2 | F5: 12
A6: 基础物料 | B6: 后硬盘背板 | C6: 302-000146 | D6: 后置 PSU 4*2.5寸硬盘背板组件(仅支持NVME) | E6: 1 | F6: 6
A7: 基础物料 | B7: SATA SSD | C7: 302-001346 | D7: SSD ES3521AV6-480G-SATA-6G-2.5读取HW V1.0 | E7: 2 | F7: 12
A8: 基础物料 | B8: SAS HDD | C8: 302-001056 | D8: S硬盘2.4T-2.5SAS-12G10K-256M-XJ V1.0 | E8: 10 | F8: 60
A9: 基础物料 | B9: NVMe SSD | C9: 302-003066 | D9: NVMeSSD UH831a-1.6TB-PCIe4-2.5读写YL-K | E9: 2 | F9: 12
A10: 基础物料 | B10: RAID标卡 | C10: 302-001332 | D10: RAID标卡-2GB 9460-8i-PCIe | E10: 1 | F10: 6
A11: 基础物料 | B11: 超级电容 | C11: 302-001655 | D11: 3508/3516 RAID卡超级电容 | E11: 1 | F11: 6
A12: 基础物料 | B12: RAID卡线缆 | C12: 302-000251 | D12: 高速电缆 Mini SAS HD Cable-0.85m | E12: 2 | F12: 12
A13: 基础物料 | B13: 灵活网卡 | C13: 302-002934 | D13: 灵活网卡-TM210 4*GE 接口卡 | E13: 1 | F13: 6
... A23: 基础物料 | B23: 整机安装服务（中国大陆） | C23: 80-008592 | D23: 鲲泰服务器基础硬件安装服务-2U | E23: 1 | F23: 6
A24: 小计 | G24: 数量
A26: 2 | B26: 305-000026 | C26: R522 | D26: 8T容量服务器 | G26: Config：
A27: 物料类别 | B27: 产品名称 | C27: 料号 | D27: 描述 | E27: 单套数量 | F27: 总数量
A28: 基础物料 | B28: 服务器机箱 | C28: 302-001687 | D28: 机箱 25*2.5硬盘EXP 2U2P-无RAID SAS线1620S | E28: 1 | F28: 1
A29: 基础物料 | B29: 2.6G常规主板 | C29: 302-001363 | D29: S主板 S920S00-5220-AJ 2*(920,32C) 1711 | E29: 1 | F29: 1
A30: 基础物料 | B30: 内存 | C30: 302-001644 | D30: S内存DDR4-32GB-3200-2Rank(2G*4bit) HLS | E30: 4 | F30: 4
A31: 基础物料 | B31: Riser卡 | C31: 302-000147 | D31: 3*16X SLOT (PCIE X8) Riser1&2 模组 | E31: 2 | F31: 2
A32: 基础物料 | B32: 后硬盘背板 | C32: 302-000146 | D32: 后置 PSU 4*2.5寸硬盘背板组件(仅支持NVME) | E32: 1 | F32: 1
A33: 基础物料 | B33: SAS HDD | C33: 302-000637 | D33: S硬盘600G-2.5SAS-12G10K-256M-XJ V1.0 | E33: 3 | F33: 3
A34: 基础物料 | B34: NVMe SSD | C34: 302-003065 | D34: NVMeSSD UH811a-3.84TB-PCIe4-2.5读取YL-K | E34: 3 | F34: 3
A35: 基础物料 | B35: RAID标卡 | C35: 302-001332 | D35: RAID标卡-2GB 9460-8i-PCIe | E35: 1 | F35: 1
A36: 基础物料 | B36: 超级电容 | C36: 302-001655 | D36: 3508/3516 RAID卡超级电容 | E36: 1 | F36: 1
A37: 基础物料 | B37: RAID卡线缆 | C37: 302-000251 | D37: 高速电缆 Mini SAS HD Cable-0.85m | E37: 2 | F37: 2
A38: 基础物料 | B38: 灵活网卡 | C38: 302-002934 | D38: 灵活网卡-TM210 4*GE 接口卡 | E38: 1 | F38: 1
A39: 基础物料 | B39: 电源模块 | C39: 302-001170 | D39: 服务器白金900W 2.0 版本交流电源 | E39: 2 | F39: 2
... A48: 基础物料 | B48: 整机安装服务（中国大陆） | C48: 80-008592 | D48: 鲲泰服务器基础硬件安装服务-2U | E48: 1 | F48: 1
A49: 小计 | G49: 数量
A51: 3 | B51: 305-000026 | C51: R522 | D51: 14T容量服务器 | G51: Config：
A52: 物料类别 | B52: 产品名称 | C52: 料号 | D52: 描述 | E52: 单套数量 | F52: 总数量
A53: 基础物料 | B53: 服务器机箱 | C53: 302-001687 | D53: 机箱 25*2.5硬盘EXP 2U2P-无RAID SAS线1620S | E53: 1 | F53: 1
A54: 基础物料 | B54: 2.6G常规主板 | C54: 302-001363 | D54: S主板 S920S00-5220-AJ 2*(920,32C) 1711 | E54: 1 | F54: 1
A55: 基础物料 | B55: 内存 | C55: 302-001644 | D55: S内存DDR4-32GB-3200-2Rank(2G*4bit) HLS | E55: 4 | F55: 4
A56: 基础物料 | B56: Riser卡 | C56: 302-000147 | D56: 3*16X SLOT (PCIE X8) Riser1&2 模组 | E56: 2 | F56: 2
A57: 基础物料 | B57: 后硬盘背板 | C57: 302-000146 | D57: 后置 PSU 4*2.5寸硬盘背板组件(仅支持NVME) | E57: 1 | F57: 1
A58: 基础物料 | B58: SAS HDD | C58: 302-000637 | D58: S硬盘600G-2.5SAS-12G10K-256M-XJ V1.0 | E58: 3 | F58: 3
A59: 基础物料 | B59: NVMe SSD | C59: 302-003065 | D59: NVMeSSD UH811a-3.84TB-PCIe4-2.5读取YL-K | E59: 4 | F59: 4
A60: 基础物料 | B60: RAID标卡 | C60: 302-001332 | D60: RAID标卡-2GB 9460-8i-PCIe | E60: 1 | F60: 1
A61: 基础物料 | B61: 超级电容 | C61: 302-001655 | D61: 3508/3516 RAID卡超级电容 | E61: 1 | F61: 1
A62: 基础物料 | B62: RAID卡线缆 | C62: 302-000251 | D62: 高速电缆 Mini SAS HD Cable-0.85m | E62: 2 | F62: 2
A63: 基础物料 | B63: 灵活网卡 | C63: 302-002934 | D63: 灵活网卡-TM210 4*GE 接口卡 | E63: 1 | F63: 1
A64: 基础物料 | B64: 电源模块 | C64: 302-001170 | D64: 服务器白金900W 2.0 版本交流电源 | E64: 2 | F64: 2
... A73: 基础物料 | B73: 整机安装服务（中国大陆） | C73: 80-008592 | D73: 鲲泰服务器基础硬件安装服务-2U | E73: 1 | F73: 1
A74: 小计 | G74: 数量
